Workbook

Sheet LMC
A1: Prearmados | B1: Faltan Precios | C1: Falta Estructura | D1: Productos en 0 | E1: Estructuras Comunes
B2: =IFERROR(__xludf.DUMMYFUNCTION("sort(filter(Prearmados!$E:$E,Prearmados!$I:$I=B1),filter(Prearmados!$J:$J,Prearmados!$I:$I=B1),1)"),"#N/A") -> #N/A | C2: =IFERROR(__xludf.DUMMYFUNCTION("unique(filter(Prearmados!$E:$E,Prearmados!$I:$I=C1))"),"Tanque Combustible 3000 lts Plastico") -> Tanque Combustible 3000 lts Plastico | D2: =IFERROR(__xludf.DUMMYFUNCTION("unique(filter(Precio_Productos!B3:B17,Precio_Productos!E3:E17=0))"),"#N/A") -> #N/A | E2: =IFERROR(__xludf.DUMMYFUNCTION("unique(filter(Estructuras!F:F,Estructuras!C:C=Precio_Productos!A18))"),"Tanque Combinado 3000 lts C/Taller") -> Tanque Combinado 3000 lts C/Taller
C3: =IFERROR(__xludf.DUMMYFUNCTION("""COMPUTED_VALUE"""),"Tanque Combustible 3500 lts Plastico") -> Tanque Combustible 3500 lts Plastico | E3: =IFERROR(__xludf.DUMMYFUNCTION("""COMPUTED_VALUE"""),"Tanque Combinado 4000 lts C/Taller") -> Tanque Combinado 4000 lts C/Taller
C4: =IFERROR(__xludf.DUMMYFUNCTION("""COMPUTED_VALUE"""),"Tanque Combinado Plastico") -> Tanque Combinado Plastico
C5: =IFERROR(__xludf.DUMMYFUNCTION("""COMPUTED_VALUE"""),"Tanque 8000 lts") -> Tanque 8000 lts
C6: =IFERROR(__xludf.DUMMYFUNCTION("""COMPUTED_VALUE"""),"Elevador Frontal M1001 Reforzado") -> Elevador Frontal M1001 Reforzado
C7: =IFERROR(__xludf.DUMMYFUNCTION("""COMPUTED_VALUE"""),"Elevador Frontal C/Paralelogramo M1002 Reforzado") -> Elevador Frontal C/Paralelogramo M1002 Reforzado
C8: =IFERROR(__xludf.DUMMYFUNCTION("""COMPUTED_VALUE"""),"Desmalezadora de Arrastre 2,00") -> Desmalezadora de Arrastre 2,00

Sheet Validaciones Cotizador
A1: Implemento | B1: Ordenes | C1: Indice | D1: Cantidad | E1: Superpocisión | F1: Dejar Vacío | G1: Seleccionado | I1: Variable | J1: Dimension | L1: Implemento | M1: ID_Filtro | N1: Orden | O1: Indice | P1: Unidad | Q1: Código | R1: Cant | S1: Check_Comp | T1: Check_Prop | U1: Descripcion | V1: 1 | W1: Minimo | X1: Máximo | Y1: 2 | Z1: Minimo | AA1: Máximo | AB1: 3 | AC1: Minimo | AD1: Máximo
A2: {=IF(COUNTIF(A$1:A1,Cotizador!F$2)=maxifs(Familias!E:E,Familias!D:D,Cotizador!F$2),IF(COUNTIF(A$1:A1,XLOOKUP(Cotizador!F$2,Implementos!B:B,Implementos!C:C,"",0,1))=SUMIFS(Implementos!D:D,Implementos!B:B,Cotizador!F$2,Implementos!C:C,XLOOKUP(Cotizador!F$2,Implementos!B:B,Implementos!C:C,"",0,1)),"",XLOOKUP(Cotizador!F$2,Implementos!B:B,Implementos!C:C,"",0,1)),Cotizador!F$2)} -> Acoplados Rurales | B2: =IF(A2="","",COUNTIF(A$1:A2,A2)) -> 1 | C2: {=IF(B2="","",IF(A2=XLOOKUP(A$2,Implementos!B:B,Implementos!C:C,"",0,1),B2+maxifs(B$1:B1,A$1:A1,A$2),B2))} -> 1 | D2: =IF(B2="","", COUNTIFS(Productos!F:F,A2,Productos!H:H,B2)+IF(F2="SI",0,1)) -> 28 | E2: =IFERROR(__xludf.DUMMYFUNCTION("IF($B2="""","""",INDEX(filter(Familias!F:F,Familias!$D:$D=$A2,Familias!$E:$E=$B2),1))"),"Y") -> Y | F2: =IFERROR(__xludf.DUMMYFUNCTION("IF($B2="""","""",INDEX(filter(Familias!G:G,Familias!$D:$D=$A2,Familias!$E:$E=$B2),1))"),"NO") -> NO | G2: {=IF(C2=1,XLOOKUP(C2,Cotizador!D:D,Cotizador!E:E,"",0,1),"")} -> 56 | I2: =IFERROR(__xludf.DUMMYFUNCTION("TRANSPOSE(filter(Cotizador!I1:V1,Cotizador!I2:V2>0))"),"Capacidad") -> Capacidad | J2: =IF(I2="","",SUMIF(Cotizador!I$1:V$1,I2,Cotizador!I$2:V$2)) -> 5575 | L2: {=IF(COUNTIF(L$1:L1,A$2)=SUMIF(A:A,A$2,D:D),IF(COUNTIF(L$1:L1,XLOOKUP(A$2,Implementos!B:B,Implementos!C:C,"",0,1))=SUMIF(A:A,XLOOKUP(A$2,Implementos!B:B,Implementos!C:C,"",0,1),D:D),"",XLOOKUP(A$2,Implementos!B:B,Implementos!C:C,"",0,1)),A$2)} -> Acoplados Rurales | M2: =IF(L2="","",max(M$1:M1)+1) -> 1 | N2: =IF(L2="","",IF(N1="Orden",1,IF(COUNTIFS(N$1:N1,N1,L$1:L1,L2)=SUMIFS(D:D,B:B,N1,A:A,L2),IF(N1=maxifs(B:B,A:A,L2),"",maxifs(N$1:N1,L$1:L1,L2)+1),N1))) -> 1 | O2: =IF(N2="","",SUMIFS(C:C,B:B,N2,A:A,L2)) -> 1 | P2: =IF(N2="","",COUNTIFS(N$1:N2,N2,L$1:L2,L2)) -> 1 | Q2: =IF(U2="","",SUMIF(Productos!E:E,U2,Productos!A:A)) -> 45 | R2: {=IF(L2="","", max(1,SUMIF(I:I,XLOOKUP(U2,Productos!E:E,Productos!G:G,"",0,1),J:J)))} -> 1 | S2: =IF(Q2="","",IF(SUMIFS(Compat_Vetado!D:D,Compat_Vetado!B:B,SUM(G:G),Compat_Vetado!C:C,Q2)=1,"SI",IF(OR(SUMIF(Cotizador!E:E,Q2,Cotizador!G:G)>0,SUMIFS(Compat_Vetado!D:D,Compat_Vetado!B:B,SUM(G:G),Compat_Vetado!C:C,Q2)=-1),"NO",""))) | T2: =IF(Q2="","",IF(S2="SI","x",IF(S2="NO","",IF(AND(OR(V2="",AND(W2<=SUMIF(I:I,V2,J:J),SUMIF(I:I,V2,J:J)<=X2)),OR(Y2="",AND(Z2<=SUMIF(I:I,Y2,J:J),SUMIF(I:I,Y2,J:J)<=AA2)),OR(AB2="",AND(AC2<=SUMIF(I:I,AB2,J:J),SUMIF(I:I,AB2,J:J)<=AD2))),"x","")))) -> x | U2: =IFERROR(__xludf.DUMMYFUNCTION("IF(P2="""","""",IFERROR(INDEX(filter(Productos!E:E,Productos!F:F=L2,Productos!H:H=N2),P2),IF(M2=SUM(D:D),""Finalizar"",""-"")))"),"Tanque Combustible 1100 lts Bajo") -> Tanque Combustible 1100 lts Bajo | V2: =IFERROR(__xludf.DUMMYFUNCTION("IF(OR($U2="""",COUNTIF($I:$I,IFERROR(unique(filter(Prod_Prop!$H:$H,Prod_Prop!$G:$G=$U2,Prod_Prop!$E:$E=V$1)),""Check""))=0),"""",IFERROR(unique(filter(Prod_Prop!$H:$H,Prod_Prop!$G:$G=$U2,Prod_Prop!$E:$E=V$1)),""""))"),"") | W2: =IF(V2="","",SUMIFS(Prod_Prop!$J:$J,Prod_Prop!$B:$B,$Q2,Prod_Prop!$H:$H,V2,Prod_Prop!$I:$I,W$1)*IF(V2="Peso",$R2,1)) | X2: =IF(V2="","",SUMIFS(Prod_Prop!$J:$J,Prod_Prop!$B:$B,$Q2,Prod_Prop!$H:$H,V2,Prod_Prop!$I:$I,X$1)*IF(V2="Peso",$R2,1)) | Y2: =IFERROR(__xludf.DUMMYFUNCTION("IF(OR($U2="""",COUNTIF($I:$I,IFERROR(unique(filter(Prod_Prop!$H:$H,Prod_Prop!$G:$G=$U2,Prod_Prop!$E:$E=Y$1)),""Check""))=0),"""",IFERROR(unique(filter(Prod_Prop!$H:$H,Prod_Prop!$G:$G=$U2,Prod_Prop!$E:$E=Y$1)),""""))"),"") | Z2: =IF(Y2="","",SUMIFS(Prod_Prop!$J:$J,Prod_Prop!$B:$B,$Q2,Prod_Prop!$H:$H,Y2,Prod_Prop!$I:$I,Z$1)*IF(Y2="Peso",$R2,1)) | AA2: =IF(Y2="","",SUMIFS(Prod_Prop!$J:$J,Prod_Prop!$B:$B,$Q2,Prod_Prop!$H:$H,Y2,Prod_Prop!$I:$I,AA$1)*IF(Y2="Peso",$R2,1)) | AB2: =IFERROR(__xludf.DUMMYFUNCTION("IF(OR($U2="""",COUNTIF($I:$I,IFERROR(unique(filter(Prod_Prop!$H:$H,Prod_Prop!$G:$G=$U2,Prod_Prop!$E:$E=AB$1)),""Check""))=0),"""",IFERROR(unique(filter(Prod_Prop!$H:$H,Prod_Prop!$G:$G=$U2,Prod_Prop!$E:$E=AB$1)),""""))"),"") | AC2: =IF(AB2="","",SUMIFS(Prod_Prop!$J:$J,Prod_Prop!$B:$B,$Q2,Prod_Prop!$H:$H,AB2,Prod_Prop!$I:$I,AC$1)*IF(AB2="Peso",$R2,1)) | AD2: =IF(AB2="","",SUMIFS(Prod_Prop!$J:$J,Prod_Prop!$B:$B,$Q2,Prod_Prop!$H:$H,AB2,Prod_Prop!$I:$I,AD$1)*IF(AB2="Peso",$R2,1))
A3: {=IF(COUNTIF(A$1:A2,Cotizador!F$2)=maxifs(Familias!E:E,Familias!D:D,Cotizador!F$2),IF(COUNTIF(A$1:A2,XLOOKUP(Cotizador!F$2,Implementos!B:B,Implementos!C:C,"",0,1))=SUMIFS(Implementos!D:D,Implementos!B:B,Cotizador!F$2,Implementos!C:C,XLOOKUP(Cotizador!F$2,Implementos!B:B,Implementos!C:C,"",0,1)),"",XLOOKUP(Cotizador!F$2,Implementos!B:B,Implementos!C:C,"",0,1)),Cotizador!F$2)} -> Acoplados Rurales | B3: =IF(A3="","",COUNTIF(A$1:A3,A3)) -> 2 | C3: {=IF(B3="","",IF(A3=XLOOKUP(A$2,Implementos!B:B,Implementos!C:C,"",0,1),B3+maxifs(B$1:B2,A$1:A2,A$2),B3))} -> 2 | D3: =IF(B3="","", COUNTIFS(Productos!F:F,A3,Productos!H:H,B3)+IF(F3="SI",0,1)) -> 11 | E3: =IFERROR(__xludf.DUMMYFUNCTION("IF($B3="""","""",INDEX(filter(Familias!F:F,Familias!$D:$D=$A3,Familias!$E:$E=$B3),1))"),"Y") -> Y | F3: =IFERROR(__xludf.DUMMYFUNCTION("IF($B3="""","""",INDEX(filter(Familias!G:G,Familias!$D:$D=$A3,Familias!$E:$E=$B3),1))"),"NO") -> NO | G3: {=IF(C3=1,XLOOKUP(C3,Cotizador!D:D,Cotizador!E:E,"",0,1),"")} | I3: =IFERROR(__xludf.DUMMYFUNCTION("""COMPUTED_VALUE"""),"Peso") -> Peso | J3: =IF(I3="","",SUMIF(Cotizador!I$1:V$1,I3,Cotizador!I$2:V$2)) -> 4841.25 | L3: {=IF(COUNTIF(L$1:L2,A$2)=SUMIF(A:A,A$2,D:D),IF(COUNTIF(L$1:L2,XLOOKUP(A$2,Implementos!B:B,Implementos!C:C,"",0,1))=SUMIF(A:A,XLOOKUP(A$2,Implementos!B:B,Implementos!C:C,"",0,1),D:D),"",XLOOKUP(A$2,Implementos!B:B,Implementos!C:C,"",0,1)),A$2)} -> Acoplados Rurales | M3: =IF(L3="","",max(M$1:M2)+1) -> 2 | N3: =IF(L3="","",IF(N2="Orden",1,IF(COUNTIFS(N$1:N2,N2,L$1:L2,L3)=SUMIFS(D:D,B:B,N2,A:A,L3),IF(N2=maxifs(B:B,A:A,L3),"",maxifs(N$1:N2,L$1:L2,L3)+1),N2))) -> 1 | O3: =IF(N3="","",SUMIFS(C:C,B:B,N3,A:A,L3)) -> 1 | P3: =IF(N3="","",COUNTIFS(N$1:N3,N3,L$1:L3,L3)) -> 2 | Q3: =IF(U3="","",SUMIF(Productos!E:E,U3,Productos!A:A)) -> 46 | R3: {=IF(L3="","", max(1,SUMIF(I:I,XLOOKUP(U3,Productos!E:E,Productos!G:G,"",0,1),J:J)))} -> 1 | S3: =IF(Q3="","",IF(SUMIFS(Compat_Vetado!D:D,Compat_Vetado!B:B,SUM(G:G),Compat_Vetado!C:C,Q3)=1,"SI",IF(OR(SUMIF(Cotizador!E:E,Q3,Cotizador!G:G)>0,SUMIFS(Compat_Vetado!D:D,Compat_Vetado!B:B,SUM(G:G),Compat_Vetado!C:C,Q3)=-1),"NO",""))) | T3: =IF(Q3="","",IF(S3="SI","x",IF(S3="NO","",IF(AND(OR(V3="",AND(W3<=SUMIF(I:I,V3,J:J),SUMIF(I:I,V3,J:J)<=X3)),OR(Y3="",AND(Z3<=SUMIF(I:I,Y3,J:J),SUMIF(I:I,Y3,J:J)<=AA3)),OR(AB3="",AND(AC3<=SUMIF(I:I,AB3,J:J),SUMIF(I:I,AB3,J:J)<=AD3))),"x","")))) -> x | U3: =IFERROR(__xludf.DUMMYFUNCTION("IF(P3="""","""",IFERROR(INDEX(filter(Productos!E:E,Productos!F:F=L3,Productos!H:H=N3),P3),IF(M3=SUM(D:D),""Finalizar"",""-"")))"),"Tanque Combustible 1500 lts Standard") -> Tanque Combustible 1500 lts Standard | V3: =IFERROR(__xludf.DUMMYFUNCTION("IF(OR($U3="""",COUNTIF($I:$I,IFERROR(unique(filter(Prod_Prop!$H:$H,Prod_Prop!$G:$G=$U3,Prod_Prop!$E:$E=V$1)),""Check""))=0),"""",IFERROR(unique(filter(Prod_Prop!$H:$H,Prod_Prop!$G:$G=$U3,Prod_Prop!$E:$E=V$1)),""""))"),"") | W3: =IF(V3="","",SUMIFS(Prod_Prop!$J:$J,Prod_Prop!$B:$B,$Q3,Prod_Prop!$H:$H,V3,Prod_Prop!$I:$I,W$1)*IF(V3="Peso",$R3,1)) | X3: =IF(V3="","",SUMIFS(Prod_Prop!$J:$J,Prod_Prop!$B:$B,$Q3,Prod_Prop!$H:$H,V3,Prod_Prop!$I:$I,X$1)*IF(V3="Peso",$R3,1)) | Y3: =IFERROR(__xludf.DUMMYFUNCTION("IF(OR($U3="""",COUNTIF($I:$I,IFERROR(unique(filter(Prod_Prop!$H:$H,Prod_Prop!$G:$G=$U3,Prod_Prop!$E:$E=Y$1)),""Check""))=0),"""",IFERROR(unique(filter(Prod_Prop!$H:$H,Prod_Prop!$G:$G=$U3,Prod_Prop!$E:$E=Y$1)),""""))"),"") | Z3: =IF(Y3="","",SUMIFS(Prod_Prop!$J:$J,Prod_Prop!$B:$B,$Q3,Prod_Prop!$H:$H,Y3,Prod_Prop!$I:$I,Z$1)*IF(Y3="Peso",$R3,1)) | AA3: =IF(Y3="","",SUMIFS(Prod_Prop!$J:$J,Prod_Prop!$B:$B,$Q3,Prod_Prop!$H:$H,Y3,Prod_Prop!$I:$I,AA$1)*IF(Y3="Peso",$R3,1)) | AB3: =IFERROR(__xludf.DUMMYFUNCTION("IF(OR($U3="""",COUNTIF($I:$I,IFERROR(unique(filter(Prod_Prop!$H:$H,Prod_Prop!$G:$G=$U3,Prod_Prop!$E:$E=AB$1)),""Check""))=0),"""",IFERROR(unique(filter(Prod_Prop!$H:$H,Prod_Prop!$G:$G=$U3,Prod_Prop!$E:$E=AB$1)),""""))"),"") | AC3: =IF(AB3="","",SUMIFS(Prod_Prop!$J:$J,Prod_Prop!$B:$B,$Q3,Prod_Prop!$H:$H,AB3,Prod_Prop!$I:$I,AC$1)*IF(AB3="Peso",$R3,1)) | AD3: =IF(AB3="","",SUMIFS(Prod_Prop!$J:$J,Prod_Prop!$B:$B,$Q3,Prod_Prop!$H:$H,AB3,Prod_Prop!$I:$I,AD$1)*IF(AB3="Peso",$R3,1))
A4: {=IF(COUNTIF(A$1:A3,Cotizador!F$2)=maxifs(Familias!E:E,Familias!D:D,Cotizador!F$2),IF(COUNTIF(A$1:A3,XLOOKUP(Cotizador!F$2,Implementos!B:B,Implementos!C:C,"",0,1))=SUMIFS(Implementos!D:D,Implementos!B:B,Cotizador!F$2,Implementos!C:C,XLOOKUP(Cotizador!F$2,Implementos!B:B,Implementos!C:C,"",0,1)),"",XLOOKUP(Cotizador!F$2,Implementos!B:B,Implementos!C:C,"",0,1)),Cotizador!F$2)} -> Acoplados Rurales | B4: =IF(A4="","",COUNTIF(A$1:A4,A4)) -> 3 | C4: {=IF(B4="","",IF(A4=XLOOKUP(A$2,Implementos!B:B,Implementos!C:C,"",0,1),B4+maxifs(B$1:B3,A$1:A3,A$2),B4))} -> 3 | D4: =IF(B4="","", COUNTIFS(Productos!F:F,A4,Productos!H:H,B4)+IF(F4="SI",0,1)) -> 21 | E4: =IFERROR(__xludf.DUMMYFUNCTION("IF($B4="""","""",INDEX(filter(Familias!F:F,Familias!$D:$D=$A4,Familias!$E:$E=$B4),1))"),"O") -> O | F4: =IFERROR(__xludf.DUMMYFUNCTION("IF($B4="""","""",INDEX(filter(Familias!G:G,Familias!$D:$D=$A4,Familias!$E:$E=$B4),1))"),"SI") -> SI | G4: {=IF(C4=1,XLOOKUP(C4,Cotizador!D:D,Cotizador!E:E,"",0,1),"")} | I4: =IFERROR(__xludf.DUMMYFUNCTION("""COMPUTED_VALUE"""),"Longitud") -> Longitud | J4: =IF(I4="","",SUMIF(Cotizador!I$1:V$1,I4,Cotizador!I$2:V$2)) -> 4.95 | L4: {=IF(COUNTIF(L$1:L3,A$2)=SUMIF(A:A,A$2,D:D),IF(COUNTIF(L$1:L3,XLOOKUP(A$2,Implementos!B:B,Implementos!C:C,"",0,1))=SUMIF(A:A,XLOOKUP(A$2,Implementos!B:B,Implementos!C:C,"",0,1),D:D),"",XLOOKUP(A$2,Implementos!B:B,Implementos!C:C,"",0,1)),A$2)} -> Acoplados Rurales | M4: =IF(L4="","",max(M$1:M3)+1) -> 3 | N4: =IF(L4="","",IF(N3="Orden",1,IF(COUNTIFS(N$1:N3,N3,L$1:L3,L4)=SUMIFS(D:D,B:B,N3,A:A,L4),IF(N3=maxifs(B:B,A:A,L4),"",maxifs(N$1:N3,L$1:L3,L4)+1),N3))) -> 1 | O4: =IF(N4="","",SUMIFS(C:C,B:B,N4,A:A,L4)) -> 1 | P4: =IF(N4="","",COUNTIFS(N$1:N4,N4,L$1:L4,L4)) -> 3 | Q4: =IF(U4="","",SUMIF(Productos!E:E,U4,Productos!A:A)) -> 47 | R4: {=IF(L4="","", max(1,SUMIF(I:I,XLOOKUP(U4,Productos!E:E,Productos!G:G,"",0,1),J:J)))} -> 1 | S4: =IF(Q4="","",IF(SUMIFS(Compat_Vetado!D:D,Compat_Vetado!B:B,SUM(G:G),Compat_Vetado!C:C,Q4)=1,"SI",IF(OR(SUMIF(Cotizador!E:E,Q4,Cotizador!G:G)>0,SUMIFS(Compat_Vetado!D:D,Compat_Vetado!B:B,SUM(G:G),Compat_Vetado!C:C,Q4)=-1),"NO",""))) | T4: =IF(Q4="","",IF(S4="SI","x",IF(S4="NO","",IF(AND(OR(V4="",AND(W4<=SUMIF(I:I,V4,J:J),SUMIF(I:I,V4,J:J)<=X4)),OR(Y4="",AND(Z4<=SUMIF(I:I,Y4,J:J),SUMIF(I:I,Y4,J:J)<=AA4)),OR(AB4="",AND(AC4<=SUMIF(I:I,AB4,J:J),SUMIF(I:I,AB4,J:J)<=AD4))),"x","")))) -> x | U4: =IFERROR(__xludf.DUMMYFUNCTION("IF(P4="""","""",IFERROR(INDEX(filter(Productos!E:E,Productos!F:F=L4,Productos!H:H=N4),P4),IF(M4=SUM(D:D),""Finalizar"",""-"")))"),"Tanque Combustible 1800 lts Standard") -> Tanque Combustible 1800 lts Standard | V4: =IFERROR(__xludf.DUMMYFUNCTION("IF(OR($U4="""",COUNTIF($I:$I,IFERROR(unique(filter(Prod_Prop!$H:$H,Prod_Prop!$G:$G=$U4,Prod_Prop!$E:$E=V$1)),""Check""))=0),"""",IFERROR(unique(filter(Prod_Prop!$H:$H,Prod_Prop!$G:$G=$U4,Prod_Prop!$E:$E=V$1)),""""))"),"") | W4: =IF(V4="","",SUMIFS(Prod_Prop!$J:$J,Prod_Prop!$B:$B,$Q4,Prod_Prop!$H:$H,V4,Prod_Prop!$I:$I,W$1)*IF(V4="Peso",$R4,1)) | X4: =IF(V4="","",SUMIFS(Prod_Prop!$J:$J,Prod_Prop!$B:$B,$Q4,Prod_Prop!$H:$H,V4,Prod_Prop!$I:$I,X$1)*IF(V4="Peso",$R4,1)) | Y4: =IFERROR(__xludf.DUMMYFUNCTION("IF(OR($U4="""",COUNTIF($I:$I,IFERROR(unique(filter(Prod_Prop!$H:$H,Prod_Prop!$G:$G=$U4,Prod_Prop!$E:$E=Y$1)),""Check""))=0),"""",IFERROR(unique(filter(Prod_Prop!$H:$H,Prod_Prop!$G:$G=$U4,Prod_Prop!$E:$E=Y$1)),""""))"),"") | Z4: =IF(Y4="","",SUMIFS(Prod_Prop!$J:$J,Prod_Prop!$B:$B,$Q4,Prod_Prop!$H:$H,Y4,Prod_Prop!$I:$I,Z$1)*IF(Y4="Peso",$R4,1)) | AA4: =IF(Y4="","",SUMIFS(Prod_Prop!$J:$J,Prod_Prop!$B:$B,$Q4,Prod_Prop!$H:$H,Y4,Prod_Prop!$I:$I,AA$1)*IF(Y4="Peso",$R4,1)) | AB4: =IFERROR(__xludf.DUMMYFUNCTION("IF(OR($U4="""",COUNTIF($I:$I,IFERROR(unique(filter(Prod_Prop!$H:$H,Prod_Prop!$G:$G=$U4,Prod_Prop!$E:$E=AB$1)),""Check""))=0),"""",IFERROR(unique(filter(Prod_Prop!$H:$H,Prod_Prop!$G:$G=$U4,Prod_Prop!$E:$E=AB$1)),""""))"),"") | AC4: =IF(AB4="","",SUMIFS(Prod_Prop!$J:$J,Prod_Prop!$B:$B,$Q4,Prod_Prop!$H:$H,AB4,Prod_Prop!$I:$I,AC$1)*IF(AB4="Peso",$R4,1)) | AD4: =IF(AB4="","",SUMIFS(Prod_Prop!$J:$J,Prod_Prop!$B:$B,$Q4,Prod_Prop!$H:$H,AB4,Prod_Prop!$I:$I,AD$1)*IF(AB4="Peso",$R4,1))
A5: {=IF(COUNTIF(A$1:A4,Cotizador!F$2)=maxifs(Familias!E:E,Familias!D:D,Cotizador!F$2),IF(COUNTIF(A$1:A4,XLOOKUP(Cotizador!F$2,Implementos!B:B,Implementos!C:C,"",0,1))=SUMIFS(Implementos!D:D,Implementos!B:B,Cotizador!F$2,Implementos!C:C,XLOOKUP(Cotizador!F$2,Implementos!B:B,Implementos!C:C,"",0,1)),"",XLOOKUP(Cotizador!F$2,Implementos!B:B,Implementos!C:C,"",0,1)),Cotizador!F$2)} -> Acoplados Rurales | B5: =IF(A5="","",COUNTIF(A$1:A5,A5)) -> 4 | C5: {=IF(B5="","",IF(A5=XLOOKUP(A$2,Implementos!B:B,Implementos!C:C,"",0,1),B5+maxifs(B$1:B4,A$1:A4,A$2),B5))} -> 4 | D5: =IF(B5="","", COUNTIFS(Productos!F:F,A5,Productos!H:H,B5)+IF(F5="SI",0,1)) -> 7 | E5: =IFERROR(__xludf.DUMMYFUNCTION("IF($B5="""","""",INDEX(filter(Familias!F:F,Familias!$D:$D=$A5,Familias!$E:$E=$B5),1))"),"Y") -> Y | F5: =IFERROR(__xludf.DUMMYFUNCTION("IF($B5="""","""",INDEX(filter(Familias!G:G,Familias!$D:$D=$A5,Familias!$E:$E=$B5),1))"),"NO") -> NO | G5: {=IF(C5=1,XLOOKUP(C5,Cotizador!D:D,Cotizador!E:E,"",0,1),"")} | I5: =IFERROR(__xludf.DUMMYFUNCTION("""COMPUTED_VALUE"""),"Altura") -> Altura | J5: =IF(I5="","",SUMIF(Cotizador!I$1:V$1,I5,Cotizador!I$2:V$2)) -> 870 | L5: {=IF(COUNTIF(L$1:L4,A$2)=SUMIF(A:A,A$2,D:D),IF(COUNTIF(L$1:L4,XLOOKUP(A$2,Implementos!B:B,Implementos!C:C,"",0,1))=SUMIF(A:A,XLOOKUP(A$2,Implementos!B:B,Implementos!C:C,"",0,1),D:D),"",XLOOKUP(A$2,Implementos!B:B,Implementos!C:C,"",0,1)),A$2)} -> Acoplados Rurales | M5: =IF(L5="","",max(M$1:M4)+1) -> 4 | N5: =IF(L5="","",IF(N4="Orden",1,IF(COUNTIFS(N$1:N4,N4,L$1:L4,L5)=SUMIFS(D:D,B:B,N4,A:A,L5),IF(N4=maxifs(B:B,A:A,L5),"",maxifs(N$1:N4,L$1:L4,L5)+1),N4))) -> 1 | O5: =IF(N5="","",SUMIFS(C:C,B:B,N5,A:A,L5)) -> 1 | P5: =IF(N5="","",COUNTIFS(N$1:N5,N5,L$1:L5,L5)) -> 4 | Q5: =IF(U5="","",SUMIF(Productos!E:E,U5,Productos!A:A)) -> 48 | R5: {=IF(L5="","", max(1,SUMIF(I:I,XLOOKUP(U5,Productos!E:E,Productos!G:G,"",0,1),J:J)))} -> 1 | S5: =IF(Q5="","",IF(SUMIFS(Compat_Vetado!D:D,Compat_Vetado!B:B,SUM(G:G),Compat_Vetado!C:C,Q5)=1,"SI",IF(OR(SUMIF(Cotizador!E:E,Q5,Cotizador!G:G)>0,SUMIFS(Compat_Vetado!D:D,Compat_Vetado!B:B,SUM(G:G),Compat_Vetado!C:C,Q5)=-1),"NO",""))) | T5: =IF(Q5="","",IF(S5="SI","x",IF(S5="NO","",IF(AND(OR(V5="",AND(W5<=SUMIF(I:I,V5,J:J),SUMIF(I:I,V5,J:J)<=X5)),OR(Y5="",AND(Z5<=SUMIF(I:I,Y5,J:J),SUMIF(I:I,Y5,J:J)<=AA5)),OR(AB5="",AND(AC5<=SUMIF(I:I,AB5,J:J),SUMIF(I:I,AB5,J:J)<=AD5))),"x","")))) -> x | U5: =IFERROR(__xludf.DUMMYFUNCTION("IF(P5="""","""",IFERROR(INDEX(filter(Productos!E:E,Productos!F:F=L5,Productos!H:H=N5),P5),IF(M5=SUM(D:D),""Finalizar"",""-"")))"),"Tanque Combustible 2000 lts Bajo") -> Tanque Combustible 2000 lts Bajo | V5: =IFERROR(__xludf.DUMMYFUNCTION("IF(OR($U5="""",COUNTIF($I:$I,IFERROR(unique(filter(Prod_Prop!$H:$H,Prod_Prop!$G:$G=$U5,Prod_Prop!$E:$E=V$1)),""Check""))=0),"""",IFERROR(unique(filter(Prod_Prop!$H:$H,Prod_Prop!$G:$G=$U5,Prod_Prop!$E:$E=V$1)),""""))"),"") | W5: =IF(V5="","",SUMIFS(Prod_Prop!$J:$J,Prod_Prop!$B:$B,$Q5,Prod_Prop!$H:$H,V5,Prod_Prop!$I:$I,W$1)*IF(V5="Peso",$R5,1)) | X5: =IF(V5="","",SUMIFS(Prod_Prop!$J:$J,Prod_Prop!$B:$B,$Q5,Prod_Prop!$H:$H,V5,Prod_Prop!$I:$I,X$1)*IF(V5="Peso",$R5,1)) | Y5: =IFERROR(__xludf.DUMMYFUNCTION("IF(OR($U5="""",COUNTIF($I:$I,IFERROR(unique(filter(Prod_Prop!$H:$H,Prod_Prop!$G:$G=$U5,Prod_Prop!$E:$E=Y$1)),""Check""))=0),"""",IFERROR(unique(filter(Prod_Prop!$H:$H,Prod_Prop!$G:$G=$U5,Prod_Prop!$E:$E=Y$1)),""""))"),"") | Z5: =IF(Y5="","",SUMIFS(Prod_Prop!$J:$J,Prod_Prop!$B:$B,$Q5,Prod_Prop!$H:$H,Y5,Prod_Prop!$I:$I,Z$1)*IF(Y5="Peso",$R5,1)) | AA5: =IF(Y5="","",SUMIFS(Prod_Prop!$J:$J,Prod_Prop!$B:$B,$Q5,Prod_Prop!$H:$H,Y5,Prod_Prop!$I:$I,AA$1)*IF(Y5="Peso",$R5,1)) | AB5: =IFERROR(__xludf.DUMMYFUNCTION("IF(OR($U5="""",COUNTIF($I:$I,IFERROR(unique(filter(Prod_Prop!$H:$H,Prod_Prop!$G:$G=$U5,Prod_Prop!$E:$E=AB$1)),""Check""))=0),"""",IFERROR(unique(filter(Prod_Prop!$H:$H,Prod_Prop!$G:$G=$U5,Prod_Prop!$E:$E=AB$1)),""""))"),"") | AC5: =IF(AB5="","",SUMIFS(Prod_Prop!$J:$J,Prod_Prop!$B:$B,$Q5,Prod_Prop!$H:$H,AB5,Prod_Prop!$I:$I,AC$1)*IF(AB5="Peso",$R5,1)) | AD5: =IF(AB5="","",SUMIFS(Prod_Prop!$J:$J,Prod_Prop!$B:$B,$Q5,Prod_Prop!$H:$H,AB5,Prod_Prop!$I:$I,AD$1)*IF(AB5="Peso",$R5,1))
A6: {=IF(COUNTIF(A$1:A5,Cotizador!F$2)=maxifs(Familias!E:E,Familias!D:D,Cotizador!F$2),IF(COUNTIF(A$1:A5,XLOOKUP(Cotizador!F$2,Implementos!B:B,Implementos!C:C,"",0,1))=SUMIFS(Implementos!D:D,Implementos!B:B,Cotizador!F$2,Implementos!C:C,XLOOKUP(Cotizador!F$2,Implementos!B:B,Implementos!C:C,"",0,1)),"",XLOOKUP(Cotizador!F$2,Implementos!B:B,Implementos!C:C,"",0,1)),Cotizador!F$2)} -> Rodados | B6: =IF(A6="","",COUNTIF(A$1:A6,A6)) -> 1 | C6: {=IF(B6="","",IF(A6=XLOOKUP(A$2,Implementos!B:B,Implementos!C:C,"",0,1),B6+maxifs(B$1:B5,A$1:A5,A$2),B6))} -> 5 | D6: =IF(B6="","", COUNTIFS(Productos!F:F,A6,Productos!H:H,B6)+IF(F6="SI",0,1)) -> 8 | E6: =IFERROR(__xludf.DUMMYFUNCTION("IF($B6="""","""",INDEX(filter(Familias!F:F,Familias!$D:$D=$A6,Familias!$E:$E=$B6),1))"),"O") -> O | F6: =IFERROR(__xludf.DUMMYFUNCTION("IF($B6="""","""",INDEX(filter(Familias!G:G,Familias!$D:$D=$A6,Familias!$E:$E=$B6),1))"),"SI") -> SI | G6: {=IF(C6=1,XLOOKUP(C6,Cotizador!D:D,Cotizador!E:E,"",0,1),"")} | J6: =IF(I6="","",SUMIF(Cotizador!I$1:V$1,I6,Cotizador!I$2:V$2)) | L6: {=IF(COUNTIF(L$1:L5,A$2)=SUMIF(A:A,A$2,D:D),IF(COUNTIF(L$1:L5,XLOOKUP(A$2,Implementos!B:B,Implementos!C:C,"",0,1))=SUMIF(A:A,XLOOKUP(A$2,Implementos!B:B,Implementos!C:C,"",0,1),D:D),"",XLOOKUP(A$2,Implementos!B:B,Implementos!C:C,"",0,1)),A$2)} -> Acoplados Rurales | M6: =IF(L6="","",max(M$1:M5)+1) -> 5 | N6: =IF(L6="","",IF(N5="Orden",1,IF(COUNTIFS(N$1:N5,N5,L$1:L5,L6)=SUMIFS(D:D,B:B,N5,A:A,L6),IF(N5=maxifs(B:B,A:A,L6),"",maxifs(N$1:N5,L$1:L5,L6)+1),N5))) -> 1 | O6: =IF(N6="","",SUMIFS(C:C,B:B,N6,A:A,L6)) -> 1 | P6: =IF(N6="","",COUNTIFS(N$1:N6,N6,L$1:L6,L6)) -> 5 | Q6: =IF(U6="","",SUMIF(Productos!E:E,U6,Productos!A:A)) -> 49 | R6: {=IF(L6="","", max(1,SUMIF(I:I,XLOOKUP(U6,Productos!E:E,Productos!G:G,"",0,1),J:J)))} -> 1 | S6: =IF(Q6="","",IF(SUMIFS(Compat_Vetado!D:D,Compat_Vetado!B:B,SUM(G:G),Compat_Vetado!C:C,Q6)=1,"SI",IF(OR(SUMIF(Cotizador!E:E,Q6,Cotizador!G:G)>0,SUMIFS(Compat_Vetado!D:D,Compat_Vetado!B:B,SUM(G:G),Compat_Vetado!C:C,Q6)=-1),"NO",""))) | T6: =IF(Q6="","",IF(S6="SI","x",IF(S6="NO","",IF(AND(OR(V6="",AND(W6<=SUMIF(I:I,V6,J:J),SUMIF(I:I,V6,J:J)<=X6)),OR(Y6="",AND(Z6<=SUMIF(I:I,Y6,J:J),SUMIF(I:I,Y6,J:J)<=AA6)),OR(AB6="",AND(AC6<=SUMIF(I:I,AB6,J:J),SUMIF(I:I,AB6,J:J)<=AD6))),"x","")))) -> x | U6: =IFERROR(__xludf.DUMMYFUNCTION("IF(P6="""","""",IFERROR(INDEX(filter(Productos!E:E,Productos!F:F=L6,Productos!H:H=N6),P6),IF(M6=SUM(D:D),""Finalizar"",""-"")))"),"Tanque Combustible 2000 lts Standard") -> Tanque Combustible 2000 lts Standard | V6: =IFERROR(__xludf.DUMMYFUNCTION("IF(OR($U6="""",COUNTIF($I:$I,IFERROR(unique(filter(Prod_Prop!$H:$H,Prod_Prop!$G:$G=$U6,Prod_Prop!$E:$E=V$1)),""Check""))=0),"""",IFERROR(unique(filter(Prod_Prop!$H:$H,Prod_Prop!$G:$G=$U6,Prod_Prop!$E:$E=V$1)),""""))"),"") | W6: =IF(V6="","",SUMIFS(Prod_Prop!$J:$J,Prod_Prop!$B:$B,$Q6,Prod_Prop!$H:$H,V6,Prod_Prop!$I:$I,W$1)*IF(V6="Peso",$R6,1)) | X6: =IF(V6="","",SUMIFS(Prod_Prop!$J:$J,Prod_Prop!$B:$B,$Q6,Prod_Prop!$H:$H,V6,Prod_Prop!$I:$I,X$1)*IF(V6="Peso",$R6,1)) | Y6: =IFERROR(__xludf.DUMMYFUNCTION("IF(OR($U6="""",COUNTIF($I:$I,IFERROR(unique(filter(Prod_Prop!$H:$H,Prod_Prop!$G:$G=$U6,Prod_Prop!$E:$E=Y$1)),""Check""))=0),"""",IFERROR(unique(filter(Prod_Prop!$H:$H,Prod_Prop!$G:$G=$U6,Prod_Prop!$E:$E=Y$1)),""""))"),"") | Z6: =IF(Y6="","",SUMIFS(Prod_Prop!$J:$J,Prod_Prop!$B:$B,$Q6,Prod_Prop!$H:$H,Y6,Prod_Prop!$I:$I,Z$1)*IF(Y6="Peso",$R6,1)) | AA6: =IF(Y6="","",SUMIFS(Prod_Prop!$J:$J,Prod_Prop!$B:$B,$Q6,Prod_Prop!$H:$H,Y6,Prod_Prop!$I:$I,AA$1)*IF(Y6="Peso",$R6,1)) | AB6: =IFERROR(__xludf.DUMMYFUNCTION("IF(OR($U6="""",COUNTIF($I:$I,IFERROR(unique(filter(Prod_Prop!$H:$H,Prod_Prop!$G:$G=$U6,Prod_Prop!$E:$E=AB$1)),""Check""))=0),"""",IFERROR(unique(filter(Prod_Prop!$H:$H,Prod_Prop!$G:$G=$U6,Prod_Prop!$E:$E=AB$1)),""""))"),"") | AC6: =IF(AB6="","",SUMIFS(Prod_Prop!$J:$J,Prod_Prop!$B:$B,$Q6,Prod_Prop!$H:$H,AB6,Prod_Prop!$I:$I,AC$1)*IF(AB6="Peso",$R6,1)) | AD6: =IF(AB6="","",SUMIFS(Prod_Prop!$J:$J,Prod_Prop!$B:$B,$Q6,Prod_Prop!$H:$H,AB6,Prod_Prop!$I:$I,AD$1)*IF(AB6="Peso",$R6,1))
A7: {=IF(COUNTIF(A$1:A6,Cotizador!F$2)=maxifs(Familias!E:E,Familias!D:D,Cotizador!F$2),IF(COUNTIF(A$1:A6,XLOOKUP(Cotizador!F$2,Implementos!B:B,Implementos!C:C,"",0,1))=SUMIFS(Implementos!D:D,Implementos!B:B,Cotizador!F$2,Implementos!C:C,XLOOKUP(Cotizador!F$2,Implementos!B:B,Implementos!C:C,"",0,1)),"",XLOOKUP(Cotizador!F$2,Implementos!B:B,Implementos!C:C,"",0,1)),Cotizador!F$2)} -> Rodados | B7: =IF(A7="","",COUNTIF(A$1:A7,A7)) -> 2 | C7: {=IF(B7="","",IF(A7=XLOOKUP(A$2,Implementos!B:B,Implementos!C:C,"",0,1),B7+maxifs(B$1:B6,A$1:A6,A$2),B7))} -> 6 | D7: =IF(B7="","", COUNTIFS(Productos!F:F,A7,Productos!H:H,B7)+IF(F7="SI",0,1)) -> 10 | E7: =IFERROR(__xludf.DUMMYFUNCTION("IF($B7="""","""",INDEX(filter(Familias!F:F,Familias!$D:$D=$A7,Familias!$E:$E=$B7),1))"),"O") -> O | F7: =IFERROR(__xludf.DUMMYFUNCTION("IF($B7="""","""",INDEX(filter(Familias!G:G,Familias!$D:$D=$A7,Familias!$E:$E=$B7),1))"),"SI") -> SI | G7: {=IF(C7=1,XLOOKUP(C7,Cotizador!D:D,Cotizador!E:E,"",0,1),"")} | J7: =IF(I7="","",SUMIF(Cotizador!I$1:V$1,I7,Cotizador!I$2:V$2)) | L7: {=IF(COUNTIF(L$1:L6,A$2)=SUMIF(A:A,A$2,D:D),IF(COUNTIF(L$1:L6,XLOOKUP(A$2,Implementos!B:B,Implementos!C:C,"",0,1))=SUMIF(A:A,XLOOKUP(A$2,Implementos!B:B,Implementos!C:C,"",0,1),D:D),"",XLOOKUP(A$2,Implementos!B:B,Implementos!C:C,"",0,1)),A$2)} -> Acoplados Rurales | M7: =IF(L7="","",max(M$1:M6)+1) -> 6 | N7: =IF(L7="","",IF(N6="Orden",1,IF(COUNTIFS(N$1:N6,N6,L$1:L6,L7)=SUMIFS(D:D,B:B,N6,A:A,L7),IF(N6=maxifs(B:B,A:A,L7),"",maxifs(N$1:N6,L$1:L6,L7)+1),N6))) -> 1 | O7: =IF(N7="","",SUMIFS(C:C,B:B,N7,A:A,L7)) -> 1 | P7: =IF(N7="","",COUNTIFS(N$1:N7,N7,L$1:L7,L7)) -> 6 | Q7: =IF(U7="","",SUMIF(Productos!E:E,U7,Productos!A:A)) -> 50 | R7: {=IF(L7="","", max(1,SUMIF(I:I,XLOOKUP(U7,Productos!E:E,Productos!G:G,"",0,1),J:J)))} -> 1 | S7: =IF(Q7="","",IF(SUMIFS(Compat_Vetado!D:D,Compat_Vetado!B:B,SUM(G:G),Compat_Vetado!C:C,Q7)=1,"SI",IF(OR(SUMIF(Cotizador!E:E,Q7,Cotizador!G:G)>0,SUMIFS(Compat_Vetado!D:D,Compat_Vetado!B:B,SUM(G:G),Compat_Vetado!C:C,Q7)=-1),"NO",""))) | T7: =IF(Q7="","",IF(S7="SI","x",IF(S7="NO","",IF(AND(OR(V7="",AND(W7<=SUMIF(I:I,V7,J:J),SUMIF(I:I,V7,J:J)<=X7)),OR(Y7="",AND(Z7<=SUMIF(I:I,Y7,J:J),SUMIF(I:I,Y7,J:J)<=AA7)),OR(AB7="",AND(AC7<=SUMIF(I:I,AB7,J:J),SUMIF(I:I,AB7,J:J)<=AD7))),"x","")))) -> x | U7: =IFERROR(__xludf.DUMMYFUNCTION("IF(P7="""","""",IFERROR(INDEX(filter(Productos!E:E,Productos!F:F=L7,Productos!H:H=N7),P7),IF(M7=SUM(D:D),""Finalizar"",""-"")))"),"Tanque Combustible 3000 lts Standard") -> Tanque Combustible 3000 lts Standard | V7: =IFERROR(__xludf.DUMMYFUNCTION("IF(OR($U7="""",COUNTIF($I:$I,IFERROR(unique(filter(Prod_Prop!$H:$H,Prod_Prop!$G:$G=$U7,Prod_Prop!$E:$E=V$1)),""Check""))=0),"""",IFERROR(unique(filter(Prod_Prop!$H:$H,Prod_Prop!$G:$G=$U7,Prod_Prop!$E:$E=V$1)),""""))"),"") | W7: =IF(V7="","",SUMIFS(Prod_Prop!$J:$J,Prod_Prop!$B:$B,$Q7,Prod_Prop!$H:$H,V7,Prod_Prop!$I:$I,W$1)*IF(V7="Peso",$R7,1)) | X7: =IF(V7="","",SUMIFS(Prod_Prop!$J:$J,Prod_Prop!$B:$B,$Q7,Prod_Prop!$H:$H,V7,Prod_Prop!$I:$I,X$1)*IF(V7="Peso",$R7,1)) | Y7: =IFERROR(__xludf.DUMMYFUNCTION("IF(OR($U7="""",COUNTIF($I:$I,IFERROR(unique(filter(Prod_Prop!$H:$H,Prod_Prop!$G:$G=$U7,Prod_Prop!$E:$E=Y$1)),""Check""))=0),"""",IFERROR(unique(filter(Prod_Prop!$H:$H,Prod_Prop!$G:$G=$U7,Prod_Prop!$E:$E=Y$1)),""""))"),"") | Z7: =IF(Y7="","",SUMIFS(Prod_Prop!$J:$J,Prod_Prop!$B:$B,$Q7,Prod_Prop!$H:$H,Y7,Prod_Prop!$I:$I,Z$1)*IF(Y7="Peso",$R7,1)) | AA7: =IF(Y7="","",SUMIFS(Prod_Prop!$J:$J,Prod_Prop!$B:$B,$Q7,Prod_Prop!$H:$H,Y7,Prod_Prop!$I:$I,AA$1)*IF(Y7="Peso",$R7,1)) | AB7: =IFERROR(__xludf.DUMMYFUNCTION("IF(OR($U7="""",COUNTIF($I:$I,IFERROR(unique(filter(Prod_Prop!$H:$H,Prod_Prop!$G:$G=$U7,Prod_Prop!$E:$E=AB$1)),""Check""))=0),"""",IFERROR(unique(filter(Prod_Prop!$H:$H,Prod_Prop!$G:$G=$U7,Prod_Prop!$E:$E=AB$1)),""""))"),"") | AC7: =IF(AB7="","",SUMIFS(Prod_Prop!$J:$J,Prod_Prop!$B:$B,$Q7,Prod_Prop!$H:$H,AB7,Prod_Prop!$I:$I,AC$1)*IF(AB7="Peso",$R7,1)) | AD7: =IF(AB7="","",SUMIFS(Prod_Prop!$J:$J,Prod_Prop!$B:$B,$Q7,Prod_Prop!$H:$H,AB7,Prod_Prop!$I:$I,AD$1)*IF(AB7="Peso",$R7,1))
A8: {=IF(COUNTIF(A$1:A7,Cotizador!F$2)=maxifs(Familias!E:E,Familias!D:D,Cotizador!F$2),IF(COUNTIF(A$1:A7,XLOOKUP(Cotizador!F$2,Implementos!B:B,Implementos!C:C,"",0,1))=SUMIFS(Implementos!D:D,Implementos!B:B,Cotizador!F$2,Implementos!C:C,XLOOKUP(Cotizador!F$2,Implementos!B:B,Implementos!C:C,"",0,1)),"",XLOOKUP(Cotizador!F$2,Implementos!B:B,Implementos!C:C,"",0,1)),Cotizador!F$2)} -> Rodados | B8: =IF(A8="","",COUNTIF(A$1:A8,A8)) -> 3 | C8: {=IF(B8="","",IF(A8=XLOOKUP(A$2,Implementos!B:B,Implementos!C:C,"",0,1),B8+maxifs(B$1:B7,A$1:A7,A$2),B8))} -> 7 | D8: =IF(B8="","", COUNTIFS(Productos!F:F,A8,Productos!H:H,B8)+IF(F8="SI",0,1)) -> 8 | E8: =IFERROR(__xludf.DUMMYFUNCTION("IF($B8="""","""",INDEX(filter(Familias!F:F,Familias!$D:$D=$A8,Familias!$E:$E=$B8),1))"),"O") -> O | F8: =IFERROR(__xludf.DUMMYFUNCTION("IF($B8="""","""",INDEX(filter(Familias!G:G,Familias!$D:$D=$A8,Familias!$E:$E=$B8),1))"),"SI") -> SI | G8: {=IF(C8=1,XLOOKUP(C8,Cotizador!D:D,Cotizador!E:E,"",0,1),"")} | J8: =IF(I8="","",SUMIF(Cotizador!I$1:V$1,I8,Cotizador!I$2:V$2)) | L8: {=IF(COUNTIF(L$1:L7,A$2)=SUMIF(A:A,A$2,D:D),IF(COUNTIF(L$1:L7,XLOOKUP(A$2,Implementos!B:B,Implementos!C:C,"",0,1))=SUMIF(A:A,XLOOKUP(A$2,Implementos!B:B,Implementos!C:C,"",0,1),D:D),"",XLOOKUP(A$2,Implementos!B:B,Implementos!C:C,"",0,1)),A$2)} -> Acoplados Rurales | M8: =IF(L8="","",max(M$1:M7)+1) -> 7 | N8: =IF(L8="","",IF(N7="Orden",1,IF(COUNTIFS(N$1:N7,N7,L$1:L7,L8)=SUMIFS(D:D,B:B,N7,A:A,L8),IF(N7=maxifs(B:B,A:A,L8),"",maxifs(N$1:N7,L$1:L7,L8)+1),N7))) -> 1 | O8: =IF(N8="","",SUMIFS(C:C,B:B,N8,A:A,L8)) -> 1 | P8: =IF(N8="","",COUNTIFS(N$1:N8,N8,L$1:L8,L8)) -> 7 | Q8: =IF(U8="","",SUMIF(Productos!E:E,U8,Productos!A:A)) -> 51 | R8: {=IF(L8="","", max(1,SUMIF(I:I,XLOOKUP(U8,Productos!E:E,Productos!G:G,"",0,1),J:J)))} -> 1 | S8: =IF(Q8="","",IF(SUMIFS(Compat_Vetado!D:D,Compat_Vetado!B:B,SUM(G:G),Compat_Vetado!C:C,Q8)=1,"SI",IF(OR(SUMIF(Cotizador!E:E,Q8,Cotizador!G:G)>0,SUMIFS(Compat_Vetado!D:D,Compat_Vetado!B:B,SUM(G:G),Compat_Vetado!C:C,Q8)=-1),"NO",""))) | T8: =IF(Q8="","",IF(S8="SI","x",IF(S8="NO","",IF(AND(OR(V8="",AND(W8<=SUMIF(I:I,V8,J:J),SUMIF(I:I,V8,J:J)<=X8)),OR(Y8="",AND(Z8<=SUMIF(I:I,Y8,J:J),SUMIF(I:I,Y8,J:J)<=AA8)),OR(AB8="",AND(AC8<=SUMIF(I:I,AB8,J:J),SUMIF(I:I,AB8,J:J)<=AD8))),"x","")))) -> x | U8: =IFERROR(__xludf.DUMMYFUNCTION("IF(P8="""","""",IFERROR(INDEX(filter(Productos!E:E,Productos!F:F=L8,Productos!H:H=N8),P8),IF(M8=SUM(D:D),""Finalizar"",""-"")))"),"Tanque Combustible 3000 lts Alto") -> Tanque Combustible 3000 lts Alto | V8: =IFERROR(__xludf.DUMMYFUNCTION("IF(OR($U8="""",COUNTIF($I:$I,IFERROR(unique(filter(Prod_Prop!$H:$H,Prod_Prop!$G:$G=$U8,Prod_Prop!$E:$E=V$1)),""Check""))=0),"""",IFERROR(unique(filter(Prod_Prop!$H:$H,Prod_Prop!$G:$G=$U8,Prod_Prop!$E:$E=V$1)),""""))"),"") | W8: =IF(V8="","",SUMIFS(Prod_Prop!$J:$J,Prod_Prop!$B:$B,$Q8,Prod_Prop!$H:$H,V8,Prod_Prop!$I:$I,W$1)*IF(V8="Peso",$R8,1)) | X8: =IF(V8="","",SUMIFS(Prod_Prop!$J:$J,Prod_Prop!$B:$B,$Q8,Prod_Prop!$H:$H,V8,Prod_Prop!$I:$I,X$1)*IF(V8="Peso",$R8,1)) | Y8: =IFERROR(__xludf.DUMMYFUNCTION("IF(OR($U8="""",COUNTIF($I:$I,IFERROR(unique(filter(Prod_Prop!$H:$H,Prod_Prop!$G:$G=$U8,Prod_Prop!$E:$E=Y$1)),""Check""))=0),"""",IFERROR(unique(filter(Prod_Prop!$H:$H,Prod_Prop!$G:$G=$U8,Prod_Prop!$E:$E=Y$1)),""""))"),"") | Z8: =IF(Y8="","",SUMIFS(Prod_Prop!$J:$J,Prod_Prop!$B:$B,$Q8,Prod_Prop!$H:$H,Y8,Prod_Prop!$I:$I,Z$1)*IF(Y8="Peso",$R8,1)) | AA8: =IF(Y8="","",SUMIFS(Prod_Prop!$J:$J,Prod_Prop!$B:$B,$Q8,Prod_Prop!$H:$H,Y8,Prod_Prop!$I:$I,AA$1)*IF(Y8="Peso",$R8,1)) | AB8: =IFERROR(__xludf.DUMMYFUNCTION("IF(OR($U8="""",COUNTIF($I:$I,IFERROR(unique(filter(Prod_Prop!$H:$H,Prod_Prop!$G:$G=$U8,Prod_Prop!$E:$E=AB$1)),""Check""))=0),"""",IFERROR(unique(filter(Prod_Prop!$H:$H,Prod_Prop!$G:$G=$U8,Prod_Prop!$E:$E=AB$1)),""""))"),"") | AC8: =IF(AB8="","",SUMIFS(Prod_Prop!$J:$J,Prod_Prop!$B:$B,$Q8,Prod_Prop!$H:$H,AB8,Prod_Prop!$I:$I,AC$1)*IF(AB8="Peso",$R8,1)) | AD8: =IF(AB8="","",SUMIFS(Prod_Prop!$J:$J,Prod_Prop!$B:$B,$Q8,Prod_Prop!$H:$H,AB8,Prod_Prop!$I:$I,AD$1)*IF(AB8="Peso",$R8,1))
A9: {=IF(COUNTIF(A$1:A8,Cotizador!F$2)=maxifs(Familias!E:E,Familias!D:D,Cotizador!F$2),IF(COUNTIF(A$1:A8,XLOOKUP(Cotizador!F$2,Implementos!B:B,Implementos!C:C,"",0,1))=SUMIFS(Implementos!D:D,Implementos!B:B,Cotizador!F$2,Implementos!C:C,XLOOKUP(Cotizador!F$2,Implementos!B:B,Implementos!C:C,"",0,1)),"",XLOOKUP(Cotizador!F$2,Implementos!B:B,Implementos!C:C,"",0,1)),Cotizador!F$2)} | B9: =IF(A9="","",COUNTIF(A$1:A9,A9)) | C9: {=IF(B9="","",IF(A9=XLOOKUP(A$2,Implementos!B:B,Implementos!C:C,"",0,1),B9+maxifs(B$1:B8,A$1:A8,A$2),B9))} | D9: =IF(B9="","", COUNTIFS(Productos!F:F,A9,Productos!H:H,B9)+IF(F9="SI",0,1)) | E9: =IFERROR(__xludf.DUMMYFUNCTION("IF($B9="""","""",INDEX(filter(Familias!F:F,Familias!$D:$D=$A9,Familias!$E:$E=$B9),1))"),"") | F9: =IFERROR(__xludf.DUMMYFUNCTION("IF($B9="""","""",INDEX(filter(Familias!G:G,Familias!$D:$D=$A9,Familias!$E:$E=$B9),1))"),"") | G9: {=IF(C9=1,XLOOKUP(C9,Cotizador!D:D,Cotizador!E:E,"",0,1),"")} | J9: =IF(I9="","",SUMIF(Cotizador!I$1:V$1,I9,Cotizador!I$2:V$2)) | L9: {=IF(COUNTIF(L$1:L8,A$2)=SUMIF(A:A,A$2,D:D),IF(COUNTIF(L$1:L8,XLOOKUP(A$2,Implementos!B:B,Implementos!C:C,"",0,1))=SUMIF(A:A,XLOOKUP(A$2,Implementos!B:B,Implementos!C:C,"",0,1),D:D),"",XLOOKUP(A$2,Implementos!B:B,Implementos!C:C,"",0,1)),A$2)} -> Acoplados Rurales | M9: =IF(L9="","",max(M$1:M8)+1) -> 8 | N9: =IF(L9="","",IF(N8="Orden",1,IF(COUNTIFS(N$1:N8,N8,L$1:L8,L9)=SUMIFS(D:D,B:B,N8,A:A,L9),IF(N8=maxifs(B:B,A:A,L9),"",maxifs(N$1:N8,L$1:L8,L9)+1),N8))) -> 1 | O9: =IF(N9="","",SUMIFS(C:C,B:B,N9,A:A,L9)) -> 1 | P9: =IF(N9="","",COUNTIFS(N$1:N9,N9,L$1:L9,L9)) -> 8 | Q9: =IF(U9="","",SUMIF(Productos!E:E,U9,Productos!A:A)) -> 52 | R9: {=IF(L9="","", max(1,SUMIF(I:I,XLOOKUP(U9,Productos!E:E,Productos!G:G,"",0,1),J:J)))} -> 1 | S9: =IF(Q9="","",IF(SUMIFS(Compat_Vetado!D:D,Compat_Vetado!B:B,SUM(G:G),Compat_Vetado!C:C,Q9)=1,"SI",IF(OR(SUMIF(Cotizador!E:E,Q9,Cotizador!G:G)>0,SUMIFS(Compat_Vetado!D:D,Compat_Vetado!B:B,SUM(G:G),Compat_Vetado!C:C,Q9)=-1),"NO",""))) | T9: =IF(Q9="","",IF(S9="SI","x",IF(S9="NO","",IF(AND(OR(V9="",AND(W9<=SUMIF(I:I,V9,J:J),SUMIF(I:I,V9,J:J)<=X9)),OR(Y9="",AND(Z9<=SUMIF(I:I,Y9,J:J),SUMIF(I:I,Y9,J:J)<=AA9)),OR(AB9="",AND(AC9<=SUMIF(I:I,AB9,J:J),SUMIF(I:I,AB9,J:J)<=AD9))),"x","")))) -> x | U9: =IFERROR(__xludf.DUMMYFUNCTION("IF(P9="""","""",IFERROR(INDEX(filter(Productos!E:E,Productos!F:F=L9,Productos!H:H=N9),P9),IF(M9=SUM(D:D),""Finalizar"",""-"")))"),"Tanque Combustible 4000 lts Standard") -> Tanque Combustible 4000 lts Standard | V9: =IFERROR(__xludf.DUMMYFUNCTION("IF(OR($U9="""",COUNTIF($I:$I,IFERROR(unique(filter(Prod_Prop!$H:$H,Prod_Prop!$G:$G=$U9,Prod_Prop!$E:$E=V$1)),""Check""))=0),"""",IFERROR(unique(filter(Prod_Prop!$H:$H,Prod_Prop!$G:$G=$U9,Prod_Prop!$E:$E=V$1)),""""))"),"") | W9: =IF(V9="","",SUMIFS(Prod_Prop!$J:$J,Prod_Prop!$B:$B,$Q9,Prod_Prop!$H:$H,V9,Prod_Prop!$I:$I,W$1)*IF(V9="Peso",$R9,1)) | X9: =IF(V9="","",SUMIFS(Prod_Prop!$J:$J,Prod_Prop!$B:$B,$Q9,Prod_Prop!$H:$H,V9,Prod_Prop!$I:$I,X$1)*IF(V9="Peso",$R9,1)) | Y9: =IFERROR(__xludf.DUMMYFUNCTION("IF(OR($U9="""",COUNTIF($I:$I,IFERROR(unique(filter(Prod_Prop!$H:$H,Prod_Prop!$G:$G=$U9,Prod_Prop!$E:$E=Y$1)),""Check""))=0),"""",IFERROR(unique(filter(Prod_Prop!$H:$H,Prod_Prop!$G:$G=$U9,Prod_Prop!$E:$E=Y$1)),""""))"),"") | Z9: =IF(Y9="","",SUMIFS(Prod_Prop!$J:$J,Prod_Prop!$B:$B,$Q9,Prod_Prop!$H:$H,Y9,Prod_Prop!$I:$I,Z$1)*IF(Y9="Peso",$R9,1)) | AA9: =IF(Y9="","",SUMIFS(Prod_Prop!$J:$J,Prod_Prop!$B:$B,$Q9,Prod_Prop!$H:$H,Y9,Prod_Prop!$I:$I,AA$1)*IF(Y9="Peso",$R9,1)) | AB9: =IFERROR(__xludf.DUMMYFUNCTION("IF(OR($U9="""",COUNTIF($I:$I,IFERROR(unique(filter(Prod_Prop!$H:$H,Prod_Prop!$G:$G=$U9,Prod_Prop!$E:$E=AB$1)),""Check""))=0),"""",IFERROR(unique(filter(Prod_Prop!$H:$H,Prod_Prop!$G:$G=$U9,Prod_Prop!$E:$E=AB$1)),""""))"),"") | AC9: =IF(AB9="","",SUMIFS(Prod_Prop!$J:$J,Prod_Prop!$B:$B,$Q9,Prod_Prop!$H:$H,AB9,Prod_Prop!$I:$I,AC$1)*IF(AB9="Peso",$R9,1)) | AD9: =IF(AB9="","",SUMIFS(Prod_Prop!$J:$J,Prod_Prop!$B:$B,$Q9,Prod_Prop!$H:$H,AB9,Prod_Prop!$I:$I,AD$1)*IF(AB9="Peso",$R9,1))
A10: {=IF(COUNTIF(A$1:A9,Cotizador!F$2)=maxifs(Familias!E:E,Familias!D:D,Cotizador!F$2),IF(COUNTIF(A$1:A9,XLOOKUP(Cotizador!F$2,Implementos!B:B,Implementos!C:C,"",0,1))=SUMIFS(Implementos!D:D,Implementos!B:B,Cotizador!F$2,Implementos!C:C,XLOOKUP(Cotizador!F$2,Implementos!B:B,Implementos!C:C,"",0,1)),"",XLOOKUP(Cotizador!F$2,Implementos!B:B,Implementos!C:C,"",0,1)),Cotizador!F$2)} | B10: =IF(A10="","",COUNTIF(A$1:A10,A10)) | C10: {=IF(B10="","",IF(A10=XLOOKUP(A$2,Implementos!B:B,Implementos!C:C,"",0,1),B10+maxifs(B$1:B9,A$1:A9,A$2),B10))} | D10: =IF(B10="","", COUNTIFS(Productos!F:F,A10,Productos!H:H,B10)+IF(F10="SI",0,1)) | E10: =IFERROR(__xludf.DUMMYFUNCTION("IF($B10="""","""",INDEX(filter(Familias!F:F,Familias!$D:$D=$A10,Familias!$E:$E=$B10),1))"),"") | F10: =IFERROR(__xludf.DUMMYFUNCTION("IF($B10="""","""",INDEX(filter(Familias!G:G,Familias!$D:$D=$A10,Familias!$E:$E=$B10),1))"),"") | G10: {=IF(C10=1,XLOOKUP(C10,Cotizador!D:D,Cotizador!E:E,"",0,1),"")} | J10: =IF(I10="","",SUMIF(Cotizador!I$1:V$1,I10,Cotizador!I$2:V$2)) | L10: {=IF(COUNTIF(L$1:L9,A$2)=SUMIF(A:A,A$2,D:D),IF(COUNTIF(L$1:L9,XLOOKUP(A$2,Implementos!B:B,Implementos!C:C,"",0,1))=SUMIF(A:A,XLOOKUP(A$2,Implementos!B:B,Implementos!C:C,"",0,1),D:D),"",XLOOKUP(A$2,Implementos!B:B,Implementos!C:C,"",0,1)),A$2)} -> Acoplados Rurales | M10: =IF(L10="","",max(M$1:M9)+1) -> 9 | N10: =IF(L10="","",IF(N9="Orden",1,IF(COUNTIFS(N$1:N9,N9,L$1:L9,L10)=SUMIFS(D:D,B:B,N9,A:A,L10),IF(N9=maxifs(B:B,A:A,L10),"",maxifs(N$1:N9,L$1:L9,L10)+1),N9))) -> 1 | O10: =IF(N10="","",SUMIFS(C:C,B:B,N10,A:A,L10)) -> 1 | P10: =IF(N10="","",COUNTIFS(N$1:N10,N10,L$1:L10,L10)) -> 9 | Q10: =IF(U10="","",SUMIF(Productos!E:E,U10,Productos!A:A)) -> 53 | R10: {=IF(L10="","", max(1,SUMIF(I:I,XLOOKUP(U10,Productos!E:E,Productos!G:G,"",0,1),J:J)))} -> 1 | S10: =IF(Q10="","",IF(SUMIFS(Compat_Vetado!D:D,Compat_Vetado!B:B,SUM(G:G),Compat_Vetado!C:C,Q10)=1,"SI",IF(OR(SUMIF(Cotizador!E:E,Q10,Cotizador!G:G)>0,SUMIFS(Compat_Vetado!D:D,Compat_Vetado!B:B,SUM(G:G),Compat_Vetado!C:C,Q10)=-1),"NO",""))) | T10: =IF(Q10="","",IF(S10="SI","x",IF(S10="NO","",IF(AND(OR(V10="",AND(W10<=SUMIF(I:I,V10,J:J),SUMIF(I:I,V10,J:J)<=X10)),OR(Y10="",AND(Z10<=SUMIF(I:I,Y10,J:J),SUMIF(I:I,Y10,J:J)<=AA10)),OR(AB10="",AND(AC10<=SUMIF(I:I,AB10,J:J),SUMIF(I:I,AB10,J:J)<=AD10))),"x","")))) -> x | U10: =IFERROR(__xludf.DUMMYFUNCTION("IF(P10="""","""",IFERROR(INDEX(filter(Productos!E:E,Productos!F:F=L10,Productos!H:H=N10),P10),IF(M10=SUM(D:D),""Finalizar"",""-"")))"),"Tanque Combustible 5000 lts Standard") -> Tanque Combustible 5000 lts Standard | V10: =IFERROR(__xludf.DUMMYFUNCTION("IF(OR($U10="""",COUNTIF($I:$I,IFERROR(unique(filter(Prod_Prop!$H:$H,Prod_Prop!$G:$G=$U10,Prod_Prop!$E:$E=V$1)),""Check""))=0),"""",IFERROR(unique(filter(Prod_Prop!$H:$H,Prod_Prop!$G:$G=$U10,Prod_Prop!$E:$E=V$1)),""""))"),"") | W10: =IF(V10="","",SUMIFS(Prod_Prop!$J:$J,Prod_Prop!$B:$B,$Q10,Prod_Prop!$H:$H,V10,Prod_Prop!$I:$I,W$1)*IF(V10="Peso",$R10,1)) | X10: =IF(V10="","",SUMIFS(Prod_Prop!$J:$J,Prod_Prop!$B:$B,$Q10,Prod_Prop!$H:$H,V10,Prod_Prop!$I:$I,X$1)*IF(V10="Peso",$R10,1)) | Y10: =IFERROR(__xludf.DUMMYFUNCTION("IF(OR($U10="""",COUNTIF($I:$I,IFERROR(unique(filter(Prod_Prop!$H:$H,Prod_Prop!$G:$G=$U10,Prod_Prop!$E:$E=Y$1)),""Check""))=0),"""",IFERROR(unique(filter(Prod_Prop!$H:$H,Prod_Prop!$G:$G=$U10,Prod_Prop!$E:$E=Y$1)),""""))"),"") | Z10: =IF(Y10="","",SUMIFS(Prod_Prop!$J:$J,Prod_Prop!$B:$B,$Q10,Prod_Prop!$H:$H,Y10,Prod_Prop!$I:$I,Z$1)*IF(Y10="Peso",$R10,1)) | AA10: =IF(Y10="","",SUMIFS(Prod_Prop!$J:$J,Prod_Prop!$B:$B,$Q10,Prod_Prop!$H:$H,Y10,Prod_Prop!$I:$I,AA$1)*IF(Y10="Peso",$R10,1)) | AB10: =IFERROR(__xludf.DUMMYFUNCTION("IF(OR($U10="""",COUNTIF($I:$I,IFERROR(unique(filter(Prod_Prop!$H:$H,Prod_Prop!$G:$G=$U10,Prod_Prop!$E:$E=AB$1)),""Check""))=0),"""",IFERROR(unique(filter(Prod_Prop!$H:$H,Prod_Prop!$G:$G=$U10,Prod_Prop!$E:$E=AB$1)),""""))"),"") | AC10: =IF(AB10="","",SUMIFS(Prod_Prop!$J:$J,Prod_Prop!$B:$B,$Q10,Prod_Prop!$H:$H,AB10,Prod_Prop!$I:$I,AC$1)*IF(AB10="Peso",$R10,1)) | AD10: =IF(AB10="","",SUMIFS(Prod_Prop!$J:$J,Prod_Prop!$B:$B,$Q10,Prod_Prop!$H:$H,AB10,Prod_Prop!$I:$I,AD$1)*IF(AB10="Peso",$R10,1))
A11: {=IF(COUNTIF(A$1:A10,Cotizador!F$2)=maxifs(Familias!E:E,Familias!D:D,Cotizador!F$2),IF(COUNTIF(A$1:A10,XLOOKUP(Cotizador!F$2,Implementos!B:B,Implementos!C:C,"",0,1))=SUMIFS(Implementos!D:D,Implementos!B:B,Cotizador!F$2,Implementos!C:C,XLOOKUP(Cotizador!F$2,Implementos!B:B,Implementos!C:C,"",0,1)),"",XLOOKUP(Cotizador!F$2,Implementos!B:B,Implementos!C:C,"",0,1)),Cotizador!F$2)} | B11: =IF(A11="","",COUNTIF(A$1:A11,A11)) | C11: {=IF(B11="","",IF(A11=XLOOKUP(A$2,Implementos!B:B,Implementos!C:C,"",0,1),B11+maxifs(B$1:B10,A$1:A10,A$2),B11))} | D11: =IF(B11="","", COUNTIFS(Productos!F:F,A11,Productos!H:H,B11)+IF(F11="SI",0,1)) | E11: =IFERROR(__xludf.DUMMYFUNCTION("IF($B11="""","""",INDEX(filter(Familias!F:F,Familias!$D:$D=$A11,Familias!$E:$E=$B11),1))"),"") | F11: =IFERROR(__xludf.DUMMYFUNCTION("IF($B11="""","""",INDEX(filter(Familias!G:G,Familias!$D:$D=$A11,Familias!$E:$E=$B11),1))"),"") | G11: {=IF(C11=1,XLOOKUP(C11,Cotizador!D:D,Cotizador!E:E,"",0,1),"")} | J11: =IF(I11="","",SUMIF(Cotizador!I$1:V$1,I11,Cotizador!I$2:V$2)) | L11: {=IF(COUNTIF(L$1:L10,A$2)=SUMIF(A:A,A$2,D:D),IF(COUNTIF(L$1:L10,XLOOKUP(A$2,Implementos!B:B,Implementos!C:C,"",0,1))=SUMIF(A:A,XLOOKUP(A$2,Implementos!B:B,Implementos!C:C,"",0,1),D:D),"",XLOOKUP(A$2,Implementos!B:B,Implementos!C:C,"",0,1)),A$2)} -> Acoplados Rurales | M11: =IF(L11="","",max(M$1:M10)+1) -> 10 | N11: =IF(L11="","",IF(N10="Orden",1,IF(COUNTIFS(N$1:N10,N10,L$1:L10,L11)=SUMIFS(D:D,B:B,N10,A:A,L11),IF(N10=maxifs(B:B,A:A,L11),"",maxifs(N$1:N10,L$1:L10,L11)+1),N10))) -> 1 | O11: =IF(N11="","",SUMIFS(C:C,B:B,N11,A:A,L11)) -> 1 | P11: =IF(N11="","",COUNTIFS(N$1:N11,N11,L$1:L11,L11)) -> 10 | Q11: =IF(U11="","",SUMIF(Productos!E:E,U11,Productos!A:A)) -> 54 | R11: {=IF(L11="","", max(1,SUMIF(I:I,XLOOKUP(U11,Productos!E:E,Productos!G:G,"",0,1),J:J)))} -> 1 | S11: =IF(Q11="","",IF(SUMIFS(Compat_Vetado!D:D,Compat_Vetado!B:B,SUM(G:G),Compat_Vetado!C:C,Q11)=1,"SI",IF(OR(SUMIF(Cotizador!E:E,Q11,Cotizador!G:G)>0,SUMIFS(Compat_Vetado!D:D,Compat_Vetado!B:B,SUM(G:G),Compat_Vetado!C:C,Q11)=-1),"NO",""))) | T11: =IF(Q11="","",IF(S11="SI","x",IF(S11="NO","",IF(AND(OR(V11="",AND(W11<=SUMIF(I:I,V11,J:J),SUMIF(I:I,V11,J:J)<=X11)),OR(Y11="",AND(Z11<=SUMIF(I:I,Y11,J:J),SUMIF(I:I,Y11,J:J)<=AA11)),OR(AB11="",AND(AC11<=SUMIF(I:I,AB11,J:J),SUMIF(I:I,AB11,J:J)<=AD11))),"x","")))) -> x | U11: =IFERROR(__xludf.DUMMYFUNCTION("IF(P11="""","""",IFERROR(INDEX(filter(Productos!E:E,Productos!F:F=L11,Productos!H:H=N11),P11),IF(M11=SUM(D:D),""Finalizar"",""-"")))"),"Tanque Combustible 5000 lts Alto") -> Tanque Combustible 5000 lts Alto | V11: =IFERROR(__xludf.DUMMYFUNCTION("IF(OR($U11="""",COUNTIF($I:$I,IFERROR(unique(filter(Prod_Prop!$H:$H,Prod_Prop!$G:$G=$U11,Prod_Prop!$E:$E=V$1)),""Check""))=0),"""",IFERROR(unique(filter(Prod_Prop!$H:$H,Prod_Prop!$G:$G=$U11,Prod_Prop!$E:$E=V$1)),""""))"),"") | W11: =IF(V11="","",SUMIFS(Prod_Prop!$J:$J,Prod_Prop!$B:$B,$Q11,Prod_Prop!$H:$H,V11,Prod_Prop!$I:$I,W$1)*IF(V11="Peso",$R11,1)) | X11: =IF(V11="","",SUMIFS(Prod_Prop!$J:$J,Prod_Prop!$B:$B,$Q11,Prod_Prop!$H:$H,V11,Prod_Prop!$I:$I,X$1)*IF(V11="Peso",$R11,1)) | Y11: =IFERROR(__xludf.DUMMYFUNCTION("IF(OR($U11="""",COUNTIF($I:$I,IFERROR(unique(filter(Prod_Prop!$H:$H,Prod_Prop!$G:$G=$U11,Prod_Prop!$E:$E=Y$1)),""Check""))=0),"""",IFERROR(unique(filter(Prod_Prop!$H:$H,Prod_Prop!$G:$G=$U11,Prod_Prop!$E:$E=Y$1)),""""))"),"") | Z11: =IF(Y11="","",SUMIFS(Prod_Prop!$J:$J,Prod_Prop!$B:$B,$Q11,Prod_Prop!$H:$H,Y11,Prod_Prop!$I:$I,Z$1)*IF(Y11="Peso",$R11,1)) | AA11: =IF(Y11="","",SUMIFS(Prod_Prop!$J:$J,Prod_Prop!$B:$B,$Q11,Prod_Prop!$H:$H,Y11,Prod_Prop!$I:$I,AA$1)*IF(Y11="Peso",$R11,1)) | AB11: =IFERROR(__xludf.DUMMYFUNCTION("IF(OR($U11="""",COUNTIF($I:$I,IFERROR(unique(filter(Prod_Prop!$H:$H,Prod_Prop!$G:$G=$U11,Prod_Prop!$E:$E=AB$1)),""Check""))=0),"""",IFERROR(unique(filter(Prod_Prop!$H:$H,Prod_Prop!$G:$G=$U11,Prod_Prop!$E:$E=AB$1)),""""))"),"") | AC11: =IF(AB11="","",SUMIFS(Prod_Prop!$J:$J,Prod_Prop!$B:$B,$Q11,Prod_Prop!$H:$H,AB11,Prod_Prop!$I:$I,AC$1)*IF(AB11="Peso",$R11,1)) | AD11: =IF(AB11="","",SUMIFS(Prod_Prop!$J:$J,Prod_Prop!$B:$B,$Q11,Prod_Prop!$H:$H,AB11,Prod_Prop!$I:$I,AD$1)*IF(AB11="Peso",$R11,1))
A12: {=IF(COUNTIF(A$1:A11,Cotizador!F$2)=maxifs(Familias!E:E,Familias!D:D,Cotizador!F$2),IF(COUNTIF(A$1:A11,XLOOKUP(Cotizador!F$2,Implementos!B:B,Implementos!C:C,"",0,1))=SUMIFS(Implementos!D:D,Implementos!B:B,Cotizador!F$2,Implementos!C:C,XLOOKUP(Cotizador!F$2,Implementos!B:B,Implementos!C:C,"",0,1)),"",XLOOKUP(Cotizador!F$2,Implementos!B:B,Implementos!C:C,"",0,1)),Cotizador!F$2)} | B12: =IF(A12="","",COUNTIF(A$1:A12,A12)) | C12: {=IF(B12="","",IF(A12=XLOOKUP(A$2,Implementos!B:B,Implementos!C:C,"",0,1),B12+maxifs(B$1:B11,A$1:A11,A$2),B12))} | D12: =IF(B12="","", COUNTIFS(Productos!F:F,A12,Productos!H:H,B12)+IF(F12="SI",0,1)) | E12: =IFERROR(__xludf.DUMMYFUNCTION("IF($B12="""","""",INDEX(filter(Familias!F:F,Familias!$D:$D=$A12,Familias!$E:$E=$B12),1))"),"") | F12: =IFERROR(__xludf.DUMMYFUNCTION("IF($B12="""","""",INDEX(filter(Familias!G:G,Familias!$D:$D=$A12,Familias!$E:$E=$B12),1))"),"") | G12: {=IF(C12=1,XLOOKUP(C12,Cotizador!D:D,Cotizador!E:E,"",0,1),"")} | J12: =IF(I12="","",SUMIF(Cotizador!I$1:V$1,I12,Cotizador!I$2:V$2)) | L12: {=IF(COUNTIF(L$1:L11,A$2)=SUMIF(A:A,A$2,D:D),IF(COUNTIF(L$1:L11,XLOOKUP(A$2,Implementos!B:B,Implementos!C:C,"",0,1))=SUMIF(A:A,XLOOKUP(A$2,Implementos!B:B,Implementos!C:C,"",0,1),D:D),"",XLOOKUP(A$2,Implementos!B:B,Implementos!C:C,"",0,1)),A$2)} -> Acoplados Rurales | M12: =IF(L12="","",max(M$1:M11)+1) -> 11 | N12: =IF(L12="","",IF(N11="Orden",1,IF(COUNTIFS(N$1:N11,N11,L$1:L11,L12)=SUMIFS(D:D,B:B,N11,A:A,L12),IF(N11=maxifs(B:B,A:A,L12),"",maxifs(N$1:N11,L$1:L11,L12)+1),N11))) -> 1 | O12: =IF(N12="","",SUMIFS(C:C,B:B,N12,A:A,L12)) -> 1 | P12: =IF(N12="","",COUNTIFS(N$1:N12,N12,L$1:L12,L12)) -> 11 | Q12: =IF(U12="","",SUMIF(Productos!E:E,U12,Productos!A:A)) -> 55 | R12: {=IF(L12="","", max(1,SUMIF(I:I,XLOOKUP(U12,Productos!E:E,Productos!G:G,"",0,1),J:J)))} -> 1 | S12: =IF(Q12="","",IF(SUMIFS(Compat_Vetado!D:D,Compat_Vetado!B:B,SUM(G:G),Compat_Vetado!C:C,Q12)=1,"SI",IF(OR(SUMIF(Cotizador!E:E,Q12,Cotizador!G:G)>0,SUMIFS(Compat_Vetado!D:D,Compat_Vetado!B:B,SUM(G:G),Compat_Vetado!C:C,Q12)=-1),"NO",""))) | T12: =IF(Q12="","",IF(S12="SI","x",IF(S12="NO","",IF(AND(OR(V12="",AND(W12<=SUMIF(I:I,V12,J:J),SUMIF(I:I,V12,J:J)<=X12)),OR(Y12="",AND(Z12<=SUMIF(I:I,Y12,J:J),SUMIF(I:I,Y12,J:J)<=AA12)),OR(AB12="",AND(AC12<=SUMIF(I:I,AB12,J:J),SUMIF(I:I,AB12,J:J)<=AD12))),"x","")))) -> x | U12: =IFERROR(__xludf.DUMMYFUNCTION("IF(P12="""","""",IFERROR(INDEX(filter(Productos!E:E,Productos!F:F=L12,Productos!H:H=N12),P12),IF(M12=SUM(D:D),""Finalizar"",""-"")))"),"Tanque Combustible 2000 lts Alto") -> Tanque Combustible 2000 lts Alto | V12: =IFERROR(__xludf.DUMMYFUNCTION("IF(OR($U12="""",COUNTIF($I:$I,IFERROR(unique(filter(Prod_Prop!$H:$H,Prod_Prop!$G:$G=$U12,Prod_Prop!$E:$E=V$1)),""Check""))=0),"""",IFERROR(unique(filter(Prod_Prop!$H:$H,Prod_Prop!$G:$G=$U12,Prod_Prop!$E:$E=V$1)),""""))"),"") | W12: =IF(V12="","",SUMIFS(Prod_Prop!$J:$J,Prod_Prop!$B:$B,$Q12,Prod_Prop!$H:$H,V12,Prod_Prop!$I:$I,W$1)*IF(V12="Peso",$R12,1)) | X12: =IF(V12="","",SUMIFS(Prod_Prop!$J:$J,Prod_Prop!$B:$B,$Q12,Prod_Prop!$H:$H,V12,Prod_Prop!$I:$I,X$1)*IF(V12="Peso",$R12,1)) | Y12: =IFERROR(__xludf.DUMMYFUNCTION("IF(OR($U12="""",COUNTIF($I:$I,IFERROR(unique(filter(Prod_Prop!$H:$H,Prod_Prop!$G:$G=$U12,Prod_Prop!$E:$E=Y$1)),""Check""))=0),"""",IFERROR(unique(filter(Prod_Prop!$H:$H,Prod_Prop!$G:$G=$U12,Prod_Prop!$E:$E=Y$1)),""""))"),"") | Z12: =IF(Y12="","",SUMIFS(Prod_Prop!$J:$J,Prod_Prop!$B:$B,$Q12,Prod_Prop!$H:$H,Y12,Prod_Prop!$I:$I,Z$1)*IF(Y12="Peso",$R12,1)) | AA12: =IF(Y12="","",SUMIFS(Prod_Prop!$J:$J,Prod_Prop!$B:$B,$Q12,Prod_Prop!$H:$H,Y12,Prod_Prop!$I:$I,AA$1)*IF(Y12="Peso",$R12,1)) | AB12: =IFERROR(__xludf.DUMMYFUNCTION("IF(OR($U12="""",COUNTIF($I:$I,IFERROR(unique(filter(Prod_Prop!$H:$H,Prod_Prop!$G:$G=$U12,Prod_Prop!$E:$E=AB$1)),""Check""))=0),"""",IFERROR(unique(filter(Prod_Prop!$H:$H,Prod_Prop!$G:$G=$U12,Prod_Prop!$E:$E=AB$1)),""""))"),"") | AC12: =IF(AB12="","",SUMIFS(Prod_Prop!$J:$J,Prod_Prop!$B:$B,$Q12,Prod_Prop!$H:$H,AB12,Prod_Prop!$I:$I,AC$1)*IF(AB12="Peso",$R12,1)) | AD12: =IF(AB12="","",SUMIFS(Prod_Prop!$J:$J,Prod_Prop!$B:$B,$Q12,Prod_Prop!$H:$H,AB12,Prod_Prop!$I:$I,AD$1)*IF(AB12="Peso",$R12,1))
A13: {=IF(COUNTIF(A$1:A12,Cotizador!F$2)=maxifs(Familias!E:E,Familias!D:D,Cotizador!F$2),IF(COUNTIF(A$1:A12,XLOOKUP(Cotizador!F$2,Implementos!B:B,Implementos!C:C,"",0,1))=SUMIFS(Implementos!D:D,Implementos!B:B,Cotizador!F$2,Implementos!C:C,XLOOKUP(Cotizador!F$2,Implementos!B:B,Implementos!C:C,"",0,1)),"",XLOOKUP(Cotizador!F$2,Implementos!B:B,Implementos!C:C,"",0,1)),Cotizador!F$2)} | B13: =IF(A13="","",COUNTIF(A$1:A13,A13)) | C13: {=IF(B13="","",IF(A13=XLOOKUP(A$2,Implementos!B:B,Implementos!C:C,"",0,1),B13+maxifs(B$1:B12,A$1:A12,A$2),B13))} | D13: =IF(B13="","", COUNTIFS(Productos!F:F,A13,Productos!H:H,B13)+IF(F13="SI",0,1)) | E13: =IFERROR(__xludf.DUMMYFUNCTION("IF($B13="""","""",INDEX(filter(Familias!F:F,Familias!$D:$D=$A13,Familias!$E:$E=$B13),1))"),"") | F13: =IFERROR(__xludf.DUMMYFUNCTION("IF($B13="""","""",INDEX(filter(Familias!G:G,Familias!$D:$D=$A13,Familias!$E:$E=$B13),1))"),"") | G13: {=IF(C13=1,XLOOKUP(C13,Cotizador!D:D,Cotizador!E:E,"",0,1),"")} | J13: =IF(I13="","",SUMIF(Cotizador!I$1:V$1,I13,Cotizador!I$2:V$2)) | L13: {=IF(COUNTIF(L$1:L12,A$2)=SUMIF(A:A,A$2,D:D),IF(COUNTIF(L$1:L12,XLOOKUP(A$2,Implementos!B:B,Implementos!C:C,"",0,1))=SUMIF(A:A,XLOOKUP(A$2,Implementos!B:B,Implementos!C:C,"",0,1),D:D),"",XLOOKUP(A$2,Implementos!B:B,Implementos!C:C,"",0,1)),A$2)} -> Acoplados Rurales | M13: =IF(L13="","",max(M$1:M12)+1) -> 12 | N13: =IF(L13="","",IF(N12="Orden",1,IF(COUNTIFS(N$1:N12,N12,L$1:L12,L13)=SUMIFS(D:D,B:B,N12,A:A,L13),IF(N12=maxifs(B:B,A:A,L13),"",maxifs(N$1:N12,L$1:L12,L13)+1),N12))) -> 1 | O13: =IF(N13="","",SUMIFS(C:C,B:B,N13,A:A,L13)) -> 1 | P13: =IF(N13="","",COUNTIFS(N$1:N13,N13,L$1:L13,L13)) -> 12 | Q13: =IF(U13="","",SUMIF(Productos!E:E,U13,Productos!A:A)) -> 56 | R13: {=IF(L13="","", max(1,SUMIF(I:I,XLOOKUP(U13,Productos!E:E,Productos!G:G,"",0,1),J:J)))} -> 1 | S13: =IF(Q13="","",IF(SUMIFS(Compat_Vetado!D:D,Compat_Vetado!B:B,SUM(G:G),Compat_Vetado!C:C,Q13)=1,"SI",IF(OR(SUMIF(Cotizador!E:E,Q13,Cotizador!G:G)>0,SUMIFS(Compat_Vetado!D:D,Compat_Vetado!B:B,SUM(G:G),Compat_Vetado!C:C,Q13)=-1),"NO",""))) -> NO | T13: =IF(Q13="","",IF(S13="SI","x",IF(S13="NO","",IF(AND(OR(V13="",AND(W13<=SUMIF(I:I,V13,J:J),SUMIF(I:I,V13,J:J)<=X13)),OR(Y13="",AND(Z13<=SUMIF(I:I,Y13,J:J),SUMIF(I:I,Y13,J:J)<=AA13)),OR(AB13="",AND(AC13<=SUMIF(I:I,AB13,J:J),SUMIF(I:I,AB13,J:J)<=AD13))),"x","")))) | U13: =IFERROR(__xludf.DUMMYFUNCTION("IF(P13="""","""",IFERROR(INDEX(filter(Productos!E:E,Productos!F:F=L13,Productos!H:H=N13),P13),IF(M13=SUM(D:D),""Finalizar"",""-"")))"),"Tanque Combustible 4000 lts Alto") -> Tanque Combustible 4000 lts Alto | V13: =IFERROR(__xludf.DUMMYFUNCTION("IF(OR($U13="""",COUNTIF($I:$I,IFERROR(unique(filter(Prod_Prop!$H:$H,Prod_Prop!$G:$G=$U13,Prod_Prop!$E:$E=V$1)),""Check""))=0),"""",IFERROR(unique(filter(Prod_Prop!$H:$H,Prod_Prop!$G:$G=$U13,Prod_Prop!$E:$E=V$1)),""""))"),"") | W13: =IF(V13="","",SUMIFS(Prod_Prop!$J:$J,Prod_Prop!$B:$B,$Q13,Prod_Prop!$H:$H,V13,Prod_Prop!$I:$I,W$1)*IF(V13="Peso",$R13,1)) | X13: =IF(V13="","",SUMIFS(Prod_Prop!$J:$J,Prod_Prop!$B:$B,$Q13,Prod_Prop!$H:$H,V13,Prod_Prop!$I:$I,X$1)*IF(V13="Peso",$R13,1)) | Y13: =IFERROR(__xludf.DUMMYFUNCTION("IF(OR($U13="""",COUNTIF($I:$I,IFERROR(unique(filter(Prod_Prop!$H:$H,Prod_Prop!$G:$G=$U13,Prod_Prop!$E:$E=Y$1)),""Check""))=0),"""",IFERROR(unique(filter(Prod_Prop!$H:$H,Prod_Prop!$G:$G=$U13,Prod_Prop!$E:$E=Y$1)),""""))"),"") | Z13: =IF(Y13="","",SUMIFS(Prod_Prop!$J:$J,Prod_Prop!$B:$B,$Q13,Prod_Prop!$H:$H,Y13,Prod_Prop!$I:$I,Z$1)*IF(Y13="Peso",$R13,1)) | AA13: =IF(Y13="","",SUMIFS(Prod_Prop!$J:$J,Prod_Prop!$B:$B,$Q13,Prod_Prop!$H:$H,Y13,Prod_Prop!$I:$I,AA$1)*IF(Y13="Peso",$R13,1)) | AB13: =IFERROR(__xludf.DUMMYFUNCTION("IF(OR($U13="""",COUNTIF($I:$I,IFERROR(unique(filter(Prod_Prop!$H:$H,Prod_Prop!$G:$G=$U13,Prod_Prop!$E:$E=AB$1)),""Check""))=0),"""",IFERROR(unique(filter(Prod_Prop!$H:$H,Prod_Prop!$G:$G=$U13,Prod_Prop!$E:$E=AB$1)),""""))"),"") | AC13: =IF(AB13="","",SUMIFS(Prod_Prop!$J:$J,Prod_Prop!$B:$B,$Q13,Prod_Prop!$H:$H,AB13,Prod_Prop!$I:$I,AC$1)*IF(AB13="Peso",$R13,1)) | AD13: =IF(AB13="","",SUMIFS(Prod_Prop!$J:$J,Prod_Prop!$B:$B,$Q13,Prod_Prop!$H:$H,AB13,Prod_Prop!$I:$I,AD$1)*IF(AB13="Peso",$R13,1))
A14: {=IF(COUNTIF(A$1:A13,Cotizador!F$2)=maxifs(Familias!E:E,Familias!D:D,Cotizador!F$2),IF(COUNTIF(A$1:A13,XLOOKUP(Cotizador!F$2,Implementos!B:B,Implementos!C:C,"",0,1))=SUMIFS(Implementos!D:D,Implementos!B:B,Cotizador!F$2,Implementos!C:C,XLOOKUP(Cotizador!F$2,Implementos!B:B,Implementos!C:C,"",0,1)),"",XLOOKUP(Cotizador!F$2,Implementos!B:B,Implementos!C:C,"",0,1)),Cotizador!F$2)} | B14: =IF(A14="","",COUNTIF(A$1:A14,A14)) | C14: {=IF(B14="","",IF(A14=XLOOKUP(A$2,Implementos!B:B,Implementos!C:C,"",0,1),B14+maxifs(B$1:B13,A$1:A13,A$2),B14))} | D14: =IF(B14="","", COUNTIFS(Productos!F:F,A14,Productos!H:H,B14)+IF(F14="SI",0,1)) | E14: =IFERROR(__xludf.DUMMYFUNCTION("IF($B14="""","""",INDEX(filter(Familias!F:F,Familias!$D:$D=$A14,Familias!$E:$E=$B14),1))"),"") | F14: =IFERROR(__xludf.DUMMYFUNCTION("IF($B14="""","""",INDEX(filter(Familias!G:G,Familias!$D:$D=$A14,Familias!$E:$E=$B14),1))"),"") | G14: {=IF(C14=1,XLOOKUP(C14,Cotizador!D:D,Cotizador!E:E,"",0,1),"")} | J14: =IF(I14="","",SUMIF(Cotizador!I$1:V$1,I14,Cotizador!I$2:V$2)) | L14: {=IF(COUNTIF(L$1:L13,A$2)=SUMIF(A:A,A$2,D:D),IF(COUNTIF(L$1:L13,XLOOKUP(A$2,Implementos!B:B,Implementos!C:C,"",0,1))=SUMIF(A:A,XLOOKUP(A$2,Implementos!B:B,Implementos!C:C,"",0,1),D:D),"",XLOOKUP(A$2,Implementos!B:B,Implementos!C:C,"",0,1)),A$2)} -> Acoplados Rurales | M14: =IF(L14="","",max(M$1:M13)+1) -> 13 | N14: =IF(L14="","",IF(N13="Orden",1,IF(COUNTIFS(N$1:N13,N13,L$1:L13,L14)=SUMIFS(D:D,B:B,N13,A:A,L14),IF(N13=maxifs(B:B,A:A,L14),"",maxifs(N$1:N13,L$1:L13,L14)+1),N13))) -> 1 | O14: =IF(N14="","",SUMIFS(C:C,B:B,N14,A:A,L14)) -> 1 | P14: =IF(N14="","",COUNTIFS(N$1:N14,N14,L$1:L14,L14)) -> 13 | Q14: =IF(U14="","",SUMIF(Productos!E:E,U14,Productos!A:A)) -> 92 | R14: {=IF(L14="","", max(1,SUMIF(I:I,XLOOKUP(U14,Productos!E:E,Productos!G:G,"",0,1),J:J)))} -> 1 | S14: =IF(Q14="","",IF(SUMIFS(Compat_Vetado!D:D,Compat_Vetado!B:B,SUM(G:G),Compat_Vetado!C:C,Q14)=1,"SI",IF(OR(SUMIF(Cotizador!E:E,Q14,Cotizador!G:G)>0,SUMIFS(Compat_Vetado!D:D,Compat_Vetado!B:B,SUM(G:G),Compat_Vetado!C:C,Q14)=-1),"NO",""))) -> NO | T14: =IF(Q14="","",IF(S14="SI","x",IF(S14="NO","",IF(AND(OR(V14="",AND(W14<=SUMIF(I:I,V14,J:J),SUMIF(I:I,V14,J:J)<=X14)),OR(Y14="",AND(Z14<=SUMIF(I:I,Y14,J:J),SUMIF(I:I,Y14,J:J)<=AA14)),OR(AB14="",AND(AC14<=SUMIF(I:I,AB14,J:J),SUMIF(I:I,AB14,J:J)<=AD14))),"x","")))) | U14: =IFERROR(__xludf.DUMMYFUNCTION("IF(P14="""","""",IFERROR(INDEX(filter(Productos!E:E,Productos!F:F=L14,Productos!H:H=N14),P14),IF(M14=SUM(D:D),""Finalizar"",""-"")))"),"Tanque Plastico Horizontal 750 Lts") -> Tanque Plastico Horizontal 750 Lts | V14: =IFERROR(__xludf.DUMMYFUNCTION("IF(OR($U14="""",COUNTIF($I:$I,IFERROR(unique(filter(Prod_Prop!$H:$H,Prod_Prop!$G:$G=$U14,Prod_Prop!$E:$E=V$1)),""Check""))=0),"""",IFERROR(unique(filter(Prod_Prop!$H:$H,Prod_Prop!$G:$G=$U14,Prod_Prop!$E:$E=V$1)),""""))"),"") | W14: =IF(V14="","",SUMIFS(Prod_Prop!$J:$J,Prod_Prop!$B:$B,$Q14,Prod_Prop!$H:$H,V14,Prod_Prop!$I:$I,W$1)*IF(V14="Peso",$R14,1)) | X14: =IF(V14="","",SUMIFS(Prod_Prop!$J:$J,Prod_Prop!$B:$B,$Q14,Prod_Prop!$H:$H,V14,Prod_Prop!$I:$I,X$1)*IF(V14="Peso",$R14,1)) | Y14: =IFERROR(__xludf.DUMMYFUNCTION("IF(OR($U14="""",COUNTIF($I:$I,IFERROR(unique(filter(Prod_Prop!$H:$H,Prod_Prop!$G:$G=$U14,Prod_Prop!$E:$E=Y$1)),""Check""))=0),"""",IFERROR(unique(filter(Prod_Prop!$H:$H,Prod_Prop!$G:$G=$U14,Prod_Prop!$E:$E=Y$1)),""""))"),"") | Z14: =IF(Y14="","",SUMIFS(Prod_Prop!$J:$J,Prod_Prop!$B:$B,$Q14,Prod_Prop!$H:$H,Y14,Prod_Prop!$I:$I,Z$1)*IF(Y14="Peso",$R14,1)) | AA14: =IF(Y14="","",SUMIFS(Prod_Prop!$J:$J,Prod_Prop!$B:$B,$Q14,Prod_Prop!$H:$H,Y14,Prod_Prop!$I:$I,AA$1)*IF(Y14="Peso",$R14,1)) | AB14: =IFERROR(__xludf.DUMMYFUNCTION("IF(OR($U14="""",COUNTIF($I:$I,IFERROR(unique(filter(Prod_Prop!$H:$H,Prod_Prop!$G:$G=$U14,Prod_Prop!$E:$E=AB$1)),""Check""))=0),"""",IFERROR(unique(filter(Prod_Prop!$H:$H,Prod_Prop!$G:$G=$U14,Prod_Prop!$E:$E=AB$1)),""""))"),"") | AC14: =IF(AB14="","",SUMIFS(Prod_Prop!$J:$J,Prod_Prop!$B:$B,$Q14,Prod_Prop!$H:$H,AB14,Prod_Prop!$I:$I,AC$1)*IF(AB14="Peso",$R14,1)) | AD14: =IF(AB14="","",SUMIFS(Prod_Prop!$J:$J,Prod_Prop!$B:$B,$Q14,Prod_Prop!$H:$H,AB14,Prod_Prop!$I:$I,AD$1)*IF(AB14="Peso",$R14,1))
A15: {=IF(COUNTIF(A$1:A14,Cotizador!F$2)=maxifs(Familias!E:E,Familias!D:D,Cotizador!F$2),IF(COUNTIF(A$1:A14,XLOOKUP(Cotizador!F$2,Implementos!B:B,Implementos!C:C,"",0,1))=SUMIFS(Implementos!D:D,Implementos!B:B,Cotizador!F$2,Implementos!C:C,XLOOKUP(Cotizador!F$2,Implementos!B:B,Implementos!C:C,"",0,1)),"",XLOOKUP(Cotizador!F$2,Implementos!B:B,Implementos!C:C,"",0,1)),Cotizador!F$2)} | B15: =IF(A15="","",COUNTIF(A$1:A15,A15)) | C15: {=IF(B15="","",IF(A15=XLOOKUP(A$2,Implementos!B:B,Implementos!C:C,"",0,1),B15+maxifs(B$1:B14,A$1:A14,A$2),B15))} | D15: =IF(B15="","", COUNTIFS(Productos!F:F,A15,Productos!H:H,B15)+IF(F15="SI",0,1)) | E15: =IFERROR(__xludf.DUMMYFUNCTION("IF($B15="""","""",INDEX(filter(Familias!F:F,Familias!$D:$D=$A15,Familias!$E:$E=$B15),1))"),"") | F15: =IFERROR(__xludf.DUMMYFUNCTION("IF($B15="""","""",INDEX(filter(Familias!G:G,Familias!$D:$D=$A15,Familias!$E:$E=$B15),1))"),"") | G15: {=IF(C15=1,XLOOKUP(C15,Cotizador!D:D,Cotizador!E:E,"",0,1),"")} | J15: =IF(I15="","",SUMIF(Cotizador!I$1:V$1,I15,Cotizador!I$2:V$2)) | L15: {=IF(COUNTIF(L$1:L14,A$2)=SUMIF(A:A,A$2,D:D),IF(COUNTIF(L$1:L14,XLOOKUP(A$2,Implementos!B:B,Implementos!C:C,"",0,1))=SUMIF(A:A,XLOOKUP(A$2,Implementos!B:B,Implementos!C:C,"",0,1),D:D),"",XLOOKUP(A$2,Implementos!B:B,Implementos!C:C,"",0,1)),A$2)} -> Acoplados Rurales | M15: =IF(L15="","",max(M$1:M14)+1) -> 14 | N15: =IF(L15="","",IF(N14="Orden",1,IF(COUNTIFS(N$1:N14,N14,L$1:L14,L15)=SUMIFS(D:D,B:B,N14,A:A,L15),IF(N14=maxifs(B:B,A:A,L15),"",maxifs(N$1:N14,L$1:L14,L15)+1),N14))) -> 1 | O15: =IF(N15="","",SUMIFS(C:C,B:B,N15,A:A,L15)) -> 1 | P15: =IF(N15="","",COUNTIFS(N$1:N15,N15,L$1:L15,L15)) -> 14 | Q15: =IF(U15="","",SUMIF(Productos!E:E,U15,Productos!A:A)) -> 93 | R15: {=IF(L15="","", max(1,SUMIF(I:I,XLOOKUP(U15,Productos!E:E,Productos!G:G,"",0,1),J:J)))} -> 1 | S15: =IF(Q15="","",IF(SUMIFS(Compat_Vetado!D:D,Compat_Vetado!B:B,SUM(G:G),Compat_Vetado!C:C,Q15)=1,"SI",IF(OR(SUMIF(Cotizador!E:E,Q15,Cotizador!G:G)>0,SUMIFS(Compat_Vetado!D:D,Compat_Vetado!B:B,SUM(G:G),Compat_Vetado!C:C,Q15)=-1),"NO",""))) | T15: =IF(Q15="","",IF(S15="SI","x",IF(S15="NO","",IF(AND(OR(V15="",AND(W15<=SUMIF(I:I,V15,J:J),SUMIF(I:I,V15,J:J)<=X15)),OR(Y15="",AND(Z15<=SUMIF(I:I,Y15,J:J),SUMIF(I:I,Y15,J:J)<=AA15)),OR(AB15="",AND(AC15<=SUMIF(I:I,AB15,J:J),SUMIF(I:I,AB15,J:J)<=AD15))),"x","")))) -> x | U15: =IFERROR(__xludf.DUMMYFUNCTION("IF(P15="""","""",IFERROR(INDEX(filter(Productos!E:E,Productos!F:F=L15,Productos!H:H=N15),P15),IF(M15=SUM(D:D),""Finalizar"",""-"")))"),"Medio Tanque Plastico Superior 700 Lts") -> Medio Tanque Plastico Superior 700 Lts | V15: =IFERROR(__xludf.DUMMYFUNCTION("IF(OR($U15="""",COUNTIF($I:$I,IFERROR(unique(filter(Prod_Prop!$H:$H,Prod_Prop!$G:$G=$U15,Prod_Prop!$E:$E=V$1)),""Check""))=0),"""",IFERROR(unique(filter(Prod_Prop!$H:$H,Prod_Prop!$G:$G=$U15,Prod_Prop!$E:$E=V$1)),""""))"),"") | W15: =IF(V15="","",SUMIFS(Prod_Prop!$J:$J,Prod_Prop!$B:$B,$Q15,Prod_Prop!$H:$H,V15,Prod_Prop!$I:$I,W$1)*IF(V15="Peso",$R15,1)) | X15: =IF(V15="","",SUMIFS(Prod_Prop!$J:$J,Prod_Prop!$B:$B,$Q15,Prod_Prop!$H:$H,V15,Prod_Prop!$I:$I,X$1)*IF(V15="Peso",$R15,1)) | Y15: =IFERROR(__xludf.DUMMYFUNCTION("IF(OR($U15="""",COUNTIF($I:$I,IFERROR(unique(filter(Prod_Prop!$H:$H,Prod_Prop!$G:$G=$U15,Prod_Prop!$E:$E=Y$1)),""Check""))=0),"""",IFERROR(unique(filter(Prod_Prop!$H:$H,Prod_Prop!$G:$G=$U15,Prod_Prop!$E:$E=Y$1)),""""))"),"") | Z15: =IF(Y15="","",SUMIFS(Prod_Prop!$J:$J,Prod_Prop!$B:$B,$Q15,Prod_Prop!$H:$H,Y15,Prod_Prop!$I:$I,Z$1)*IF(Y15="Peso",$R15,1)) | AA15: =IF(Y15="","",SUMIFS(Prod_Prop!$J:$J,Prod_Prop!$B:$B,$Q15,Prod_Prop!$H:$H,Y15,Prod_Prop!$I:$I,AA$1)*IF(Y15="Peso",$R15,1)) | AB15: =IFERROR(__xludf.DUMMYFUNCTION("IF(OR($U15="""",COUNTIF($I:$I,IFERROR(unique(filter(Prod_Prop!$H:$H,Prod_Prop!$G:$G=$U15,Prod_Prop!$E:$E=AB$1)),""Check""))=0),"""",IFERROR(unique(filter(Prod_Prop!$H:$H,Prod_Prop!$G:$G=$U15,Prod_Prop!$E:$E=AB$1)),""""))"),"") | AC15: =IF(AB15="","",SUMIFS(Prod_Prop!$J:$J,Prod_Prop!$B:$B,$Q15,Prod_Prop!$H:$H,AB15,Prod_Prop!$I:$I,AC$1)*IF(AB15="Peso",$R15,1)) | AD15: =IF(AB15="","",SUMIFS(Prod_Prop!$J:$J,Prod_Prop!$B:$B,$Q15,Prod_Prop!$H:$H,AB15,Prod_Prop!$I:$I,AD$1)*IF(AB15="Peso",$R15,1))
A16: {=IF(COUNTIF(A$1:A15,Cotizador!F$2)=maxifs(Familias!E:E,Familias!D:D,Cotizador!F$2),IF(COUNTIF(A$1:A15,XLOOKUP(Cotizador!F$2,Implementos!B:B,Implementos!C:C,"",0,1))=SUMIFS(Implementos!D:D,Implementos!B:B,Cotizador!F$2,Implementos!C:C,XLOOKUP(Cotizador!F$2,Implementos!B:B,Implementos!C:C,"",0,1)),"",XLOOKUP(Cotizador!F$2,Implementos!B:B,Implementos!C:C,"",0,1)),Cotizador!F$2)} | B16: =IF(A16="","",COUNTIF(A$1:A16,A16)) | C16: {=IF(B16="","",IF(A16=XLOOKUP(A$2,Implementos!B:B,Implementos!C:C,"",0,1),B16+maxifs(B$1:B15,A$1:A15,A$2),B16))} | D16: =IF(B16="","", COUNTIFS(Productos!F:F,A16,Productos!H:H,B16)+IF(F16="SI",0,1)) | E16: =IFERROR(__xludf.DUMMYFUNCTION("IF($B16="""","""",INDEX(filter(Familias!F:F,Familias!$D:$D=$A16,Familias!$E:$E=$B16),1))"),"") | F16: =IFERROR(__xludf.DUMMYFUNCTION("IF($B16="""","""",INDEX(filter(Familias!G:G,Familias!$D:$D=$A16,Familias!$E:$E=$B16),1))"),"") | G16: {=IF(C16=1,XLOOKUP(C16,Cotizador!D:D,Cotizador!E:E,"",0,1),"")} | J16: =IF(I16="","",SUMIF(Cotizador!I$1:V$1,I16,Cotizador!I$2:V$2)) | L16: {=IF(COUNTIF(L$1:L15,A$2)=SUMIF(A:A,A$2,D:D),IF(COUNTIF(L$1:L15,XLOOKUP(A$2,Implementos!B:B,Implementos!C:C,"",0,1))=SUMIF(A:A,XLOOKUP(A$2,Implementos!B:B,Implementos!C:C,"",0,1),D:D),"",XLOOKUP(A$2,Implementos!B:B,Implementos!C:C,"",0,1)),A$2)} -> Acoplados Rurales | M16: =IF(L16="","",max(M$1:M15)+1) -> 15 | N16: =IF(L16="","",IF(N15="Orden",1,IF(COUNTIFS(N$1:N15,N15,L$1:L15,L16)=SUMIFS(D:D,B:B,N15,A:A,L16),IF(N15=maxifs(B:B,A:A,L16),"",maxifs(N$1:N15,L$1:L15,L16)+1),N15))) -> 1 | O16: =IF(N16="","",SUMIFS(C:C,B:B,N16,A:A,L16)) -> 1 | P16: =IF(N16="","",COUNTIFS(N$1:N16,N16,L$1:L16,L16)) -> 15 | Q16: =IF(U16="","",SUMIF(Productos!E:E,U16,Productos!A:A)) -> 118 | R16: {=IF(L16="","", max(1,SUMIF(I:I,XLOOKUP(U16,Productos!E:E,Productos!G:G,"",0,1),J:J)))} -> 1 | S16: =IF(Q16="","",IF(SUMIFS(Compat_Vetado!D:D,Compat_Vetado!B:B,SUM(G:G),Compat_Vetado!C:C,Q16)=1,"SI",IF(OR(SUMIF(Cotizador!E:E,Q16,Cotizador!G:G)>0,SUMIFS(Compat_Vetado!D:D,Compat_Vetado!B:B,SUM(G:G),Compat_Vetado!C:C,Q16)=-1),"NO",""))) | T16: =IF(Q16="","",IF(S16="SI","x",IF(S16="NO","",IF(AND(OR(V16="",AND(W16<=SUMIF(I:I,V16,J:J),SUMIF(I:I,V16,J:J)<=X16)),OR(Y16="",AND(Z16<=SUMIF(I:I,Y16,J:J),SUMIF(I:I,Y16,J:J)<=AA16)),OR(AB16="",AND(AC16<=SUMIF(I:I,AB16,J:J),SUMIF(I:I,AB16,J:J)<=AD16))),"x","")))) -> x | U16: =IFERROR(__xludf.DUMMYFUNCTION("IF(P16="""","""",IFERROR(INDEX(filter(Productos!E:E,Productos!F:F=L16,Productos!H:H=N16),P16),IF(M16=SUM(D:D),""Finalizar"",""-"")))"),"Plataforma Playo 4.00 x 1.90 x 0.45 Lateral Simple Baranda Fija") -> Plataforma Playo 4.00 x 1.90 x 0.45 Lateral Simple Baranda Fija | V16: =IFERROR(__xludf.DUMMYFUNCTION("IF(OR($U16="""",COUNTIF($I:$I,IFERROR(unique(filter(Prod_Prop!$H:$H,Prod_Prop!$G:$G=$U16,Prod_Prop!$E:$E=V$1)),""Check""))=0),"""",IFERROR(unique(filter(Prod_Prop!$H:$H,Prod_Prop!$G:$G=$U16,Prod_Prop!$E:$E=V$1)),""""))"),"") | W16: =IF(V16="","",SUMIFS(Prod_Prop!$J:$J,Prod_Prop!$B:$B,$Q16,Prod_Prop!$H:$H,V16,Prod_Prop!$I:$I,W$1)*IF(V16="Peso",$R16,1)) | X16: =IF(V16="","",SUMIFS(Prod_Prop!$J:$J,Prod_Prop!$B:$B,$Q16,Prod_Prop!$H:$H,V16,Prod_Prop!$I:$I,X$1)*IF(V16="Peso",$R16,1)) | Y16: =IFERROR(__xludf.DUMMYFUNCTION("IF(OR($U16="""",COUNTIF($I:$I,IFERROR(unique(filter(Prod_Prop!$H:$H,Prod_Prop!$G:$G=$U16,Prod_Prop!$E:$E=Y$1)),""Check""))=0),"""",IFERROR(unique(filter(Prod_Prop!$H:$H,Prod_Prop!$G:$G=$U16,Prod_Prop!$E:$E=Y$1)),""""))"),"") | Z16: =IF(Y16="","",SUMIFS(Prod_Prop!$J:$J,Prod_Prop!$B:$B,$Q16,Prod_Prop!$H:$H,Y16,Prod_Prop!$I:$I,Z$1)*IF(Y16="Peso",$R16,1)) | AA16: =IF(Y16="","",SUMIFS(Prod_Prop!$J:$J,Prod_Prop!$B:$B,$Q16,Prod_Prop!$H:$H,Y16,Prod_Prop!$I:$I,AA$1)*IF(Y16="Peso",$R16,1)) | AB16: =IFERROR(__xludf.DUMMYFUNCTION("IF(OR($U16="""",COUNTIF($I:$I,IFERROR(unique(filter(Prod_Prop!$H:$H,Prod_Prop!$G:$G=$U16,Prod_Prop!$E:$E=AB$1)),""Check""))=0),"""",IFERROR(unique(filter(Prod_Prop!$H:$H,Prod_Prop!$G:$G=$U16,Prod_Prop!$E:$E=AB$1)),""""))"),"") | AC16: =IF(AB16="","",SUMIFS(Prod_Prop!$J:$J,Prod_Prop!$B:$B,$Q16,Prod_Prop!$H:$H,AB16,Prod_Prop!$I:$I,AC$1)*IF(AB16="Peso",$R16,1)) | AD16: =IF(AB16="","",SUMIFS(Prod_Prop!$J:$J,Prod_Prop!$B:$B,$Q16,Prod_Prop!$H:$H,AB16,Prod_Prop!$I:$I,AD$1)*IF(AB16="Peso",$R16,1))
A17: {=IF(COUNTIF(A$1:A16,Cotizador!F$2)=maxifs(Familias!E:E,Familias!D:D,Cotizador!F$2),IF(COUNTIF(A$1:A16,XLOOKUP(Cotizador!F$2,Implementos!B:B,Implementos!C:C,"",0,1))=SUMIFS(Implementos!D:D,Implementos!B:B,Cotizador!F$2,Implementos!C:C,XLOOKUP(Cotizador!F$2,Implementos!B:B,Implementos!C:C,"",0,1)),"",XLOOKUP(Cotizador!F$2,Implementos!B:B,Implementos!C:C,"",0,1)),Cotizador!F$2)} | B17: =IF(A17="","",COUNTIF(A$1:A17,A17)) | C17: {=IF(B17="","",IF(A17=XLOOKUP(A$2,Implementos!B:B,Implementos!C:C,"",0,1),B17+maxifs(B$1:B16,A$1:A16,A$2),B17))} | D17: =IF(B17="","", COUNTIFS(Productos!F:F,A17,Productos!H:H,B17)+IF(F17="SI",0,1)) | E17: =IFERROR(__xludf.DUMMYFUNCTION("IF($B17="""","""",INDEX(filter(Familias!F:F,Familias!$D:$D=$A17,Familias!$E:$E=$B17),1))"),"") | F17: =IFERROR(__xludf.DUMMYFUNCTION("IF($B17="""","""",INDEX(filter(Familias!G:G,Familias!$D:$D=$A17,Familias!$E:$E=$B17),1))"),"") | G17: {=IF(C17=1,XLOOKUP(C17,Cotizador!D:D,Cotizador!E:E,"",0,1),"")} | J17: =IF(I17="","",SUMIF(Cotizador!I$1:V$1,I17,Cotizador!I$2:V$2)) | L17: {=IF(COUNTIF(L$1:L16,A$2)=SUMIF(A:A,A$2,D:D),IF(COUNTIF(L$1:L16,XLOOKUP(A$2,Implementos!B:B,Implementos!C:C,"",0,1))=SUMIF(A:A,XLOOKUP(A$2,Implementos!B:B,Implementos!C:C,"",0,1),D:D),"",XLOOKUP(A$2,Implementos!B:B,Implementos!C:C,"",0,1)),A$2)} -> Acoplados Rurales | M17: =IF(L17="","",max(M$1:M16)+1) -> 16 | N17: =IF(L17="","",IF(N16="Orden",1,IF(COUNTIFS(N$1:N16,N16,L$1:L16,L17)=SUMIFS(D:D,B:B,N16,A:A,L17),IF(N16=maxifs(B:B,A:A,L17),"",maxifs(N$1:N16,L$1:L16,L17)+1),N16))) -> 1 | O17: =IF(N17="","",SUMIFS(C:C,B:B,N17,A:A,L17)) -> 1 | P17: =IF(N17="","",COUNTIFS(N$1:N17,N17,L$1:L17,L17)) -> 16 | Q17: =IF(U17="","",SUMIF(Productos!E:E,U17,Productos!A:A)) -> 119 | R17: {=IF(L17="","", max(1,SUMIF(I:I,XLOOKUP(U17,Productos!E:E,Productos!G:G,"",0,1),J:J)))} -> 1 | S17: =IF(Q17="","",IF(SUMIFS(Compat_Vetado!D:D,Compat_Vetado!B:B,SUM(G:G),Compat_Vetado!C:C,Q17)=1,"SI",IF(OR(SUMIF(Cotizador!E:E,Q17,Cotizador!G:G)>0,SUMIFS(Compat_Vetado!D:D,Compat_Vetado!B:B,SUM(G:G),Compat_Vetado!C:C,Q17)=-1),"NO",""))) | T17: =IF(Q17="","",IF(S17="SI","x",IF(S17="NO","",IF(AND(OR(V17="",AND(W17<=SUMIF(I:I,V17,J:J),SUMIF(I:I,V17,J:J)<=X17)),OR(Y17="",AND(Z17<=SUMIF(I:I,Y17,J:J),SUMIF(I:I,Y17,J:J)<=AA17)),OR(AB17="",AND(AC17<=SUMIF(I:I,AB17,J:J),SUMIF(I:I,AB17,J:J)<=AD17))),"x","")))) -> x | U17: =IFERROR(__xludf.DUMMYFUNCTION("IF(P17="""","""",IFERROR(INDEX(filter(Productos!E:E,Productos!F:F=L17,Productos!H:H=N17),P17),IF(M17=SUM(D:D),""Finalizar"",""-"")))"),"Plataforma Playo 4.00 x 1.90 x 0.45 Lateral Simple Baranda Ventilada") -> Plataforma Playo 4.00 x 1.90 x 0.45 Lateral Simple Baranda Ventilada | V17: =IFERROR(__xludf.DUMMYFUNCTION("IF(OR($U17="""",COUNTIF($I:$I,IFERROR(unique(filter(Prod_Prop!$H:$H,Prod_Prop!$G:$G=$U17,Prod_Prop!$E:$E=V$1)),""Check""))=0),"""",IFERROR(unique(filter(Prod_Prop!$H:$H,Prod_Prop!$G:$G=$U17,Prod_Prop!$E:$E=V$1)),""""))"),"") | W17: =IF(V17="","",SUMIFS(Prod_Prop!$J:$J,Prod_Prop!$B:$B,$Q17,Prod_Prop!$H:$H,V17,Prod_Prop!$I:$I,W$1)*IF(V17="Peso",$R17,1)) | X17: =IF(V17="","",SUMIFS(Prod_Prop!$J:$J,Prod_Prop!$B:$B,$Q17,Prod_Prop!$H:$H,V17,Prod_Prop!$I:$I,X$1)*IF(V17="Peso",$R17,1)) | Y17: =IFERROR(__xludf.DUMMYFUNCTION("IF(OR($U17="""",COUNTIF($I:$I,IFERROR(unique(filter(Prod_Prop!$H:$H,Prod_Prop!$G:$G=$U17,Prod_Prop!$E:$E=Y$1)),""Check""))=0),"""",IFERROR(unique(filter(Prod_Prop!$H:$H,Prod_Prop!$G:$G=$U17,Prod_Prop!$E:$E=Y$1)),""""))"),"") | Z17: =IF(Y17="","",SUMIFS(Prod_Prop!$J:$J,Prod_Prop!$B:$B,$Q17,Prod_Prop!$H:$H,Y17,Prod_Prop!$I:$I,Z$1)*IF(Y17="Peso",$R17,1)) | AA17: =IF(Y17="","",SUMIFS(Prod_Prop!$J:$J,Prod_Prop!$B:$B,$Q17,Prod_Prop!$H:$H,Y17,Prod_Prop!$I:$I,AA$1)*IF(Y17="Peso",$R17,1)) | AB17: =IFERROR(__xludf.DUMMYFUNCTION("IF(OR($U17="""",COUNTIF($I:$I,IFERROR(unique(filter(Prod_Prop!$H:$H,Prod_Prop!$G:$G=$U17,Prod_Prop!$E:$E=AB$1)),""Check""))=0),"""",IFERROR(unique(filter(Prod_Prop!$H:$H,Prod_Prop!$G:$G=$U17,Prod_Prop!$E:$E=AB$1)),""""))"),"") | AC17: =IF(AB17="","",SUMIFS(Prod_Prop!$J:$J,Prod_Prop!$B:$B,$Q17,Prod_Prop!$H:$H,AB17,Prod_Prop!$I:$I,AC$1)*IF(AB17="Peso",$R17,1)) | AD17: =IF(AB17="","",SUMIFS(Prod_Prop!$J:$J,Prod_Prop!$B:$B,$Q17,Prod_Prop!$H:$H,AB17,Prod_Prop!$I:$I,AD$1)*IF(AB17="Peso",$R17,1))
A18: {=IF(COUNTIF(A$1:A17,Cotizador!F$2)=maxifs(Familias!E:E,Familias!D:D,Cotizador!F$2),IF(COUNTIF(A$1:A17,XLOOKUP(Cotizador!F$2,Implementos!B:B,Implementos!C:C,"",0,1))=SUMIFS(Implementos!D:D,Implementos!B:B,Cotizador!F$2,Implementos!C:C,XLOOKUP(Cotizador!F$2,Implementos!B:B,Implementos!C:C,"",0,1)),"",XLOOKUP(Cotizador!F$2,Implementos!B:B,Implementos!C:C,"",0,1)),Cotizador!F$2)} | B18: =IF(A18="","",COUNTIF(A$1:A18,A18)) | C18: {=IF(B18="","",IF(A18=XLOOKUP(A$2,Implementos!B:B,Implementos!C:C,"",0,1),B18+maxifs(B$1:B17,A$1:A17,A$2),B18))} | D18: =IF(B18="","", COUNTIFS(Productos!F:F,A18,Productos!H:H,B18)+IF(F18="SI",0,1)) | E18: =IFERROR(__xludf.DUMMYFUNCTION("IF($B18="""","""",INDEX(filter(Familias!F:F,Familias!$D:$D=$A18,Familias!$E:$E=$B18),1))"),"") | F18: =IFERROR(__xludf.DUMMYFUNCTION("IF($B18="""","""",INDEX(filter(Familias!G:G,Familias!$D:$D=$A18,Familias!$E:$E=$B18),1))"),"") | G18: {=IF(C18=1,XLOOKUP(C18,Cotizador!D:D,Cotizador!E:E,"",0,1),"")} | J18: =IF(I18="","",SUMIF(Cotizador!I$1:V$1,I18,Cotizador!I$2:V$2)) | L18: {=IF(COUNTIF(L$1:L17,A$2)=SUMIF(A:A,A$2,D:D),IF(COUNTIF(L$1:L17,XLOOKUP(A$2,Implementos!B:B,Implementos!C:C,"",0,1))=SUMIF(A:A,XLOOKUP(A$2,Implementos!B:B,Implementos!C:C,"",0,1),D:D),"",XLOOKUP(A$2,Implementos!B:B,Implementos!C:C,"",0,1)),A$2)} -> Acoplados Rurales | M18: =IF(L18="","",max(M$1:M17)+1) -> 17 | N18: =IF(L18="","",IF(N17="Orden",1,IF(COUNTIFS(N$1:N17,N17,L$1:L17,L18)=SUMIFS(D:D,B:B,N17,A:A,L18),IF(N17=maxifs(B:B,A:A,L18),"",maxifs(N$1:N17,L$1:L17,L18)+1),N17))) -> 1 | O18: =IF(N18="","",SUMIFS(C:C,B:B,N18,A:A,L18)) -> 1 | P18: =IF(N18="","",COUNTIFS(N$1:N18,N18,L$1:L18,L18)) -> 17 | Q18: =IF(U18="","",SUMIF(Productos!E:E,U18,Productos!A:A)) -> 120 | R18: {=IF(L18="","", max(1,SUMIF(I:I,XLOOKUP(U18,Productos!E:E,Productos!G:G,"",0,1),J:J)))} -> 1 | S18: =IF(Q18="","",IF(SUMIFS(Compat_Vetado!D:D,Compat_Vetado!B:B,SUM(G:G),Compat_Vetado!C:C,Q18)=1,"SI",IF(OR(SUMIF(Cotizador!E:E,Q18,Cotizador!G:G)>0,SUMIFS(Compat_Vetado!D:D,Compat_Vetado!B:B,SUM(G:G),Compat_Vetado!C:C,Q18)=-1),"NO",""))) | T18: =IF(Q18="","",IF(S18="SI","x",IF(S18="NO","",IF(AND(OR(V18="",AND(W18<=SUMIF(I:I,V18,J:J),SUMIF(I:I,V18,J:J)<=X18)),OR(Y18="",AND(Z18<=SUMIF(I:I,Y18,J:J),SUMIF(I:I,Y18,J:J)<=AA18)),OR(AB18="",AND(AC18<=SUMIF(I:I,AB18,J:J),SUMIF(I:I,AB18,J:J)<=AD18))),"x","")))) -> x | U18: =IFERROR(__xludf.DUMMYFUNCTION("IF(P18="""","""",IFERROR(INDEX(filter(Productos!E:E,Productos!F:F=L18,Productos!H:H=N18),P18),IF(M18=SUM(D:D),""Finalizar"",""-"")))"),"Plataforma Playo 4.00 x 1.90 x 0.45 Lateral Doble Baranda Ventilada") -> Plataforma Playo 4.00 x 1.90 x 0.45 Lateral Doble Baranda Ventilada | V18: =IFERROR(__xludf.DUMMYFUNCTION("IF(OR($U18="""",COUNTIF($I:$I,IFERROR(unique(filter(Prod_Prop!$H:$H,Prod_Prop!$G:$G=$U18,Prod_Prop!$E:$E=V$1)),""Check""))=0),"""",IFERROR(unique(filter(Prod_Prop!$H:$H,Prod_Prop!$G:$G=$U18,Prod_Prop!$E:$E=V$1)),""""))"),"") | W18: =IF(V18="","",SUMIFS(Prod_Prop!$J:$J,Prod_Prop!$B:$B,$Q18,Prod_Prop!$H:$H,V18,Prod_Prop!$I:$I,W$1)*IF(V18="Peso",$R18,1)) | X18: =IF(V18="","",SUMIFS(Prod_Prop!$J:$J,Prod_Prop!$B:$B,$Q18,Prod_Prop!$H:$H,V18,Prod_Prop!$I:$I,X$1)*IF(V18="Peso",$R18,1)) | Y18: =IFERROR(__xludf.DUMMYFUNCTION("IF(OR($U18="""",COUNTIF($I:$I,IFERROR(unique(filter(Prod_Prop!$H:$H,Prod_Prop!$G:$G=$U18,Prod_Prop!$E:$E=Y$1)),""Check""))=0),"""",IFERROR(unique(filter(Prod_Prop!$H:$H,Prod_Prop!$G:$G=$U18,Prod_Prop!$E:$E=Y$1)),""""))"),"") | Z18: =IF(Y18="","",SUMIFS(Prod_Prop!$J:$J,Prod_Prop!$B:$B,$Q18,Prod_Prop!$H:$H,Y18,Prod_Prop!$I:$I,Z$1)*IF(Y18="Peso",$R18,1)) | AA18: =IF(Y18="","",SUMIFS(Prod_Prop!$J:$J,Prod_Prop!$B:$B,$Q18,Prod_Prop!$H:$H,Y18,Prod_Prop!$I:$I,AA$1)*IF(Y18="Peso",$R18,1)) | AB18: =IFERROR(__xludf.DUMMYFUNCTION("IF(OR($U18="""",COUNTIF($I:$I,IFERROR(unique(filter(Prod_Prop!$H:$H,Prod_Prop!$G:$G=$U18,Prod_Prop!$E:$E=AB$1)),""Check""))=0),"""",IFERROR(unique(filter(Prod_Prop!$H:$H,Prod_Prop!$G:$G=$U18,Prod_Prop!$E:$E=AB$1)),""""))"),"") | AC18: =IF(AB18="","",SUMIFS(Prod_Prop!$J:$J,Prod_Prop!$B:$B,$Q18,Prod_Prop!$H:$H,AB18,Prod_Prop!$I:$I,AC$1)*IF(AB18="Peso",$R18,1)) | AD18: =IF(AB18="","",SUMIFS(Prod_Prop!$J:$J,Prod_Prop!$B:$B,$Q18,Prod_Prop!$H:$H,AB18,Prod_Prop!$I:$I,AD$1)*IF(AB18="Peso",$R18,1))
A19: {=IF(COUNTIF(A$1:A18,Cotizador!F$2)=maxifs(Familias!E:E,Familias!D:D,Cotizador!F$2),IF(COUNTIF(A$1:A18,XLOOKUP(Cotizador!F$2,Implementos!B:B,Implementos!C:C,"",0,1))=SUMIFS(Implementos!D:D,Implementos!B:B,Cotizador!F$2,Implementos!C:C,XLOOKUP(Cotizador!F$2,Implementos!B:B,Implementos!C:C,"",0,1)),"",XLOOKUP(Cotizador!F$2,Implementos!B:B,Implementos!C:C,"",0,1)),Cotizador!F$2)} | B19: =IF(A19="","",COUNTIF(A$1:A19,A19)) | C19: {=IF(B19="","",IF(A19=XLOOKUP(A$2,Implementos!B:B,Implementos!C:C,"",0,1),B19+maxifs(B$1:B18,A$1:A18,A$2),B19))} | D19: =IF(B19="","", COUNTIFS(Productos!F:F,A19,Productos!H:H,B19)+IF(F19="SI",0,1)) | E19: =IFERROR(__xludf.DUMMYFUNCTION("IF($B19="""","""",INDEX(filter(Familias!F:F,Familias!$D:$D=$A19,Familias!$E:$E=$B19),1))"),"") | F19: =IFERROR(__xludf.DUMMYFUNCTION("IF($B19="""","""",INDEX(filter(Familias!G:G,Familias!$D:$D=$A19,Familias!$E:$E=$B19),1))"),"") | G19: {=IF(C19=1,XLOOKUP(C19,Cotizador!D:D,Cotizador!E:E,"",0,1),"")} | J19: =IF(I19="","",SUMIF(Cotizador!I$1:V$1,I19,Cotizador!I$2:V$2)) | L19: {=IF(COUNTIF(L$1:L18,A$2)=SUMIF(A:A,A$2,D:D),IF(COUNTIF(L$1:L18,XLOOKUP(A$2,Implementos!B:B,Implementos!C:C,"",0,1))=SUMIF(A:A,XLOOKUP(A$2,Implementos!B:B,Implementos!C:C,"",0,1),D:D),"",XLOOKUP(A$2,Implementos!B:B,Implementos!C:C,"",0,1)),A$2)} -> Acoplados Rurales | M19: =IF(L19="","",max(M$1:M18)+1) -> 18 | N19: =IF(L19="","",IF(N18="Orden",1,IF(COUNTIFS(N$1:N18,N18,L$1:L18,L19)=SUMIFS(D:D,B:B,N18,A:A,L19),IF(N18=maxifs(B:B,A:A,L19),"",maxifs(N$1:N18,L$1:L18,L19)+1),N18))) -> 1 | O19: =IF(N19="","",SUMIFS(C:C,B:B,N19,A:A,L19)) -> 1 | P19: =IF(N19="","",COUNTIFS(N$1:N19,N19,L$1:L19,L19)) -> 18 | Q19: =IF(U19="","",SUMIF(Productos!E:E,U19,Productos!A:A)) -> 121 | R19: {=IF(L19="","", max(1,SUMIF(I:I,XLOOKUP(U19,Productos!E:E,Productos!G:G,"",0,1),J:J)))} -> 1 | S19: =IF(Q19="","",IF(SUMIFS(Compat_Vetado!D:D,Compat_Vetado!B:B,SUM(G:G),Compat_Vetado!C:C,Q19)=1,"SI",IF(OR(SUMIF(Cotizador!E:E,Q19,Cotizador!G:G)>0,SUMIFS(Compat_Vetado!D:D,Compat_Vetado!B:B,SUM(G:G),Compat_Vetado!C:C,Q19)=-1),"NO",""))) | T19: =IF(Q19="","",IF(S19="SI","x",IF(S19="NO","",IF(AND(OR(V19="",AND(W19<=SUMIF(I:I,V19,J:J),SUMIF(I:I,V19,J:J)<=X19)),OR(Y19="",AND(Z19<=SUMIF(I:I,Y19,J:J),SUMIF(I:I,Y19,J:J)<=AA19)),OR(AB19="",AND(AC19<=SUMIF(I:I,AB19,J:J),SUMIF(I:I,AB19,J:J)<=AD19))),"x","")))) -> x | U19: =IFERROR(__xludf.DUMMYFUNCTION("IF(P19="""","""",IFERROR(INDEX(filter(Productos!E:E,Productos!F:F=L19,Productos!H:H=N19),P19),IF(M19=SUM(D:D),""Finalizar"",""-"")))"),"Plataforma Playo 4.00 x 1.90 x 0.45 Lateral Doble Baranda Fija") -> Plataforma Playo 4.00 x 1.90 x 0.45 Lateral Doble Baranda Fija | V19: =IFERROR(__xludf.DUMMYFUNCTION("IF(OR($U19="""",COUNTIF($I:$I,IFERROR(unique(filter(Prod_Prop!$H:$H,Prod_Prop!$G:$G=$U19,Prod_Prop!$E:$E=V$1)),""Check""))=0),"""",IFERROR(unique(filter(Prod_Prop!$H:$H,Prod_Prop!$G:$G=$U19,Prod_Prop!$E:$E=V$1)),""""))"),"") | W19: =IF(V19="","",SUMIFS(Prod_Prop!$J:$J,Prod_Prop!$B:$B,$Q19,Prod_Prop!$H:$H,V19,Prod_Prop!$I:$I,W$1)*IF(V19="Peso",$R19,1)) | X19: =IF(V19="","",SUMIFS(Prod_Prop!$J:$J,Prod_Prop!$B:$B,$Q19,Prod_Prop!$H:$H,V19,Prod_Prop!$I:$I,X$1)*IF(V19="Peso",$R19,1)) | Y19: =IFERROR(__xludf.DUMMYFUNCTION("IF(OR($U19="""",COUNTIF($I:$I,IFERROR(unique(filter(Prod_Prop!$H:$H,Prod_Prop!$G:$G=$U19,Prod_Prop!$E:$E=Y$1)),""Check""))=0),"""",IFERROR(unique(filter(Prod_Prop!$H:$H,Prod_Prop!$G:$G=$U19,Prod_Prop!$E:$E=Y$1)),""""))"),"") | Z19: =IF(Y19="","",SUMIFS(Prod_Prop!$J:$J,Prod_Prop!$B:$B,$Q19,Prod_Prop!$H:$H,Y19,Prod_Prop!$I:$I,Z$1)*IF(Y19="Peso",$R19,1)) | AA19: =IF(Y19="","",SUMIFS(Prod_Prop!$J:$J,Prod_Prop!$B:$B,$Q19,Prod_Prop!$H:$H,Y19,Prod_Prop!$I:$I,AA$1)*IF(Y19="Peso",$R19,1)) | AB19: =IFERROR(__xludf.DUMMYFUNCTION("IF(OR($U19="""",COUNTIF($I:$I,IFERROR(unique(filter(Prod_Prop!$H:$H,Prod_Prop!$G:$G=$U19,Prod_Prop!$E:$E=AB$1)),""Check""))=0),"""",IFERROR(unique(filter(Prod_Prop!$H:$H,Prod_Prop!$G:$G=$U19,Prod_Prop!$E:$E=AB$1)),""""))"),"") | AC19: =IF(AB19="","",SUMIFS(Prod_Prop!$J:$J,Prod_Prop!$B:$B,$Q19,Prod_Prop!$H:$H,AB19,Prod_Prop!$I:$I,AC$1)*IF(AB19="Peso",$R19,1)) | AD19: =IF(AB19="","",SUMIFS(Prod_Prop!$J:$J,Prod_Prop!$B:$B,$Q19,Prod_Prop!$H:$H,AB19,Prod_Prop!$I:$I,AD$1)*IF(AB19="Peso",$R19,1))
A20: {=IF(COUNTIF(A$1:A19,Cotizador!F$2)=maxifs(Familias!E:E,Familias!D:D,Cotizador!F$2),IF(COUNTIF(A$1:A19,XLOOKUP(Cotizador!F$2,Implementos!B:B,Implementos!C:C,"",0,1))=SUMIFS(Implementos!D:D,Implementos!B:B,Cotizador!F$2,Implementos!C:C,XLOOKUP(Cotizador!F$2,Implementos!B:B,Implementos!C:C,"",0,1)),"",XLOOKUP(Cotizador!F$2,Implementos!B:B,Implementos!C:C,"",0,1)),Cotizador!F$2)} | B20: =IF(A20="","",COUNTIF(A$1:A20,A20)) | C20: {=IF(B20="","",IF(A20=XLOOKUP(A$2,Implementos!B:B,Implementos!C:C,"",0,1),B20+maxifs(B$1:B19,A$1:A19,A$2),B20))} | D20: =IF(B20="","", COUNTIFS(Productos!F:F,A20,Productos!H:H,B20)+IF(F20="SI",0,1)) | E20: =IFERROR(__xludf.DUMMYFUNCTION("IF($B20="""","""",INDEX(filter(Familias!F:F,Familias!$D:$D=$A20,Familias!$E:$E=$B20),1))"),"") | F20: =IFERROR(__xludf.DUMMYFUNCTION("IF($B20="""","""",INDEX(filter(Familias!G:G,Familias!$D:$D=$A20,Familias!$E:$E=$B20),1))"),"") | G20: {=IF(C20=1,XLOOKUP(C20,Cotizador!D:D,Cotizador!E:E,"",0,1),"")} | J20: =IF(I20="","",SUMIF(Cotizador!I$1:V$1,I20,Cotizador!I$2:V$2)) | L20: {=IF(COUNTIF(L$1:L19,A$2)=SUMIF(A:A,A$2,D:D),IF(COUNTIF(L$1:L19,XLOOKUP(A$2,Implementos!B:B,Implementos!C:C,"",0,1))=SUMIF(A:A,XLOOKUP(A$2,Implementos!B:B,Implementos!C:C,"",0,1),D:D),"",XLOOKUP(A$2,Implementos!B:B,Implementos!C:C,"",0,1)),A$2)} -> Acoplados Rurales | M20: =IF(L20="","",max(M$1:M19)+1) -> 19 | N20: =IF(L20="","",IF(N19="Orden",1,IF(COUNTIFS(N$1:N19,N19,L$1:L19,L20)=SUMIFS(D:D,B:B,N19,A:A,L20),IF(N19=maxifs(B:B,A:A,L20),"",maxifs(N$1:N19,L$1:L19,L20)+1),N19))) -> 1 | O20: =IF(N20="","",SUMIFS(C:C,B:B,N20,A:A,L20)) -> 1 | P20: =IF(N20="","",COUNTIFS(N$1:N20,N20,L$1:L20,L20)) -> 19 | Q20: =IF(U20="","",SUMIF(Productos!E:E,U20,Productos!A:A)) -> 122 | R20: {=IF(L20="","", max(1,SUMIF(I:I,XLOOKUP(U20,Productos!E:E,Productos!G:G,"",0,1),J:J)))} -> 1 | S20: =IF(Q20="","",IF(SUMIFS(Compat_Vetado!D:D,Compat_Vetado!B:B,SUM(G:G),Compat_Vetado!C:C,Q20)=1,"SI",IF(OR(SUMIF(Cotizador!E:E,Q20,Cotizador!G:G)>0,SUMIFS(Compat_Vetado!D:D,Compat_Vetado!B:B,SUM(G:G),Compat_Vetado!C:C,Q20)=-1),"NO",""))) | T20: =IF(Q20="","",IF(S20="SI","x",IF(S20="NO","",IF(AND(OR(V20="",AND(W20<=SUMIF(I:I,V20,J:J),SUMIF(I:I,V20,J:J)<=X20)),OR(Y20="",AND(Z20<=SUMIF(I:I,Y20,J:J),SUMIF(I:I,Y20,J:J)<=AA20)),OR(AB20="",AND(AC20<=SUMIF(I:I,AB20,J:J),SUMIF(I:I,AB20,J:J)<=AD20))),"x","")))) -> x | U20: =IFERROR(__xludf.DUMMYFUNCTION("IF(P20="""","""",IFERROR(INDEX(filter(Productos!E:E,Productos!F:F=L20,Productos!H:H=N20),P20),IF(M20=SUM(D:D),""Finalizar"",""-"")))"),"Plataforma Playo 4.00 x 1.90 x 0.72 Lateral Simple Baranda Fija") -> Plataforma Playo 4.00 x 1.90 x 0.72 Lateral Simple Baranda Fija | V20: =IFERROR(__xludf.DUMMYFUNCTION("IF(OR($U20="""",COUNTIF($I:$I,IFERROR(unique(filter(Prod_Prop!$H:$H,Prod_Prop!$G:$G=$U20,Prod_Prop!$E:$E=V$1)),""Check""))=0),"""",IFERROR(unique(filter(Prod_Prop!$H:$H,Prod_Prop!$G:$G=$U20,Prod_Prop!$E:$E=V$1)),""""))"),"") | W20: =IF(V20="","",SUMIFS(Prod_Prop!$J:$J,Prod_Prop!$B:$B,$Q20,Prod_Prop!$H:$H,V20,Prod_Prop!$I:$I,W$1)*IF(V20="Peso",$R20,1)) | X20: =IF(V20="","",SUMIFS(Prod_Prop!$J:$J,Prod_Prop!$B:$B,$Q20,Prod_Prop!$H:$H,V20,Prod_Prop!$I:$I,X$1)*IF(V20="Peso",$R20,1)) | Y20: =IFERROR(__xludf.DUMMYFUNCTION("IF(OR($U20="""",COUNTIF($I:$I,IFERROR(unique(filter(Prod_Prop!$H:$H,Prod_Prop!$G:$G=$U20,Prod_Prop!$E:$E=Y$1)),""Check""))=0),"""",IFERROR(unique(filter(Prod_Prop!$H:$H,Prod_Prop!$G:$G=$U20,Prod_Prop!$E:$E=Y$1)),""""))"),"") | Z20: =IF(Y20="","",SUMIFS(Prod_Prop!$J:$J,Prod_Prop!$B:$B,$Q20,Prod_Prop!$H:$H,Y20,Prod_Prop!$I:$I,Z$1)*IF(Y20="Peso",$R20,1)) | AA20: =IF(Y20="","",SUMIFS(Prod_Prop!$J:$J,Prod_Prop!$B:$B,$Q20,Prod_Prop!$H:$H,Y20,Prod_Prop!$I:$I,AA$1)*IF(Y20="Peso",$R20,1)) | AB20: =IFERROR(__xludf.DUMMYFUNCTION("IF(OR($U20="""",COUNTIF($I:$I,IFERROR(unique(filter(Prod_Prop!$H:$H,Prod_Prop!$G:$G=$U20,Prod_Prop!$E:$E=AB$1)),""Check""))=0),"""",IFERROR(unique(filter(Prod_Prop!$H:$H,Prod_Prop!$G:$G=$U20,Prod_Prop!$E:$E=AB$1)),""""))"),"") | AC20: =IF(AB20="","",SUMIFS(Prod_Prop!$J:$J,Prod_Prop!$B:$B,$Q20,Prod_Prop!$H:$H,AB20,Prod_Prop!$I:$I,AC$1)*IF(AB20="Peso",$R20,1)) | AD20: =IF(AB20="","",SUMIFS(Prod_Prop!$J:$J,Prod_Prop!$B:$B,$Q20,Prod_Prop!$H:$H,AB20,Prod_Prop!$I:$I,AD$1)*IF(AB20="Peso",$R20,1))
A21: {=IF(COUNTIF(A$1:A20,Cotizador!F$2)=maxifs(Familias!E:E,Familias!D:D,Cotizador!F$2),IF(COUNTIF(A$1:A20,XLOOKUP(Cotizador!F$2,Implementos!B:B,Implementos!C:C,"",0,1))=SUMIFS(Implementos!D:D,Implementos!B:B,Cotizador!F$2,Implementos!C:C,XLOOKUP(Cotizador!F$2,Implementos!B:B,Implementos!C:C,"",0,1)),"",XLOOKUP(Cotizador!F$2,Implementos!B:B,Implementos!C:C,"",0,1)),Cotizador!F$2)} | B21: =IF(A21="","",COUNTIF(A$1:A21,A21)) | C21: {=IF(B21="","",IF(A21=XLOOKUP(A$2,Implementos!B:B,Implementos!C:C,"",0,1),B21+maxifs(B$1:B20,A$1:A20,A$2),B21))} | D21: =IF(B21="","", COUNTIFS(Productos!F:F,A21,Productos!H:H,B21)+IF(F21="SI",0,1)) | E21: =IFERROR(__xludf.DUMMYFUNCTION("IF($B21="""","""",INDEX(filter(Familias!F:F,Familias!$D:$D=$A21,Familias!$E:$E=$B21),1))"),"") | F21: =IFERROR(__xludf.DUMMYFUNCTION("IF($B21="""","""",INDEX(filter(Familias!G:G,Familias!$D:$D=$A21,Familias!$E:$E=$B21),1))"),"") | G21: {=IF(C21=1,XLOOKUP(C21,Cotizador!D:D,Cotizador!E:E,"",0,1),"")} | J21: =IF(I21="","",SUMIF(Cotizador!I$1:V$1,I21,Cotizador!I$2:V$2)) | L21: {=IF(COUNTIF(L$1:L20,A$2)=SUMIF(A:A,A$2,D:D),IF(COUNTIF(L$1:L20,XLOOKUP(A$2,Implementos!B:B,Implementos!C:C,"",0,1))=SUMIF(A:A,XLOOKUP(A$2,Implementos!B:B,Implementos!C:C,"",0,1),D:D),"",XLOOKUP(A$2,Implementos!B:B,Implementos!C:C,"",0,1)),A$2)} -> Acoplados Rurales | M21: =IF(L21="","",max(M$1:M20)+1) -> 20 | N21: =IF(L21="","",IF(N20="Orden",1,IF(COUNTIFS(N$1:N20,N20,L$1:L20,L21)=SUMIFS(D:D,B:B,N20,A:A,L21),IF(N20=maxifs(B:B,A:A,L21),"",maxifs(N$1:N20,L$1:L20,L21)+1),N20))) -> 1 | O21: =IF(N21="","",SUMIFS(C:C,B:B,N21,A:A,L21)) -> 1 | P21: =IF(N21="","",COUNTIFS(N$1:N21,N21,L$1:L21,L21)) -> 20 | Q21: =IF(U21="","",SUMIF(Productos!E:E,U21,Productos!A:A)) -> 123 | R21: {=IF(L21="","", max(1,SUMIF(I:I,XLOOKUP(U21,Productos!E:E,Productos!G:G,"",0,1),J:J)))} -> 1 | S21: =IF(Q21="","",IF(SUMIFS(Compat_Vetado!D:D,Compat_Vetado!B:B,SUM(G:G),Compat_Vetado!C:C,Q21)=1,"SI",IF(OR(SUMIF(Cotizador!E:E,Q21,Cotizador!G:G)>0,SUMIFS(Compat_Vetado!D:D,Compat_Vetado!B:B,SUM(G:G),Compat_Vetado!C:C,Q21)=-1),"NO",""))) | T21: =IF(Q21="","",IF(S21="SI","x",IF(S21="NO","",IF(AND(OR(V21="",AND(W21<=SUMIF(I:I,V21,J:J),SUMIF(I:I,V21,J:J)<=X21)),OR(Y21="",AND(Z21<=SUMIF(I:I,Y21,J:J),SUMIF(I:I,Y21,J:J)<=AA21)),OR(AB21="",AND(AC21<=SUMIF(I:I,AB21,J:J),SUMIF(I:I,AB21,J:J)<=AD21))),"x","")))) -> x | U21: =IFERROR(__xludf.DUMMYFUNCTION("IF(P21="""","""",IFERROR(INDEX(filter(Productos!E:E,Productos!F:F=L21,Productos!H:H=N21),P21),IF(M21=SUM(D:D),""Finalizar"",""-"")))"),"Plataforma Playo 4.00 x 1.90 x 0.72 Lateral Doble Baranda Fija") -> Plataforma Playo 4.00 x 1.90 x 0.72 Lateral Doble Baranda Fija | V21: =IFERROR(__xludf.DUMMYFUNCTION("IF(OR($U21="""",COUNTIF($I:$I,IFERROR(unique(filter(Prod_Prop!$H:$H,Prod_Prop!$G:$G=$U21,Prod_Prop!$E:$E=V$1)),""Check""))=0),"""",IFERROR(unique(filter(Prod_Prop!$H:$H,Prod_Prop!$G:$G=$U21,Prod_Prop!$E:$E=V$1)),""""))"),"") | W21: =IF(V21="","",SUMIFS(Prod_Prop!$J:$J,Prod_Prop!$B:$B,$Q21,Prod_Prop!$H:$H,V21,Prod_Prop!$I:$I,W$1)*IF(V21="Peso",$R21,1)) | X21: =IF(V21="","",SUMIFS(Prod_Prop!$J:$J,Prod_Prop!$B:$B,$Q21,Prod_Prop!$H:$H,V21,Prod_Prop!$I:$I,X$1)*IF(V21="Peso",$R21,1)) | Y21: =IFERROR(__xludf.DUMMYFUNCTION("IF(OR($U21="""",COUNTIF($I:$I,IFERROR(unique(filter(Prod_Prop!$H:$H,Prod_Prop!$G:$G=$U21,Prod_Prop!$E:$E=Y$1)),""Check""))=0),"""",IFERROR(unique(filter(Prod_Prop!$H:$H,Prod_Prop!$G:$G=$U21,Prod_Prop!$E:$E=Y$1)),""""))"),"") | Z21: =IF(Y21="","",SUMIFS(Prod_Prop!$J:$J,Prod_Prop!$B:$B,$Q21,Prod_Prop!$H:$H,Y21,Prod_Prop!$I:$I,Z$1)*IF(Y21="Peso",$R21,1)) | AA21: =IF(Y21="","",SUMIFS(Prod_Prop!$J:$J,Prod_Prop!$B:$B,$Q21,Prod_Prop!$H:$H,Y21,Prod_Prop!$I:$I,AA$1)*IF(Y21="Peso",$R21,1)) | AB21: =IFERROR(__xludf.DUMMYFUNCTION("IF(OR($U21="""",COUNTIF($I:$I,IFERROR(unique(filter(Prod_Prop!$H:$H,Prod_Prop!$G:$G=$U21,Prod_Prop!$E:$E=AB$1)),""Check""))=0),"""",IFERROR(unique(filter(Prod_Prop!$H:$H,Prod_Prop!$G:$G=$U21,Prod_Prop!$E:$E=AB$1)),""""))"),"") | AC21: =IF(AB21="","",SUMIFS(Prod_Prop!$J:$J,Prod_Prop!$B:$B,$Q21,Prod_Prop!$H:$H,AB21,Prod_Prop!$I:$I,AC$1)*IF(AB21="Peso",$R21,1)) | AD21: =IF(AB21="","",SUMIFS(Prod_Prop!$J:$J,Prod_Prop!$B:$B,$Q21,Prod_Prop!$H:$H,AB21,Prod_Prop!$I:$I,AD$1)*IF(AB21="Peso",$R21,1))
A22: {=IF(COUNTIF(A$1:A21,Cotizador!F$2)=maxifs(Familias!E:E,Familias!D:D,Cotizador!F$2),IF(COUNTIF(A$1:A21,XLOOKUP(Cotizador!F$2,Implementos!B:B,Implementos!C:C,"",0,1))=SUMIFS(Implementos!D:D,Implementos!B:B,Cotizador!F$2,Implementos!C:C,XLOOKUP(Cotizador!F$2,Implementos!B:B,Implementos!C:C,"",0,1)),"",XLOOKUP(Cotizador!F$2,Implementos!B:B,Implementos!C:C,"",0,1)),Cotizador!F$2)} | B22: =IF(A22="","",COUNTIF(A$1:A22,A22)) | C22: {=IF(B22="","",IF(A22=XLOOKUP(A$2,Implementos!B:B,Implementos!C:C,"",0,1),B22+maxifs(B$1:B21,A$1:A21,A$2),B22))} | D22: =IF(B22="","", COUNTIFS(Productos!F:F,A22,Productos!H:H,B22)+IF(F22="SI",0,1)) | E22: =IFERROR(__xludf.DUMMYFUNCTION("IF($B22="""","""",INDEX(filter(Familias!F:F,Familias!$D:$D=$A22,Familias!$E:$E=$B22),1))"),"") | F22: =IFERROR(__xludf.DUMMYFUNCTION("IF($B22="""","""",INDEX(filter(Familias!G:G,Familias!$D:$D=$A22,Familias!$E:$E=$B22),1))"),"") | G22: {=IF(C22=1,XLOOKUP(C22,Cotizador!D:D,Cotizador!E:E,"",0,1),"")} | J22: =IF(I22="","",SUMIF(Cotizador!I$1:V$1,I22,Cotizador!I$2:V$2)) | L22: {=IF(COUNTIF(L$1:L21,A$2)=SUMIF(A:A,A$2,D:D),IF(COUNTIF(L$1:L21,XLOOKUP(A$2,Implementos!B:B,Implementos!C:C,"",0,1))=SUMIF(A:A,XLOOKUP(A$2,Implementos!B:B,Implementos!C:C,"",0,1),D:D),"",XLOOKUP(A$2,Implementos!B:B,Implementos!C:C,"",0,1)),A$2)} -> Acoplados Rurales | M22: =IF(L22="","",max(M$1:M21)+1) -> 21 | N22: =IF(L22="","",IF(N21="Orden",1,IF(COUNTIFS(N$1:N21,N21,L$1:L21,L22)=SUMIFS(D:D,B:B,N21,A:A,L22),IF(N21=maxifs(B:B,A:A,L22),"",maxifs(N$1:N21,L$1:L21,L22)+1),N21))) -> 1 | O22: =IF(N22="","",SUMIFS(C:C,B:B,N22,A:A,L22)) -> 1 | P22: =IF(N22="","",COUNTIFS(N$1:N22,N22,L$1:L22,L22)) -> 21 | Q22: =IF(U22="","",SUMIF(Productos!E:E,U22,Productos!A:A)) -> 124 | R22: {=IF(L22="","", max(1,SUMIF(I:I,XLOOKUP(U22,Productos!E:E,Productos!G:G,"",0,1),J:J)))} -> 1 | S22: =IF(Q22="","",IF(SUMIFS(Compat_Vetado!D:D,Compat_Vetado!B:B,SUM(G:G),Compat_Vetado!C:C,Q22)=1,"SI",IF(OR(SUMIF(Cotizador!E:E,Q22,Cotizador!G:G)>0,SUMIFS(Compat_Vetado!D:D,Compat_Vetado!B:B,SUM(G:G),Compat_Vetado!C:C,Q22)=-1),"NO",""))) | T22: =IF(Q22="","",IF(S22="SI","x",IF(S22="NO","",IF(AND(OR(V22="",AND(W22<=SUMIF(I:I,V22,J:J),SUMIF(I:I,V22,J:J)<=X22)),OR(Y22="",AND(Z22<=SUMIF(I:I,Y22,J:J),SUMIF(I:I,Y22,J:J)<=AA22)),OR(AB22="",AND(AC22<=SUMIF(I:I,AB22,J:J),SUMIF(I:I,AB22,J:J)<=AD22))),"x","")))) -> x | U22: =IFERROR(__xludf.DUMMYFUNCTION("IF(P22="""","""",IFERROR(INDEX(filter(Productos!E:E,Productos!F:F=L22,Productos!H:H=N22),P22),IF(M22=SUM(D:D),""Finalizar"",""-"")))"),"Plataforma Playo 5.00 x 2.20 x 0.60 Lateral Doble Trasera Rebatible") -> Plataforma Playo 5.00 x 2.20 x 0.60 Lateral Doble Trasera Rebatible | V22: =IFERROR(__xludf.DUMMYFUNCTION("IF(OR($U22="""",COUNTIF($I:$I,IFERROR(unique(filter(Prod_Prop!$H:$H,Prod_Prop!$G:$G=$U22,Prod_Prop!$E:$E=V$1)),""Check""))=0),"""",IFERROR(unique(filter(Prod_Prop!$H:$H,Prod_Prop!$G:$G=$U22,Prod_Prop!$E:$E=V$1)),""""))"),"") | W22: =IF(V22="","",SUMIFS(Prod_Prop!$J:$J,Prod_Prop!$B:$B,$Q22,Prod_Prop!$H:$H,V22,Prod_Prop!$I:$I,W$1)*IF(V22="Peso",$R22,1)) | X22: =IF(V22="","",SUMIFS(Prod_Prop!$J:$J,Prod_Prop!$B:$B,$Q22,Prod_Prop!$H:$H,V22,Prod_Prop!$I:$I,X$1)*IF(V22="Peso",$R22,1)) | Y22: =IFERROR(__xludf.DUMMYFUNCTION("IF(OR($U22="""",COUNTIF($I:$I,IFERROR(unique(filter(Prod_Prop!$H:$H,Prod_Prop!$G:$G=$U22,Prod_Prop!$E:$E=Y$1)),""Check""))=0),"""",IFERROR(unique(filter(Prod_Prop!$H:$H,Prod_Prop!$G:$G=$U22,Prod_Prop!$E:$E=Y$1)),""""))"),"") | Z22: =IF(Y22="","",SUMIFS(Prod_Prop!$J:$J,Prod_Prop!$B:$B,$Q22,Prod_Prop!$H:$H,Y22,Prod_Prop!$I:$I,Z$1)*IF(Y22="Peso",$R22,1)) | AA22: =IF(Y22="","",SUMIFS(Prod_Prop!$J:$J,Prod_Prop!$B:$B,$Q22,Prod_Prop!$H:$H,Y22,Prod_Prop!$I:$I,AA$1)*IF(Y22="Peso",$R22,1)) | AB22: =IFERROR(__xludf.DUMMYFUNCTION("IF(OR($U22="""",COUNTIF($I:$I,IFERROR(unique(filter(Prod_Prop!$H:$H,Prod_Prop!$G:$G=$U22,Prod_Prop!$E:$E=AB$1)),""Check""))=0),"""",IFERROR(unique(filter(Prod_Prop!$H:$H,Prod_Prop!$G:$G=$U22,Prod_Prop!$E:$E=AB$1)),""""))"),"") | AC22: =IF(AB22="","",SUMIFS(Prod_Prop!$J:$J,Prod_Prop!$B:$B,$Q22,Prod_Prop!$H:$H,AB22,Prod_Prop!$I:$I,AC$1)*IF(AB22="Peso",$R22,1)) | AD22: =IF(AB22="","",SUMIFS(Prod_Prop!$J:$J,Prod_Prop!$B:$B,$Q22,Prod_Prop!$H:$H,AB22,Prod_Prop!$I:$I,AD$1)*IF(AB22="Peso",$R22,1))
A23: {=IF(COUNTIF(A$1:A22,Cotizador!F$2)=maxifs(Familias!E:E,Familias!D:D,Cotizador!F$2),IF(COUNTIF(A$1:A22,XLOOKUP(Cotizador!F$2,Implementos!B:B,Implementos!C:C,"",0,1))=SUMIFS(Implementos!D:D,Implementos!B:B,Cotizador!F$2,Implementos!C:C,XLOOKUP(Cotizador!F$2,Implementos!B:B,Implementos!C:C,"",0,1)),"",XLOOKUP(Cotizador!F$2,Implementos!B:B,Implementos!C:C,"",0,1)),Cotizador!F$2)} | B23: =IF(A23="","",COUNTIF(A$1:A23,A23)) | C23: {=IF(B23="","",IF(A23=XLOOKUP(A$2,Implementos!B:B,Implementos!C:C,"",0,1),B23+maxifs(B$1:B22,A$1:A22,A$2),B23))} | D23: =IF(B23="","", COUNTIFS(Productos!F:F,A23,Productos!H:H,B23)+IF(F23="SI",0,1)) | E23: =IFERROR(__xludf.DUMMYFUNCTION("IF($B23="""","""",INDEX(filter(Familias!F:F,Familias!$D:$D=$A23,Familias!$E:$E=$B23),1))"),"") | F23: =IFERROR(__xludf.DUMMYFUNCTION("IF($B23="""","""",INDEX(filter(Familias!G:G,Familias!$D:$D=$A23,Familias!$E:$E=$B23),1))"),"") | G23: {=IF(C23=1,XLOOKUP(C23,Cotizador!D:D,Cotizador!E:E,"",0,1),"")} | J23: =IF(I23="","",SUMIF(Cotizador!I$1:V$1,I23,Cotizador!I$2:V$2)) | L23: {=IF(COUNTIF(L$1:L22,A$2)=SUMIF(A:A,A$2,D:D),IF(COUNTIF(L$1:L22,XLOOKUP(A$2,Implementos!B:B,Implementos!C:C,"",0,1))=SUMIF(A:A,XLOOKUP(A$2,Implementos!B:B,Implementos!C:C,"",0,1),D:D),"",XLOOKUP(A$2,Implementos!B:B,Implementos!C:C,"",0,1)),A$2)} -> Acoplados Rurales | M23: =IF(L23="","",max(M$1:M22)+1) -> 22 | N23: =IF(L23="","",IF(N22="Orden",1,IF(COUNTIFS(N$1:N22,N22,L$1:L22,L23)=SUMIFS(D:D,B:B,N22,A:A,L23),IF(N22=maxifs(B:B,A:A,L23),"",maxifs(N$1:N22,L$1:L22,L23)+1),N22))) -> 1 | O23: =IF(N23="","",SUMIFS(C:C,B:B,N23,A:A,L23)) -> 1 | P23: =IF(N23="","",COUNTIFS(N$1:N23,N23,L$1:L23,L23)) -> 22 | Q23: =IF(U23="","",SUMIF(Productos!E:E,U23,Productos!A:A)) -> 125 | R23: {=IF(L23="","", max(1,SUMIF(I:I,XLOOKUP(U23,Productos!E:E,Productos!G:G,"",0,1),J:J)))} -> 1 | S23: =IF(Q23="","",IF(SUMIFS(Compat_Vetado!D:D,Compat_Vetado!B:B,SUM(G:G),Compat_Vetado!C:C,Q23)=1,"SI",IF(OR(SUMIF(Cotizador!E:E,Q23,Cotizador!G:G)>0,SUMIFS(Compat_Vetado!D:D,Compat_Vetado!B:B,SUM(G:G),Compat_Vetado!C:C,Q23)=-1),"NO",""))) | T23: =IF(Q23="","",IF(S23="SI","x",IF(S23="NO","",IF(AND(OR(V23="",AND(W23<=SUMIF(I:I,V23,J:J),SUMIF(I:I,V23,J:J)<=X23)),OR(Y23="",AND(Z23<=SUMIF(I:I,Y23,J:J),SUMIF(I:I,Y23,J:J)<=AA23)),OR(AB23="",AND(AC23<=SUMIF(I:I,AB23,J:J),SUMIF(I:I,AB23,J:J)<=AD23))),"x","")))) -> x | U23: =IFERROR(__xludf.DUMMYFUNCTION("IF(P23="""","""",IFERROR(INDEX(filter(Productos!E:E,Productos!F:F=L23,Productos!H:H=N23),P23),IF(M23=SUM(D:D),""Finalizar"",""-"")))"),"Plataforma Playo 5.00 x 2.20 x 0.60 Lateral Doble Baranda Fija C/Toldo") -> Plataforma Playo 5.00 x 2.20 x 0.60 Lateral Doble Baranda Fija C/Toldo | V23: =IFERROR(__xludf.DUMMYFUNCTION("IF(OR($U23="""",COUNTIF($I:$I,IFERROR(unique(filter(Prod_Prop!$H:$H,Prod_Prop!$G:$G=$U23,Prod_Prop!$E:$E=V$1)),""Check""))=0),"""",IFERROR(unique(filter(Prod_Prop!$H:$H,Prod_Prop!$G:$G=$U23,Prod_Prop!$E:$E=V$1)),""""))"),"") | W23: =IF(V23="","",SUMIFS(Prod_Prop!$J:$J,Prod_Prop!$B:$B,$Q23,Prod_Prop!$H:$H,V23,Prod_Prop!$I:$I,W$1)*IF(V23="Peso",$R23,1)) | X23: =IF(V23="","",SUMIFS(Prod_Prop!$J:$J,Prod_Prop!$B:$B,$Q23,Prod_Prop!$H:$H,V23,Prod_Prop!$I:$I,X$1)*IF(V23="Peso",$R23,1)) | Y23: =IFERROR(__xludf.DUMMYFUNCTION("IF(OR($U23="""",COUNTIF($I:$I,IFERROR(unique(filter(Prod_Prop!$H:$H,Prod_Prop!$G:$G=$U23,Prod_Prop!$E:$E=Y$1)),""Check""))=0),"""",IFERROR(unique(filter(Prod_Prop!$H:$H,Prod_Prop!$G:$G=$U23,Prod_Prop!$E:$E=Y$1)),""""))"),"") | Z23: =IF(Y23="","",SUMIFS(Prod_Prop!$J:$J,Prod_Prop!$B:$B,$Q23,Prod_Prop!$H:$H,Y23,Prod_Prop!$I:$I,Z$1)*IF(Y23="Peso",$R23,1)) | AA23: =IF(Y23="","",SUMIFS(Prod_Prop!$J:$J,Prod_Prop!$B:$B,$Q23,Prod_Prop!$H:$H,Y23,Prod_Prop!$I:$I,AA$1)*IF(Y23="Peso",$R23,1)) | AB23: =IFERROR(__xludf.DUMMYFUNCTION("IF(OR($U23="""",COUNTIF($I:$I,IFERROR(unique(filter(Prod_Prop!$H:$H,Prod_Prop!$G:$G=$U23,Prod_Prop!$E:$E=AB$1)),""Check""))=0),"""",IFERROR(unique(filter(Prod_Prop!$H:$H,Prod_Prop!$G:$G=$U23,Prod_Prop!$E:$E=AB$1)),""""))"),"") | AC23: =IF(AB23="","",SUMIFS(Prod_Prop!$J:$J,Prod_Prop!$B:$B,$Q23,Prod_Prop!$H:$H,AB23,Prod_Prop!$I:$I,AC$1)*IF(AB23="Peso",$R23,1)) | AD23: =IF(AB23="","",SUMIFS(Prod_Prop!$J:$J,Prod_Prop!$B:$B,$Q23,Prod_Prop!$H:$H,AB23,Prod_Prop!$I:$I,AD$1)*IF(AB23="Peso",$R23,1))
A24: {=IF(COUNTIF(A$1:A23,Cotizador!F$2)=maxifs(Familias!E:E,Familias!D:D,Cotizador!F$2),IF(COUNTIF(A$1:A23,XLOOKUP(Cotizador!F$2,Implementos!B:B,Implementos!C:C,"",0,1))=SUMIFS(Implementos!D:D,Implementos!B:B,Cotizador!F$2,Implementos!C:C,XLOOKUP(Cotizador!F$2,Implementos!B:B,Implementos!C:C,"",0,1)),"",XLOOKUP(Cotizador!F$2,Implementos!B:B,Implementos!C:C,"",0,1)),Cotizador!F$2)} | B24: =IF(A24="","",COUNTIF(A$1:A24,A24)) | C24: {=IF(B24="","",IF(A24=XLOOKUP(A$2,Implementos!B:B,Implementos!C:C,"",0,1),B24+maxifs(B$1:B23,A$1:A23,A$2),B24))} | D24: =IF(B24="","", COUNTIFS(Productos!F:F,A24,Productos!H:H,B24)+IF(F24="SI",0,1)) | E24: =IFERROR(__xludf.DUMMYFUNCTION("IF($B24="""","""",INDEX(filter(Familias!F:F,Familias!$D:$D=$A24,Familias!$E:$E=$B24),1))"),"") | F24: =IFERROR(__xludf.DUMMYFUNCTION("IF($B24="""","""",INDEX(filter(Familias!G:G,Familias!$D:$D=$A24,Familias!$E:$E=$B24),1))"),"") | G24: {=IF(C24=1,XLOOKUP(C24,Cotizador!D:D,Cotizador!E:E,"",0,1),"")} | J24: =IF(I24="","",SUMIF(Cotizador!I$1:V$1,I24,Cotizador!I$2:V$2)) | L24: {=IF(COUNTIF(L$1:L23,A$2)=SUMIF(A:A,A$2,D:D),IF(COUNTIF(L$1:L23,XLOOKUP(A$2,Implementos!B:B,Implementos!C:C,"",0,1))=SUMIF(A:A,XLOOKUP(A$2,Implementos!B:B,Implementos!C:C,"",0,1),D:D),"",XLOOKUP(A$2,Implementos!B:B,Implementos!C:C,"",0,1)),A$2)} -> Acoplados Rurales | M24: =IF(L24="","",max(M$1:M23)+1) -> 23 | N24: =IF(L24="","",IF(N23="Orden",1,IF(COUNTIFS(N$1:N23,N23,L$1:L23,L24)=SUMIFS(D:D,B:B,N23,A:A,L24),IF(N23=maxifs(B:B,A:A,L24),"",maxifs(N$1:N23,L$1:L23,L24)+1),N23))) -> 1 | O24: =IF(N24="","",SUMIFS(C:C,B:B,N24,A:A,L24)) -> 1 | P24: =IF(N24="","",COUNTIFS(N$1:N24,N24,L$1:L24,L24)) -> 23 | Q24: =IF(U24="","",SUMIF(Productos!E:E,U24,Productos!A:A)) -> 126 | R24: {=IF(L24="","", max(1,SUMIF(I:I,XLOOKUP(U24,Productos!E:E,Productos!G:G,"",0,1),J:J)))} -> 1 | S24: =IF(Q24="","",IF(SUMIFS(Compat_Vetado!D:D,Compat_Vetado!B:B,SUM(G:G),Compat_Vetado!C:C,Q24)=1,"SI",IF(OR(SUMIF(Cotizador!E:E,Q24,Cotizador!G:G)>0,SUMIFS(Compat_Vetado!D:D,Compat_Vetado!B:B,SUM(G:G),Compat_Vetado!C:C,Q24)=-1),"NO",""))) | T24: =IF(Q24="","",IF(S24="SI","x",IF(S24="NO","",IF(AND(OR(V24="",AND(W24<=SUMIF(I:I,V24,J:J),SUMIF(I:I,V24,J:J)<=X24)),OR(Y24="",AND(Z24<=SUMIF(I:I,Y24,J:J),SUMIF(I:I,Y24,J:J)<=AA24)),OR(AB24="",AND(AC24<=SUMIF(I:I,AB24,J:J),SUMIF(I:I,AB24,J:J)<=AD24))),"x","")))) -> x | U24: =IFERROR(__xludf.DUMMYFUNCTION("IF(P24="""","""",IFERROR(INDEX(filter(Productos!E:E,Productos!F:F=L24,Productos!H:H=N24),P24),IF(M24=SUM(D:D),""Finalizar"",""-"")))"),"Plataforma Playo 3.00 x 1.90 x 0.45 Lateral Simple Baranda Fija") -> Plataforma Playo 3.00 x 1.90 x 0.45 Lateral Simple Baranda Fija | V24: =IFERROR(__xludf.DUMMYFUNCTION("IF(OR($U24="""",COUNTIF($I:$I,IFERROR(unique(filter(Prod_Prop!$H:$H,Prod_Prop!$G:$G=$U24,Prod_Prop!$E:$E=V$1)),""Check""))=0),"""",IFERROR(unique(filter(Prod_Prop!$H:$H,Prod_Prop!$G:$G=$U24,Prod_Prop!$E:$E=V$1)),""""))"),"") | W24: =IF(V24="","",SUMIFS(Prod_Prop!$J:$J,Prod_Prop!$B:$B,$Q24,Prod_Prop!$H:$H,V24,Prod_Prop!$I:$I,W$1)*IF(V24="Peso",$R24,1)) | X24: =IF(V24="","",SUMIFS(Prod_Prop!$J:$J,Prod_Prop!$B:$B,$Q24,Prod_Prop!$H:$H,V24,Prod_Prop!$I:$I,X$1)*IF(V24="Peso",$R24,1)) | Y24: =IFERROR(__xludf.DUMMYFUNCTION("IF(OR($U24="""",COUNTIF($I:$I,IFERROR(unique(filter(Prod_Prop!$H:$H,Prod_Prop!$G:$G=$U24,Prod_Prop!$E:$E=Y$1)),""Check""))=0),"""",IFERROR(unique(filter(Prod_Prop!$H:$H,Prod_Prop!$G:$G=$U24,Prod_Prop!$E:$E=Y$1)),""""))"),"") | Z24: =IF(Y24="","",SUMIFS(Prod_Prop!$J:$J,Prod_Prop!$B:$B,$Q24,Prod_Prop!$H:$H,Y24,Prod_Prop!$I:$I,Z$1)*IF(Y24="Peso",$R24,1)) | AA24: =IF(Y24="","",SUMIFS(Prod_Prop!$J:$J,Prod_Prop!$B:$B,$Q24,Prod_Prop!$H:$H,Y24,Prod_Prop!$I:$I,AA$1)*IF(Y24="Peso",$R24,1)) | AB24: =IFERROR(__xludf.DUMMYFUNCTION("IF(OR($U24="""",COUNTIF($I:$I,IFERROR(unique(filter(Prod_Prop!$H:$H,Prod_Prop!$G:$G=$U24,Prod_Prop!$E:$E=AB$1)),""Check""))=0),"""",IFERROR(unique(filter(Prod_Prop!$H:$H,Prod_Prop!$G:$G=$U24,Prod_Prop!$E:$E=AB$1)),""""))"),"") | AC24: =IF(AB24="","",SUMIFS(Prod_Prop!$J:$J,Prod_Prop!$B:$B,$Q24,Prod_Prop!$H:$H,AB24,Prod_Prop!$I:$I,AC$1)*IF(AB24="Peso",$R24,1)) | AD24: =IF(AB24="","",SUMIFS(Prod_Prop!$J:$J,Prod_Prop!$B:$B,$Q24,Prod_Prop!$H:$H,AB24,Prod_Prop!$I:$I,AD$1)*IF(AB24="Peso",$R24,1))
A25: {=IF(COUNTIF(A$1:A24,Cotizador!F$2)=maxifs(Familias!E:E,Familias!D:D,Cotizador!F$2),IF(COUNTIF(A$1:A24,XLOOKUP(Cotizador!F$2,Implementos!B:B,Implementos!C:C,"",0,1))=SUMIFS(Implementos!D:D,Implementos!B:B,Cotizador!F$2,Implementos!C:C,XLOOKUP(Cotizador!F$2,Implementos!B:B,Implementos!C:C,"",0,1)),"",XLOOKUP(Cotizador!F$2,Implementos!B:B,Implementos!C:C,"",0,1)),Cotizador!F$2)} | B25: =IF(A25="","",COUNTIF(A$1:A25,A25)) | C25: {=IF(B25="","",IF(A25=XLOOKUP(A$2,Implementos!B:B,Implementos!C:C,"",0,1),B25+maxifs(B$1:B24,A$1:A24,A$2),B25))} | D25: =IF(B25="","", COUNTIFS(Productos!F:F,A25,Productos!H:H,B25)+IF(F25="SI",0,1)) | E25: =IFERROR(__xludf.DUMMYFUNCTION("IF($B25="""","""",INDEX(filter(Familias!F:F,Familias!$D:$D=$A25,Familias!$E:$E=$B25),1))"),"") | F25: =IFERROR(__xludf.DUMMYFUNCTION("IF($B25="""","""",INDEX(filter(Familias!G:G,Familias!$D:$D=$A25,Familias!$E:$E=$B25),1))"),"") | G25: {=IF(C25=1,XLOOKUP(C25,Cotizador!D:D,Cotizador!E:E,"",0,1),"")} | J25: =IF(I25="","",SUMIF(Cotizador!I$1:V$1,I25,Cotizador!I$2:V$2)) | L25: {=IF(COUNTIF(L$1:L24,A$2)=SUMIF(A:A,A$2,D:D),IF(COUNTIF(L$1:L24,XLOOKUP(A$2,Implementos!B:B,Implementos!C:C,"",0,1))=SUMIF(A:A,XLOOKUP(A$2,Implementos!B:B,Implementos!C:C,"",0,1),D:D),"",XLOOKUP(A$2,Implementos!B:B,Implementos!C:C,"",0,1)),A$2)} -> Acoplados Rurales | M25: =IF(L25="","",max(M$1:M24)+1) -> 24 | N25: =IF(L25="","",IF(N24="Orden",1,IF(COUNTIFS(N$1:N24,N24,L$1:L24,L25)=SUMIFS(D:D,B:B,N24,A:A,L25),IF(N24=maxifs(B:B,A:A,L25),"",maxifs(N$1:N24,L$1:L24,L25)+1),N24))) -> 1 | O25: =IF(N25="","",SUMIFS(C:C,B:B,N25,A:A,L25)) -> 1 | P25: =IF(N25="","",COUNTIFS(N$1:N25,N25,L$1:L25,L25)) -> 24 | Q25: =IF(U25="","",SUMIF(Productos!E:E,U25,Productos!A:A)) -> 127 | R25: {=IF(L25="","", max(1,SUMIF(I:I,XLOOKUP(U25,Productos!E:E,Productos!G:G,"",0,1),J:J)))} -> 1 | S25: =IF(Q25="","",IF(SUMIFS(Compat_Vetado!D:D,Compat_Vetado!B:B,SUM(G:G),Compat_Vetado!C:C,Q25)=1,"SI",IF(OR(SUMIF(Cotizador!E:E,Q25,Cotizador!G:G)>0,SUMIFS(Compat_Vetado!D:D,Compat_Vetado!B:B,SUM(G:G),Compat_Vetado!C:C,Q25)=-1),"NO",""))) | T25: =IF(Q25="","",IF(S25="SI","x",IF(S25="NO","",IF(AND(OR(V25="",AND(W25<=SUMIF(I:I,V25,J:J),SUMIF(I:I,V25,J:J)<=X25)),OR(Y25="",AND(Z25<=SUMIF(I:I,Y25,J:J),SUMIF(I:I,Y25,J:J)<=AA25)),OR(AB25="",AND(AC25<=SUMIF(I:I,AB25,J:J),SUMIF(I:I,AB25,J:J)<=AD25))),"x","")))) -> x | U25: =IFERROR(__xludf.DUMMYFUNCTION("IF(P25="""","""",IFERROR(INDEX(filter(Productos!E:E,Productos!F:F=L25,Productos!H:H=N25),P25),IF(M25=SUM(D:D),""Finalizar"",""-"")))"),"Plataforma Playo 3.00 x 1.90 x 0.45 Lateral Simple Baranda Ventilada") -> Plataforma Playo 3.00 x 1.90 x 0.45 Lateral Simple Baranda Ventilada | V25: =IFERROR(__xludf.DUMMYFUNCTION("IF(OR($U25="""",COUNTIF($I:$I,IFERROR(unique(filter(Prod_Prop!$H:$H,Prod_Prop!$G:$G=$U25,Prod_Prop!$E:$E=V$1)),""Check""))=0),"""",IFERROR(unique(filter(Prod_Prop!$H:$H,Prod_Prop!$G:$G=$U25,Prod_Prop!$E:$E=V$1)),""""))"),"") | W25: =IF(V25="","",SUMIFS(Prod_Prop!$J:$J,Prod_Prop!$B:$B,$Q25,Prod_Prop!$H:$H,V25,Prod_Prop!$I:$I,W$1)*IF(V25="Peso",$R25,1)) | X25: =IF(V25="","",SUMIFS(Prod_Prop!$J:$J,Prod_Prop!$B:$B,$Q25,Prod_Prop!$H:$H,V25,Prod_Prop!$I:$I,X$1)*IF(V25="Peso",$R25,1)) | Y25: =IFERROR(__xludf.DUMMYFUNCTION("IF(OR($U25="""",COUNTIF($I:$I,IFERROR(unique(filter(Prod_Prop!$H:$H,Prod_Prop!$G:$G=$U25,Prod_Prop!$E:$E=Y$1)),""Check""))=0),"""",IFERROR(unique(filter(Prod_Prop!$H:$H,Prod_Prop!$G:$G=$U25,Prod_Prop!$E:$E=Y$1)),""""))"),"") | Z25: =IF(Y25="","",SUMIFS(Prod_Prop!$J:$J,Prod_Prop!$B:$B,$Q25,Prod_Prop!$H:$H,Y25,Prod_Prop!$I:$I,Z$1)*IF(Y25="Peso",$R25,1)) | AA25: =IF(Y25="","",SUMIFS(Prod_Prop!$J:$J,Prod_Prop!$B:$B,$Q25,Prod_Prop!$H:$H,Y25,Prod_Prop!$I:$I,AA$1)*IF(Y25="Peso",$R25,1)) | AB25: =IFERROR(__xludf.DUMMYFUNCTION("IF(OR($U25="""",COUNTIF($I:$I,IFERROR(unique(filter(Prod_Prop!$H:$H,Prod_Prop!$G:$G=$U25,Prod_Prop!$E:$E=AB$1)),""Check""))=0),"""",IFERROR(unique(filter(Prod_Prop!$H:$H,Prod_Prop!$G:$G=$U25,Prod_Prop!$E:$E=AB$1)),""""))"),"") | AC25: =IF(AB25="","",SUMIFS(Prod_Prop!$J:$J,Prod_Prop!$B:$B,$Q25,Prod_Prop!$H:$H,AB25,Prod_Prop!$I:$I,AC$1)*IF(AB25="Peso",$R25,1)) | AD25: =IF(AB25="","",SUMIFS(Prod_Prop!$J:$J,Prod_Prop!$B:$B,$Q25,Prod_Prop!$H:$H,AB25,Prod_Prop!$I:$I,AD$1)*IF(AB25="Peso",$R25,1))
A26: {=IF(COUNTIF(A$1:A25,Cotizador!F$2)=maxifs(Familias!E:E,Familias!D:D,Cotizador!F$2),IF(COUNTIF(A$1:A25,XLOOKUP(Cotizador!F$2,Implementos!B:B,Implementos!C:C,"",0,1))=SUMIFS(Implementos!D:D,Implementos!B:B,Cotizador!F$2,Implementos!C:C,XLOOKUP(Cotizador!F$2,Implementos!B:B,Implementos!C:C,"",0,1)),"",XLOOKUP(Cotizador!F$2,Implementos!B:B,Implementos!C:C,"",0,1)),Cotizador!F$2)} | B26: =IF(A26="","",COUNTIF(A$1:A26,A26)) | C26: {=IF(B26="","",IF(A26=XLOOKUP(A$2,Implementos!B:B,Implementos!C:C,"",0,1),B26+maxifs(B$1:B25,A$1:A25,A$2),B26))} | D26: =IF(B26="","", COUNTIFS(Productos!F:F,A26,Productos!H:H,B26)+IF(F26="SI",0,1)) | E26: =IFERROR(__xludf.DUMMYFUNCTION("IF($B26="""","""",INDEX(filter(Familias!F:F,Familias!$D:$D=$A26,Familias!$E:$E=$B26),1))"),"") | F26: =IFERROR(__xludf.DUMMYFUNCTION("IF($B26="""","""",INDEX(filter(Familias!G:G,Familias!$D:$D=$A26,Familias!$E:$E=$B26),1))"),"") | G26: {=IF(C26=1,XLOOKUP(C26,Cotizador!D:D,Cotizador!E:E,"",0,1),"")} | J26: =IF(I26="","",SUMIF(Cotizador!I$1:V$1,I26,Cotizador!I$2:V$2)) | L26: {=IF(COUNTIF(L$1:L25,A$2)=SUMIF(A:A,A$2,D:D),IF(COUNTIF(L$1:L25,XLOOKUP(A$2,Implementos!B:B,Implementos!C:C,"",0,1))=SUMIF(A:A,XLOOKUP(A$2,Implementos!B:B,Implementos!C:C,"",0,1),D:D),"",XLOOKUP(A$2,Implementos!B:B,Implementos!C:C,"",0,1)),A$2)} -> Acoplados Rurales | M26: =IF(L26="","",max(M$1:M25)+1) -> 25 | N26: =IF(L26="","",IF(N25="Orden",1,IF(COUNTIFS(N$1:N25,N25,L$1:L25,L26)=SUMIFS(D:D,B:B,N25,A:A,L26),IF(N25=maxifs(B:B,A:A,L26),"",maxifs(N$1:N25,L$1:L25,L26)+1),N25))) -> 1 | O26: =IF(N26="","",SUMIFS(C:C,B:B,N26,A:A,L26)) -> 1 | P26: =IF(N26="","",COUNTIFS(N$1:N26,N26,L$1:L26,L26)) -> 25 | Q26: =IF(U26="","",SUMIF(Productos!E:E,U26,Productos!A:A)) -> 128 | R26: {=IF(L26="","", max(1,SUMIF(I:I,XLOOKUP(U26,Productos!E:E,Productos!G:G,"",0,1),J:J)))} -> 1 | S26: =IF(Q26="","",IF(SUMIFS(Compat_Vetado!D:D,Compat_Vetado!B:B,SUM(G:G),Compat_Vetado!C:C,Q26)=1,"SI",IF(OR(SUMIF(Cotizador!E:E,Q26,Cotizador!G:G)>0,SUMIFS(Compat_Vetado!D:D,Compat_Vetado!B:B,SUM(G:G),Compat_Vetado!C:C,Q26)=-1),"NO",""))) | T26: =IF(Q26="","",IF(S26="SI","x",IF(S26="NO","",IF(AND(OR(V26="",AND(W26<=SUMIF(I:I,V26,J:J),SUMIF(I:I,V26,J:J)<=X26)),OR(Y26="",AND(Z26<=SUMIF(I:I,Y26,J:J),SUMIF(I:I,Y26,J:J)<=AA26)),OR(AB26="",AND(AC26<=SUMIF(I:I,AB26,J:J),SUMIF(I:I,AB26,J:J)<=AD26))),"x","")))) -> x | U26: =IFERROR(__xludf.DUMMYFUNCTION("IF(P26="""","""",IFERROR(INDEX(filter(Productos!E:E,Productos!F:F=L26,Productos!H:H=N26),P26),IF(M26=SUM(D:D),""Finalizar"",""-"")))"),"Plataforma Playo 2.00 x 1.90 x 0.45 Lateral Simple Baranda Fija") -> Plataforma Playo 2.00 x 1.90 x 0.45 Lateral Simple Baranda Fija | V26: =IFERROR(__xludf.DUMMYFUNCTION("IF(OR($U26="""",COUNTIF($I:$I,IFERROR(unique(filter(Prod_Prop!$H:$H,Prod_Prop!$G:$G=$U26,Prod_Prop!$E:$E=V$1)),""Check""))=0),"""",IFERROR(unique(filter(Prod_Prop!$H:$H,Prod_Prop!$G:$G=$U26,Prod_Prop!$E:$E=V$1)),""""))"),"") | W26: =IF(V26="","",SUMIFS(Prod_Prop!$J:$J,Prod_Prop!$B:$B,$Q26,Prod_Prop!$H:$H,V26,Prod_Prop!$I:$I,W$1)*IF(V26="Peso",$R26,1)) | X26: =IF(V26="","",SUMIFS(Prod_Prop!$J:$J,Prod_Prop!$B:$B,$Q26,Prod_Prop!$H:$H,V26,Prod_Prop!$I:$I,X$1)*IF(V26="Peso",$R26,1)) | Y26: =IFERROR(__xludf.DUMMYFUNCTION("IF(OR($U26="""",COUNTIF($I:$I,IFERROR(unique(filter(Prod_Prop!$H:$H,Prod_Prop!$G:$G=$U26,Prod_Prop!$E:$E=Y$1)),""Check""))=0),"""",IFERROR(unique(filter(Prod_Prop!$H:$H,Prod_Prop!$G:$G=$U26,Prod_Prop!$E:$E=Y$1)),""""))"),"") | Z26: =IF(Y26="","",SUMIFS(Prod_Prop!$J:$J,Prod_Prop!$B:$B,$Q26,Prod_Prop!$H:$H,Y26,Prod_Prop!$I:$I,Z$1)*IF(Y26="Peso",$R26,1)) | AA26: =IF(Y26="","",SUMIFS(Prod_Prop!$J:$J,Prod_Prop!$B:$B,$Q26,Prod_Prop!$H:$H,Y26,Prod_Prop!$I:$I,AA$1)*IF(Y26="Peso",$R26,1)) | AB26: =IFERROR(__xludf.DUMMYFUNCTION("IF(OR($U26="""",COUNTIF($I:$I,IFERROR(unique(filter(Prod_Prop!$H:$H,Prod_Prop!$G:$G=$U26,Prod_Prop!$E:$E=AB$1)),""Check""))=0),"""",IFERROR(unique(filter(Prod_Prop!$H:$H,Prod_Prop!$G:$G=$U26,Prod_Prop!$E:$E=AB$1)),""""))"),"") | AC26: =IF(AB26="","",SUMIFS(Prod_Prop!$J:$J,Prod_Prop!$B:$B,$Q26,Prod_Prop!$H:$H,AB26,Prod_Prop!$I:$I,AC$1)*IF(AB26="Peso",$R26,1)) | AD26: =IF(AB26="","",SUMIFS(Prod_Prop!$J:$J,Prod_Prop!$B:$B,$Q26,Prod_Prop!$H:$H,AB26,Prod_Prop!$I:$I,AD$1)*IF(AB26="Peso",$R26,1))
A27: {=IF(COUNTIF(A$1:A26,Cotizador!F$2)=maxifs(Familias!E:E,Familias!D:D,Cotizador!F$2),IF(COUNTIF(A$1:A26,XLOOKUP(Cotizador!F$2,Implementos!B:B,Implementos!C:C,"",0,1))=SUMIFS(Implementos!D:D,Implementos!B:B,Cotizador!F$2,Implementos!C:C,XLOOKUP(Cotizador!F$2,Implementos!B:B,Implementos!C:C,"",0,1)),"",XLOOKUP(Cotizador!F$2,Implementos!B:B,Implementos!C:C,"",0,1)),Cotizador!F$2)} | B27: =IF(A27="","",COUNTIF(A$1:A27,A27)) | C27: {=IF(B27="","",IF(A27=XLOOKUP(A$2,Implementos!B:B,Implementos!C:C,"",0,1),B27+maxifs(B$1:B26,A$1:A26,A$2),B27))} | D27: =IF(B27="","", COUNTIFS(Productos!F:F,A27,Productos!H:H,B27)+IF(F27="SI",0,1)) | E27: =IFERROR(__xludf.DUMMYFUNCTION("IF($B27="""","""",INDEX(filter(Familias!F:F,Familias!$D:$D=$A27,Familias!$E:$E=$B27),1))"),"") | F27: =IFERROR(__xludf.DUMMYFUNCTION("IF($B27="""","""",INDEX(filter(Familias!G:G,Familias!$D:$D=$A27,Familias!$E:$E=$B27),1))"),"") | G27: {=IF(C27=1,XLOOKUP(C27,Cotizador!D:D,Cotizador!E:E,"",0,1),"")} | J27: =IF(I27="","",SUMIF(Cotizador!I$1:V$1,I27,Cotizador!I$2:V$2)) | L27: {=IF(COUNTIF(L$1:L26,A$2)=SUMIF(A:A,A$2,D:D),IF(COUNTIF(L$1:L26,XLOOKUP(A$2,Implementos!B:B,Implementos!C:C,"",0,1))=SUMIF(A:A,XLOOKUP(A$2,Implementos!B:B,Implementos!C:C,"",0,1),D:D),"",XLOOKUP(A$2,Implementos!B:B,Implementos!C:C,"",0,1)),A$2)} -> Acoplados Rurales | M27: =IF(L27="","",max(M$1:M26)+1) -> 26 | N27: =IF(L27="","",IF(N26="Orden",1,IF(COUNTIFS(N$1:N26,N26,L$1:L26,L27)=SUMIFS(D:D,B:B,N26,A:A,L27),IF(N26=maxifs(B:B,A:A,L27),"",maxifs(N$1:N26,L$1:L26,L27)+1),N26))) -> 1 | O27: =IF(N27="","",SUMIFS(C:C,B:B,N27,A:A,L27)) -> 1 | P27: =IF(N27="","",COUNTIFS(N$1:N27,N27,L$1:L27,L27)) -> 26 | Q27: =IF(U27="","",SUMIF(Productos!E:E,U27,Productos!A:A)) -> 129 | R27: {=IF(L27="","", max(1,SUMIF(I:I,XLOOKUP(U27,Productos!E:E,Productos!G:G,"",0,1),J:J)))} -> 1 | S27: =IF(Q27="","",IF(SUMIFS(Compat_Vetado!D:D,Compat_Vetado!B:B,SUM(G:G),Compat_Vetado!C:C,Q27)=1,"SI",IF(OR(SUMIF(Cotizador!E:E,Q27,Cotizador!G:G)>0,SUMIFS(Compat_Vetado!D:D,Compat_Vetado!B:B,SUM(G:G),Compat_Vetado!C:C,Q27)=-1),"NO",""))) | T27: =IF(Q27="","",IF(S27="SI","x",IF(S27="NO","",IF(AND(OR(V27="",AND(W27<=SUMIF(I:I,V27,J:J),SUMIF(I:I,V27,J:J)<=X27)),OR(Y27="",AND(Z27<=SUMIF(I:I,Y27,J:J),SUMIF(I:I,Y27,J:J)<=AA27)),OR(AB27="",AND(AC27<=SUMIF(I:I,AB27,J:J),SUMIF(I:I,AB27,J:J)<=AD27))),"x","")))) -> x | U27: =IFERROR(__xludf.DUMMYFUNCTION("IF(P27="""","""",IFERROR(INDEX(filter(Productos!E:E,Productos!F:F=L27,Productos!H:H=N27),P27),IF(M27=SUM(D:D),""Finalizar"",""-"")))"),"Plataforma Playo 5.00 x 1.90 x 0.60 Lateral Doble Baranda Fija") -> Plataforma Playo 5.00 x 1.90 x 0.60 Lateral Doble Baranda Fija | V27: =IFERROR(__xludf.DUMMYFUNCTION("IF(OR($U27="""",COUNTIF($I:$I,IFERROR(unique(filter(Prod_Prop!$H:$H,Prod_Prop!$G:$G=$U27,Prod_Prop!$E:$E=V$1)),""Check""))=0),"""",IFERROR(unique(filter(Prod_Prop!$H:$H,Prod_Prop!$G:$G=$U27,Prod_Prop!$E:$E=V$1)),""""))"),"") | W27: =IF(V27="","",SUMIFS(Prod_Prop!$J:$J,Prod_Prop!$B:$B,$Q27,Prod_Prop!$H:$H,V27,Prod_Prop!$I:$I,W$1)*IF(V27="Peso",$R27,1)) | X27: =IF(V27="","",SUMIFS(Prod_Prop!$J:$J,Prod_Prop!$B:$B,$Q27,Prod_Prop!$H:$H,V27,Prod_Prop!$I:$I,X$1)*IF(V27="Peso",$R27,1)) | Y27: =IFERROR(__xludf.DUMMYFUNCTION("IF(OR($U27="""",COUNTIF($I:$I,IFERROR(unique(filter(Prod_Prop!$H:$H,Prod_Prop!$G:$G=$U27,Prod_Prop!$E:$E=Y$1)),""Check""))=0),"""",IFERROR(unique(filter(Prod_Prop!$H:$H,Prod_Prop!$G:$G=$U27,Prod_Prop!$E:$E=Y$1)),""""))"),"") | Z27: =IF(Y27="","",SUMIFS(Prod_Prop!$J:$J,Prod_Prop!$B:$B,$Q27,Prod_Prop!$H:$H,Y27,Prod_Prop!$I:$I,Z$1)*IF(Y27="Peso",$R27,1)) | AA27: =IF(Y27="","",SUMIFS(Prod_Prop!$J:$J,Prod_Prop!$B:$B,$Q27,Prod_Prop!$H:$H,Y27,Prod_Prop!$I:$I,AA$1)*IF(Y27="Peso",$R27,1)) | AB27: =IFERROR(__xludf.DUMMYFUNCTION("IF(OR($U27="""",COUNTIF($I:$I,IFERROR(unique(filter(Prod_Prop!$H:$H,Prod_Prop!$G:$G=$U27,Prod_Prop!$E:$E=AB$1)),""Check""))=0),"""",IFERROR(unique(filter(Prod_Prop!$H:$H,Prod_Prop!$G:$G=$U27,Prod_Prop!$E:$E=AB$1)),""""))"),"") | AC27: =IF(AB27="","",SUMIFS(Prod_Prop!$J:$J,Prod_Prop!$B:$B,$Q27,Prod_Prop!$H:$H,AB27,Prod_Prop!$I:$I,AC$1)*IF(AB27="Peso",$R27,1)) | AD27: =IF(AB27="","",SUMIFS(Prod_Prop!$J:$J,Prod_Prop!$B:$B,$Q27,Prod_Prop!$H:$H,AB27,Prod_Prop!$I:$I,AD$1)*IF(AB27="Peso",$R27,1))
A28: {=IF(COUNTIF(A$1:A27,Cotizador!F$2)=maxifs(Familias!E:E,Familias!D:D,Cotizador!F$2),IF(COUNTIF(A$1:A27,XLOOKUP(Cotizador!F$2,Implementos!B:B,Implementos!C:C,"",0,1))=SUMIFS(Implementos!D:D,Implementos!B:B,Cotizador!F$2,Implementos!C:C,XLOOKUP(Cotizador!F$2,Implementos!B:B,Implementos!C:C,"",0,1)),"",XLOOKUP(Cotizador!F$2,Implementos!B:B,Implementos!C:C,"",0,1)),Cotizador!F$2)} | B28: =IF(A28="","",COUNTIF(A$1:A28,A28)) | C28: {=IF(B28="","",IF(A28=XLOOKUP(A$2,Implementos!B:B,Implementos!C:C,"",0,1),B28+maxifs(B$1:B27,A$1:A27,A$2),B28))} | D28: =IF(B28="","", COUNTIFS(Productos!F:F,A28,Productos!H:H,B28)+IF(F28="SI",0,1)) | E28: =IFERROR(__xludf.DUMMYFUNCTION("IF($B28="""","""",INDEX(filter(Familias!F:F,Familias!$D:$D=$A28,Familias!$E:$E=$B28),1))"),"") | F28: =IFERROR(__xludf.DUMMYFUNCTION("IF($B28="""","""",INDEX(filter(Familias!G:G,Familias!$D:$D=$A28,Familias!$E:$E=$B28),1))"),"") | G28: {=IF(C28=1,XLOOKUP(C28,Cotizador!D:D,Cotizador!E:E,"",0,1),"")} | J28: =IF(I28="","",SUMIF(Cotizador!I$1:V$1,I28,Cotizador!I$2:V$2)) | L28: {=IF(COUNTIF(L$1:L27,A$2)=SUMIF(A:A,A$2,D:D),IF(COUNTIF(L$1:L27,XLOOKUP(A$2,Implementos!B:B,Implementos!C:C,"",0,1))=SUMIF(A:A,XLOOKUP(A$2,Implementos!B:B,Implementos!C:C,"",0,1),D:D),"",XLOOKUP(A$2,Implementos!B:B,Implementos!C:C,"",0,1)),A$2)} -> Acoplados Rurales | M28: =IF(L28="","",max(M$1:M27)+1) -> 27 | N28: =IF(L28="","",IF(N27="Orden",1,IF(COUNTIFS(N$1:N27,N27,L$1:L27,L28)=SUMIFS(D:D,B:B,N27,A:A,L28),IF(N27=maxifs(B:B,A:A,L28),"",maxifs(N$1:N27,L$1:L27,L28)+1),N27))) -> 1 | O28: =IF(N28="","",SUMIFS(C:C,B:B,N28,A:A,L28)) -> 1 | P28: =IF(N28="","",COUNTIFS(N$1:N28,N28,L$1:L28,L28)) -> 27 | Q28: =IF(U28="","",SUMIF(Productos!E:E,U28,Productos!A:A)) -> 130 | R28: {=IF(L28="","", max(1,SUMIF(I:I,XLOOKUP(U28,Productos!E:E,Productos!G:G,"",0,1),J:J)))} -> 1 | S28: =IF(Q28="","",IF(SUMIFS(Compat_Vetado!D:D,Compat_Vetado!B:B,SUM(G:G),Compat_Vetado!C:C,Q28)=1,"SI",IF(OR(SUMIF(Cotizador!E:E,Q28,Cotizador!G:G)>0,SUMIFS(Compat_Vetado!D:D,Compat_Vetado!B:B,SUM(G:G),Compat_Vetado!C:C,Q28)=-1),"NO",""))) | T28: =IF(Q28="","",IF(S28="SI","x",IF(S28="NO","",IF(AND(OR(V28="",AND(W28<=SUMIF(I:I,V28,J:J),SUMIF(I:I,V28,J:J)<=X28)),OR(Y28="",AND(Z28<=SUMIF(I:I,Y28,J:J),SUMIF(I:I,Y28,J:J)<=AA28)),OR(AB28="",AND(AC28<=SUMIF(I:I,AB28,J:J),SUMIF(I:I,AB28,J:J)<=AD28))),"x","")))) -> x | U28: =IFERROR(__xludf.DUMMYFUNCTION("IF(P28="""","""",IFERROR(INDEX(filter(Productos!E:E,Productos!F:F=L28,Productos!H:H=N28),P28),IF(M28=SUM(D:D),""Finalizar"",""-"")))"),"Plataforma Playo 6.40 x 2.70 x 0.72 Lateral Doble Baranda Fija") -> Plataforma Playo 6.40 x 2.70 x 0.72 Lateral Doble Baranda Fija | V28: =IFERROR(__xludf.DUMMYFUNCTION("IF(OR($U28="""",COUNTIF($I:$I,IFERROR(unique(filter(Prod_Prop!$H:$H,Prod_Prop!$G:$G=$U28,Prod_Prop!$E:$E=V$1)),""Check""))=0),"""",IFERROR(unique(filter(Prod_Prop!$H:$H,Prod_Prop!$G:$G=$U28,Prod_Prop!$E:$E=V$1)),""""))"),"") | W28: =IF(V28="","",SUMIFS(Prod_Prop!$J:$J,Prod_Prop!$B:$B,$Q28,Prod_Prop!$H:$H,V28,Prod_Prop!$I:$I,W$1)*IF(V28="Peso",$R28,1)) | X28: =IF(V28="","",SUMIFS(Prod_Prop!$J:$J,Prod_Prop!$B:$B,$Q28,Prod_Prop!$H:$H,V28,Prod_Prop!$I:$I,X$1)*IF(V28="Peso",$R28,1)) | Y28: =IFERROR(__xludf.DUMMYFUNCTION("IF(OR($U28="""",COUNTIF($I:$I,IFERROR(unique(filter(Prod_Prop!$H:$H,Prod_Prop!$G:$G=$U28,Prod_Prop!$E:$E=Y$1)),""Check""))=0),"""",IFERROR(unique(filter(Prod_Prop!$H:$H,Prod_Prop!$G:$G=$U28,Prod_Prop!$E:$E=Y$1)),""""))"),"") | Z28: =IF(Y28="","",SUMIFS(Prod_Prop!$J:$J,Prod_Prop!$B:$B,$Q28,Prod_Prop!$H:$H,Y28,Prod_Prop!$I:$I,Z$1)*IF(Y28="Peso",$R28,1)) | AA28: =IF(Y28="","",SUMIFS(Prod_Prop!$J:$J,Prod_Prop!$B:$B,$Q28,Prod_Prop!$H:$H,Y28,Prod_Prop!$I:$I,AA$1)*IF(Y28="Peso",$R28,1)) | AB28: =IFERROR(__xludf.DUMMYFUNCTION("IF(OR($U28="""",COUNTIF($I:$I,IFERROR(unique(filter(Prod_Prop!$H:$H,Prod_Prop!$G:$G=$U28,Prod_Prop!$E:$E=AB$1)),""Check""))=0),"""",IFERROR(unique(filter(Prod_Prop!$H:$H,Prod_Prop!$G:$G=$U28,Prod_Prop!$E:$E=AB$1)),""""))"),"") | AC28: =IF(AB28="","",SUMIFS(Prod_Prop!$J:$J,Prod_Prop!$B:$B,$Q28,Prod_Prop!$H:$H,AB28,Prod_Prop!$I:$I,AC$1)*IF(AB28="Peso",$R28,1)) | AD28: =IF(AB28="","",SUMIFS(Prod_Prop!$J:$J,Prod_Prop!$B:$B,$Q28,Prod_Prop!$H:$H,AB28,Prod_Prop!$I:$I,AD$1)*IF(AB28="Peso",$R28,1))
A29: {=IF(COUNTIF(A$1:A28,Cotizador!F$2)=maxifs(Familias!E:E,Familias!D:D,Cotizador!F$2),IF(COUNTIF(A$1:A28,XLOOKUP(Cotizador!F$2,Implementos!B:B,Implementos!C:C,"",0,1))=SUMIFS(Implementos!D:D,Implementos!B:B,Cotizador!F$2,Implementos!C:C,XLOOKUP(Cotizador!F$2,Implementos!B:B,Implementos!C:C,"",0,1)),"",XLOOKUP(Cotizador!F$2,Implementos!B:B,Implementos!C:C,"",0,1)),Cotizador!F$2)} | B29: =IF(A29="","",COUNTIF(A$1:A29,A29)) | C29: {=IF(B29="","",IF(A29=XLOOKUP(A$2,Implementos!B:B,Implementos!C:C,"",0,1),B29+maxifs(B$1:B28,A$1:A28,A$2),B29))} | D29: =IF(B29="","", COUNTIFS(Productos!F:F,A29,Productos!H:H,B29)+IF(F29="SI",0,1)) | E29: =IFERROR(__xludf.DUMMYFUNCTION("IF($B29="""","""",INDEX(filter(Familias!F:F,Familias!$D:$D=$A29,Familias!$E:$E=$B29),1))"),"") | F29: =IFERROR(__xludf.DUMMYFUNCTION("IF($B29="""","""",INDEX(filter(Familias!G:G,Familias!$D:$D=$A29,Familias!$E:$E=$B29),1))"),"") | G29: {=IF(C29=1,XLOOKUP(C29,Cotizador!D:D,Cotizador!E:E,"",0,1),"")} | J29: =IF(I29="","",SUMIF(Cotizador!I$1:V$1,I29,Cotizador!I$2:V$2)) | L29: {=IF(COUNTIF(L$1:L28,A$2)=SUMIF(A:A,A$2,D:D),IF(COUNTIF(L$1:L28,XLOOKUP(A$2,Implementos!B:B,Implementos!C:C,"",0,1))=SUMIF(A:A,XLOOKUP(A$2,Implementos!B:B,Implementos!C:C,"",0,1),D:D),"",XLOOKUP(A$2,Implementos!B:B,Implementos!C:C,"",0,1)),A$2)} -> Acoplados Rurales | M29: =IF(L29="","",max(M$1:M28)+1) -> 28 | N29: =IF(L29="","",IF(N28="Orden",1,IF(COUNTIFS(N$1:N28,N28,L$1:L28,L29)=SUMIFS(D:D,B:B,N28,A:A,L29),IF(N28=maxifs(B:B,A:A,L29),"",maxifs(N$1:N28,L$1:L28,L29)+1),N28))) -> 1 | O29: =IF(N29="","",SUMIFS(C:C,B:B,N29,A:A,L29)) -> 1 | P29: =IF(N29="","",COUNTIFS(N$1:N29,N29,L$1:L29,L29)) -> 28 | Q29: =IF(U29="","",SUMIF(Productos!E:E,U29,Productos!A:A)) -> 0 | R29: {=IF(L29="","", max(1,SUMIF(I:I,XLOOKUP(U29,Productos!E:E,Productos!G:G,"",0,1),J:J)))} -> 1 | S29: =IF(Q29="","",IF(SUMIFS(Compat_Vetado!D:D,Compat_Vetado!B:B,SUM(G:G),Compat_Vetado!C:C,Q29)=1,"SI",IF(OR(SUMIF(Cotizador!E:E,Q29,Cotizador!G:G)>0,SUMIFS(Compat_Vetado!D:D,Compat_Vetado!B:B,SUM(G:G),Compat_Vetado!C:C,Q29)=-1),"NO",""))) | T29: =IF(Q29="","",IF(S29="SI","x",IF(S29="NO","",IF(AND(OR(V29="",AND(W29<=SUMIF(I:I,V29,J:J),SUMIF(I:I,V29,J:J)<=X29)),OR(Y29="",AND(Z29<=SUMIF(I:I,Y29,J:J),SUMIF(I:I,Y29,J:J)<=AA29)),OR(AB29="",AND(AC29<=SUMIF(I:I,AB29,J:J),SUMIF(I:I,AB29,J:J)<=AD29))),"x","")))) -> x | U29: =IFERROR(__xludf.DUMMYFUNCTION("IF(P29="""","""",IFERROR(INDEX(filter(Productos!E:E,Productos!F:F=L29,Productos!H:H=N29),P29),IF(M29=SUM(D:D),""Finalizar"",""-"")))"),"-") -> - | V29: =IFERROR(__xludf.DUMMYFUNCTION("IF(OR($U29="""",COUNTIF($I:$I,IFERROR(unique(filter(Prod_Prop!$H:$H,Prod_Prop!$G:$G=$U29,Prod_Prop!$E:$E=V$1)),""Check""))=0),"""",IFERROR(unique(filter(Prod_Prop!$H:$H,Prod_Prop!$G:$G=$U29,Prod_Prop!$E:$E=V$1)),""""))"),"") | W29: =IF(V29="","",SUMIFS(Prod_Prop!$J:$J,Prod_Prop!$B:$B,$Q29,Prod_Prop!$H:$H,V29,Prod_Prop!$I:$I,W$1)*IF(V29="Peso",$R29,1)) | X29: =IF(V29="","",SUMIFS(Prod_Prop!$J:$J,Prod_Prop!$B:$B,$Q29,Prod_Prop!$H:$H,V29,Prod_Prop!$I:$I,X$1)*IF(V29="Peso",$R29,1)) | Y29: =IFERROR(__xludf.DUMMYFUNCTION("IF(OR($U29="""",COUNTIF($I:$I,IFERROR(unique(filter(Prod_Prop!$H:$H,Prod_Prop!$G:$G=$U29,Prod_Prop!$E:$E=Y$1)),""Check""))=0),"""",IFERROR(unique(filter(Prod_Prop!$H:$H,Prod_Prop!$G:$G=$U29,Prod_Prop!$E:$E=Y$1)),""""))"),"") | Z29: =IF(Y29="","",SUMIFS(Prod_Prop!$J:$J,Prod_Prop!$B:$B,$Q29,Prod_Prop!$H:$H,Y29,Prod_Prop!$I:$I,Z$1)*IF(Y29="Peso",$R29,1)) | AA29: =IF(Y29="","",SUMIFS(Prod_Prop!$J:$J,Prod_Prop!$B:$B,$Q29,Prod_Prop!$H:$H,Y29,Prod_Prop!$I:$I,AA$1)*IF(Y29="Peso",$R29,1)) | AB29: =IFERROR(__xludf.DUMMYFUNCTION("IF(OR($U29="""",COUNTIF($I:$I,IFERROR(unique(filter(Prod_Prop!$H:$H,Prod_Prop!$G:$G=$U29,Prod_Prop!$E:$E=AB$1)),""Check""))=0),"""",IFERROR(unique(filter(Prod_Prop!$H:$H,Prod_Prop!$G:$G=$U29,Prod_Prop!$E:$E=AB$1)),""""))"),"") | AC29: =IF(AB29="","",SUMIFS(Prod_Prop!$J:$J,Prod_Prop!$B:$B,$Q29,Prod_Prop!$H:$H,AB29,Prod_Prop!$I:$I,AC$1)*IF(AB29="Peso",$R29,1)) | AD29: =IF(AB29="","",SUMIFS(Prod_Prop!$J:$J,Prod_Prop!$B:$B,$Q29,Prod_Prop!$H:$H,AB29,Prod_Prop!$I:$I,AD$1)*IF(AB29="Peso",$R29,1))
A30: {=IF(COUNTIF(A$1:A29,Cotizador!F$2)=maxifs(Familias!E:E,Familias!D:D,Cotizador!F$2),IF(COUNTIF(A$1:A29,XLOOKUP(Cotizador!F$2,Implementos!B:B,Implementos!C:C,"",0,1))=SUMIFS(Implementos!D:D,Implementos!B:B,Cotizador!F$2,Implementos!C:C,XLOOKUP(Cotizador!F$2,Implementos!B:B,Implementos!C:C,"",0,1)),"",XLOOKUP(Cotizador!F$2,Implementos!B:B,Implementos!C:C,"",0,1)),Cotizador!F$2)} | B30: =IF(A30="","",COUNTIF(A$1:A30,A30)) | C30: {=IF(B30="","",IF(A30=XLOOKUP(A$2,Implementos!B:B,Implementos!C:C,"",0,1),B30+maxifs(B$1:B29,A$1:A29,A$2),B30))} | D30: =IF(B30="","", COUNTIFS(Productos!F:F,A30,Productos!H:H,B30)+IF(F30="SI",0,1)) | E30: =IFERROR(__xludf.DUMMYFUNCTION("IF($B30="""","""",INDEX(filter(Familias!F:F,Familias!$D:$D=$A30,Familias!$E:$E=$B30),1))"),"") | F30: =IFERROR(__xludf.DUMMYFUNCTION("IF($B30="""","""",INDEX(filter(Familias!G:G,Familias!$D:$D=$A30,Familias!$E:$E=$B30),1))"),"") | G30: {=IF(C30=1,XLOOKUP(C30,Cotizador!D:D,Cotizador!E:E,"",0,1),"")} | J30: =IF(I30="","",SUMIF(Cotizador!I$1:V$1,I30,Cotizador!I$2:V$2)) | L30: {=IF(COUNTIF(L$1:L29,A$2)=SUMIF(A:A,A$2,D:D),IF(COUNTIF(L$1:L29,XLOOKUP(A$2,Implementos!B:B,Implementos!C:C,"",0,1))=SUMIF(A:A,XLOOKUP(A$2,Implementos!B:B,Implementos!C:C,"",0,1),D:D),"",XLOOKUP(A$2,Implementos!B:B,Implementos!C:C,"",0,1)),A$2)} -> Acoplados Rurales | M30: =IF(L30="","",max(M$1:M29)+1) -> 29 | N30: =IF(L30="","",IF(N29="Orden",1,IF(COUNTIFS(N$1:N29,N29,L$1:L29,L30)=SUMIFS(D:D,B:B,N29,A:A,L30),IF(N29=maxifs(B:B,A:A,L30),"",maxifs(N$1:N29,L$1:L29,L30)+1),N29))) -> 2 | O30: =IF(N30="","",SUMIFS(C:C,B:B,N30,A:A,L30)) -> 2 | P30: =IF(N30="","",COUNTIFS(N$1:N30,N30,L$1:L30,L30)) -> 1 | Q30: =IF(U30="","",SUMIF(Productos!E:E,U30,Productos!A:A)) -> 57 | R30: {=IF(L30="","", max(1,SUMIF(I:I,XLOOKUP(U30,Productos!E:E,Productos!G:G,"",0,1),J:J)))} -> 1 | S30: =IF(Q30="","",IF(SUMIFS(Compat_Vetado!D:D,Compat_Vetado!B:B,SUM(G:G),Compat_Vetado!C:C,Q30)=1,"SI",IF(OR(SUMIF(Cotizador!E:E,Q30,Cotizador!G:G)>0,SUMIFS(Compat_Vetado!D:D,Compat_Vetado!B:B,SUM(G:G),Compat_Vetado!C:C,Q30)=-1),"NO",""))) -> NO | T30: =IF(Q30="","",IF(S30="SI","x",IF(S30="NO","",IF(AND(OR(V30="",AND(W30<=SUMIF(I:I,V30,J:J),SUMIF(I:I,V30,J:J)<=X30)),OR(Y30="",AND(Z30<=SUMIF(I:I,Y30,J:J),SUMIF(I:I,Y30,J:J)<=AA30)),OR(AB30="",AND(AC30<=SUMIF(I:I,AB30,J:J),SUMIF(I:I,AB30,J:J)<=AD30))),"x","")))) | U30: =IFERROR(__xludf.DUMMYFUNCTION("IF(P30="""","""",IFERROR(INDEX(filter(Productos!E:E,Productos!F:F=L30,Productos!H:H=N30),P30),IF(M30=SUM(D:D),""Finalizar"",""-"")))"),"Baulera Standard - 750") -> Baulera Standard - 750 | V30: =IFERROR(__xludf.DUMMYFUNCTION("IF(OR($U30="""",COUNTIF($I:$I,IFERROR(unique(filter(Prod_Prop!$H:$H,Prod_Prop!$G:$G=$U30,Prod_Prop!$E:$E=V$1)),""Check""))=0),"""",IFERROR(unique(filter(Prod_Prop!$H:$H,Prod_Prop!$G:$G=$U30,Prod_Prop!$E:$E=V$1)),""""))"),"") | W30: =IF(V30="","",SUMIFS(Prod_Prop!$J:$J,Prod_Prop!$B:$B,$Q30,Prod_Prop!$H:$H,V30,Prod_Prop!$I:$I,W$1)*IF(V30="Peso",$R30,1)) | X30: =IF(V30="","",SUMIFS(Prod_Prop!$J:$J,Prod_Prop!$B:$B,$Q30,Prod_Prop!$H:$H,V30,Prod_Prop!$I:$I,X$1)*IF(V30="Peso",$R30,1)) | Y30: =IFERROR(__xludf.DUMMYFUNCTION("IF(OR($U30="""",COUNTIF($I:$I,IFERROR(unique(filter(Prod_Prop!$H:$H,Prod_Prop!$G:$G=$U30,Prod_Prop!$E:$E=Y$1)),""Check""))=0),"""",IFERROR(unique(filter(Prod_Prop!$H:$H,Prod_Prop!$G:$G=$U30,Prod_Prop!$E:$E=Y$1)),""""))"),"") | Z30: =IF(Y30="","",SUMIFS(Prod_Prop!$J:$J,Prod_Prop!$B:$B,$Q30,Prod_Prop!$H:$H,Y30,Prod_Prop!$I:$I,Z$1)*IF(Y30="Peso",$R30,1)) | AA30: =IF(Y30="","",SUMIFS(Prod_Prop!$J:$J,Prod_Prop!$B:$B,$Q30,Prod_Prop!$H:$H,Y30,Prod_Prop!$I:$I,AA$1)*IF(Y30="Peso",$R30,1)) | AB30: =IFERROR(__xludf.DUMMYFUNCTION("IF(OR($U30="""",COUNTIF($I:$I,IFERROR(unique(filter(Prod_Prop!$H:$H,Prod_Prop!$G:$G=$U30,Prod_Prop!$E:$E=AB$1)),""Check""))=0),"""",IFERROR(unique(filter(Prod_Prop!$H:$H,Prod_Prop!$G:$G=$U30,Prod_Prop!$E:$E=AB$1)),""""))"),"") | AC30: =IF(AB30="","",SUMIFS(Prod_Prop!$J:$J,Prod_Prop!$B:$B,$Q30,Prod_Prop!$H:$H,AB30,Prod_Prop!$I:$I,AC$1)*IF(AB30="Peso",$R30,1)) | AD30: =IF(AB30="","",SUMIFS(Prod_Prop!$J:$J,Prod_Prop!$B:$B,$Q30,Prod_Prop!$H:$H,AB30,Prod_Prop!$I:$I,AD$1)*IF(AB30="Peso",$R30,1))
A31: {=IF(COUNTIF(A$1:A30,Cotizador!F$2)=maxifs(Familias!E:E,Familias!D:D,Cotizador!F$2),IF(COUNTIF(A$1:A30,XLOOKUP(Cotizador!F$2,Implementos!B:B,Implementos!C:C,"",0,1))=SUMIFS(Implementos!D:D,Implementos!B:B,Cotizador!F$2,Implementos!C:C,XLOOKUP(Cotizador!F$2,Implementos!B:B,Implementos!C:C,"",0,1)),"",XLOOKUP(Cotizador!F$2,Implementos!B:B,Implementos!C:C,"",0,1)),Cotizador!F$2)} | B31: =IF(A31="","",COUNTIF(A$1:A31,A31)) | C31: {=IF(B31="","",IF(A31=XLOOKUP(A$2,Implementos!B:B,Implementos!C:C,"",0,1),B31+maxifs(B$1:B30,A$1:A30,A$2),B31))} | D31: =IF(B31="","", COUNTIFS(Productos!F:F,A31,Productos!H:H,B31)+IF(F31="SI",0,1)) | E31: =IFERROR(__xludf.DUMMYFUNCTION("IF($B31="""","""",INDEX(filter(Familias!F:F,Familias!$D:$D=$A31,Familias!$E:$E=$B31),1))"),"") | F31: =IFERROR(__xludf.DUMMYFUNCTION("IF($B31="""","""",INDEX(filter(Familias!G:G,Familias!$D:$D=$A31,Familias!$E:$E=$B31),1))"),"") | G31: {=IF(C31=1,XLOOKUP(C31,Cotizador!D:D,Cotizador!E:E,"",0,1),"")} | J31: =IF(I31="","",SUMIF(Cotizador!I$1:V$1,I31,Cotizador!I$2:V$2)) | L31: {=IF(COUNTIF(L$1:L30,A$2)=SUMIF(A:A,A$2,D:D),IF(COUNTIF(L$1:L30,XLOOKUP(A$2,Implementos!B:B,Implementos!C:C,"",0,1))=SUMIF(A:A,XLOOKUP(A$2,Implementos!B:B,Implementos!C:C,"",0,1),D:D),"",XLOOKUP(A$2,Implementos!B:B,Implementos!C:C,"",0,1)),A$2)} -> Acoplados Rurales | M31: =IF(L31="","",max(M$1:M30)+1) -> 30 | N31: =IF(L31="","",IF(N30="Orden",1,IF(COUNTIFS(N$1:N30,N30,L$1:L30,L31)=SUMIFS(D:D,B:B,N30,A:A,L31),IF(N30=maxifs(B:B,A:A,L31),"",maxifs(N$1:N30,L$1:L30,L31)+1),N30))) -> 2 | O31: =IF(N31="","",SUMIFS(C:C,B:B,N31,A:A,L31)) -> 2 | P31: =IF(N31="","",COUNTIFS(N$1:N31,N31,L$1:L31,L31)) -> 2 | Q31: =IF(U31="","",SUMIF(Productos!E:E,U31,Productos!A:A)) -> 58 | R31: {=IF(L31="","", max(1,SUMIF(I:I,XLOOKUP(U31,Productos!E:E,Productos!G:G,"",0,1),J:J)))} -> 1 | S31: =IF(Q31="","",IF(SUMIFS(Compat_Vetado!D:D,Compat_Vetado!B:B,SUM(G:G),Compat_Vetado!C:C,Q31)=1,"SI",IF(OR(SUMIF(Cotizador!E:E,Q31,Cotizador!G:G)>0,SUMIFS(Compat_Vetado!D:D,Compat_Vetado!B:B,SUM(G:G),Compat_Vetado!C:C,Q31)=-1),"NO",""))) | T31: =IF(Q31="","",IF(S31="SI","x",IF(S31="NO","",IF(AND(OR(V31="",AND(W31<=SUMIF(I:I,V31,J:J),SUMIF(I:I,V31,J:J)<=X31)),OR(Y31="",AND(Z31<=SUMIF(I:I,Y31,J:J),SUMIF(I:I,Y31,J:J)<=AA31)),OR(AB31="",AND(AC31<=SUMIF(I:I,AB31,J:J),SUMIF(I:I,AB31,J:J)<=AD31))),"x","")))) -> x | U31: =IFERROR(__xludf.DUMMYFUNCTION("IF(P31="""","""",IFERROR(INDEX(filter(Productos!E:E,Productos!F:F=L31,Productos!H:H=N31),P31),IF(M31=SUM(D:D),""Finalizar"",""-"")))"),"Baulera Standard - 1700 - C/Laterales") -> Baulera Standard - 1700 - C/Laterales | V31: =IFERROR(__xludf.DUMMYFUNCTION("IF(OR($U31="""",COUNTIF($I:$I,IFERROR(unique(filter(Prod_Prop!$H:$H,Prod_Prop!$G:$G=$U31,Prod_Prop!$E:$E=V$1)),""Check""))=0),"""",IFERROR(unique(filter(Prod_Prop!$H:$H,Prod_Prop!$G:$G=$U31,Prod_Prop!$E:$E=V$1)),""""))"),"") | W31: =IF(V31="","",SUMIFS(Prod_Prop!$J:$J,Prod_Prop!$B:$B,$Q31,Prod_Prop!$H:$H,V31,Prod_Prop!$I:$I,W$1)*IF(V31="Peso",$R31,1)) | X31: =IF(V31="","",SUMIFS(Prod_Prop!$J:$J,Prod_Prop!$B:$B,$Q31,Prod_Prop!$H:$H,V31,Prod_Prop!$I:$I,X$1)*IF(V31="Peso",$R31,1)) | Y31: =IFERROR(__xludf.DUMMYFUNCTION("IF(OR($U31="""",COUNTIF($I:$I,IFERROR(unique(filter(Prod_Prop!$H:$H,Prod_Prop!$G:$G=$U31,Prod_Prop!$E:$E=Y$1)),""Check""))=0),"""",IFERROR(unique(filter(Prod_Prop!$H:$H,Prod_Prop!$G:$G=$U31,Prod_Prop!$E:$E=Y$1)),""""))"),"") | Z31: =IF(Y31="","",SUMIFS(Prod_Prop!$J:$J,Prod_Prop!$B:$B,$Q31,Prod_Prop!$H:$H,Y31,Prod_Prop!$I:$I,Z$1)*IF(Y31="Peso",$R31,1)) | AA31: =IF(Y31="","",SUMIFS(Prod_Prop!$J:$J,Prod_Prop!$B:$B,$Q31,Prod_Prop!$H:$H,Y31,Prod_Prop!$I:$I,AA$1)*IF(Y31="Peso",$R31,1)) | AB31: =IFERROR(__xludf.DUMMYFUNCTION("IF(OR($U31="""",COUNTIF($I:$I,IFERROR(unique(filter(Prod_Prop!$H:$H,Prod_Prop!$G:$G=$U31,Prod_Prop!$E:$E=AB$1)),""Check""))=0),"""",IFERROR(unique(filter(Prod_Prop!$H:$H,Prod_Prop!$G:$G=$U31,Prod_Prop!$E:$E=AB$1)),""""))"),"") | AC31: =IF(AB31="","",SUMIFS(Prod_Prop!$J:$J,Prod_Prop!$B:$B,$Q31,Prod_Prop!$H:$H,AB31,Prod_Prop!$I:$I,AC$1)*IF(AB31="Peso",$R31,1)) | AD31: =IF(AB31="","",SUMIFS(Prod_Prop!$J:$J,Prod_Prop!$B:$B,$Q31,Prod_Prop!$H:$H,AB31,Prod_Prop!$I:$I,AD$1)*IF(AB31="Peso",$R31,1))
A32: {=IF(COUNTIF(A$1:A31,Cotizador!F$2)=maxifs(Familias!E:E,Familias!D:D,Cotizador!F$2),IF(COUNTIF(A$1:A31,XLOOKUP(Cotizador!F$2,Implementos!B:B,Implementos!C:C,"",0,1))=SUMIFS(Implementos!D:D,Implementos!B:B,Cotizador!F$2,Implementos!C:C,XLOOKUP(Cotizador!F$2,Implementos!B:B,Implementos!C:C,"",0,1)),"",XLOOKUP(Cotizador!F$2,Implementos!B:B,Implementos!C:C,"",0,1)),Cotizador!F$2)} | B32: =IF(A32="","",COUNTIF(A$1:A32,A32)) | C32: {=IF(B32="","",IF(A32=XLOOKUP(A$2,Implementos!B:B,Implementos!C:C,"",0,1),B32+maxifs(B$1:B31,A$1:A31,A$2),B32))} | D32: =IF(B32="","", COUNTIFS(Productos!F:F,A32,Productos!H:H,B32)+IF(F32="SI",0,1)) | E32: =IFERROR(__xludf.DUMMYFUNCTION("IF($B32="""","""",INDEX(filter(Familias!F:F,Familias!$D:$D=$A32,Familias!$E:$E=$B32),1))"),"") | F32: =IFERROR(__xludf.DUMMYFUNCTION("IF($B32="""","""",INDEX(filter(Familias!G:G,Familias!$D:$D=$A32,Familias!$E:$E=$B32),1))"),"") | G32: {=IF(C32=1,XLOOKUP(C32,Cotizador!D:D,Cotizador!E:E,"",0,1),"")} | J32: =IF(I32="","",SUMIF(Cotizador!I$1:V$1,I32,Cotizador!I$2:V$2)) | L32: {=IF(COUNTIF(L$1:L31,A$2)=SUMIF(A:A,A$2,D:D),IF(COUNTIF(L$1:L31,XLOOKUP(A$2,Implementos!B:B,Implementos!C:C,"",0,1))=SUMIF(A:A,XLOOKUP(A$2,Implementos!B:B,Implementos!C:C,"",0,1),D:D),"",XLOOKUP(A$2,Implementos!B:B,Implementos!C:C,"",0,1)),A$2)} -> Acoplados Rurales | M32: =IF(L32="","",max(M$1:M31)+1) -> 31 | N32: =IF(L32="","",IF(N31="Orden",1,IF(COUNTIFS(N$1:N31,N31,L$1:L31,L32)=SUMIFS(D:D,B:B,N31,A:A,L32),IF(N31=maxifs(B:B,A:A,L32),"",maxifs(N$1:N31,L$1:L31,L32)+1),N31))) -> 2 | O32: =IF(N32="","",SUMIFS(C:C,B:B,N32,A:A,L32)) -> 2 | P32: =IF(N32="","",COUNTIFS(N$1:N32,N32,L$1:L32,L32)) -> 3 | Q32: =IF(U32="","",SUMIF(Productos!E:E,U32,Productos!A:A)) -> 59 | R32: {=IF(L32="","", max(1,SUMIF(I:I,XLOOKUP(U32,Productos!E:E,Productos!G:G,"",0,1),J:J)))} -> 1 | S32: =IF(Q32="","",IF(SUMIFS(Compat_Vetado!D:D,Compat_Vetado!B:B,SUM(G:G),Compat_Vetado!C:C,Q32)=1,"SI",IF(OR(SUMIF(Cotizador!E:E,Q32,Cotizador!G:G)>0,SUMIFS(Compat_Vetado!D:D,Compat_Vetado!B:B,SUM(G:G),Compat_Vetado!C:C,Q32)=-1),"NO",""))) | T32: =IF(Q32="","",IF(S32="SI","x",IF(S32="NO","",IF(AND(OR(V32="",AND(W32<=SUMIF(I:I,V32,J:J),SUMIF(I:I,V32,J:J)<=X32)),OR(Y32="",AND(Z32<=SUMIF(I:I,Y32,J:J),SUMIF(I:I,Y32,J:J)<=AA32)),OR(AB32="",AND(AC32<=SUMIF(I:I,AB32,J:J),SUMIF(I:I,AB32,J:J)<=AD32))),"x","")))) -> x | U32: =IFERROR(__xludf.DUMMYFUNCTION("IF(P32="""","""",IFERROR(INDEX(filter(Productos!E:E,Productos!F:F=L32,Productos!H:H=N32),P32),IF(M32=SUM(D:D),""Finalizar"",""-"")))"),"Baulera Standard - 1000 - C/Laterales") -> Baulera Standard - 1000 - C/Laterales | V32: =IFERROR(__xludf.DUMMYFUNCTION("IF(OR($U32="""",COUNTIF($I:$I,IFERROR(unique(filter(Prod_Prop!$H:$H,Prod_Prop!$G:$G=$U32,Prod_Prop!$E:$E=V$1)),""Check""))=0),"""",IFERROR(unique(filter(Prod_Prop!$H:$H,Prod_Prop!$G:$G=$U32,Prod_Prop!$E:$E=V$1)),""""))"),"") | W32: =IF(V32="","",SUMIFS(Prod_Prop!$J:$J,Prod_Prop!$B:$B,$Q32,Prod_Prop!$H:$H,V32,Prod_Prop!$I:$I,W$1)*IF(V32="Peso",$R32,1)) | X32: =IF(V32="","",SUMIFS(Prod_Prop!$J:$J,Prod_Prop!$B:$B,$Q32,Prod_Prop!$H:$H,V32,Prod_Prop!$I:$I,X$1)*IF(V32="Peso",$R32,1)) | Y32: =IFERROR(__xludf.DUMMYFUNCTION("IF(OR($U32="""",COUNTIF($I:$I,IFERROR(unique(filter(Prod_Prop!$H:$H,Prod_Prop!$G:$G=$U32,Prod_Prop!$E:$E=Y$1)),""Check""))=0),"""",IFERROR(unique(filter(Prod_Prop!$H:$H,Prod_Prop!$G:$G=$U32,Prod_Prop!$E:$E=Y$1)),""""))"),"") | Z32: =IF(Y32="","",SUMIFS(Prod_Prop!$J:$J,Prod_Prop!$B:$B,$Q32,Prod_Prop!$H:$H,Y32,Prod_Prop!$I:$I,Z$1)*IF(Y32="Peso",$R32,1)) | AA32: =IF(Y32="","",SUMIFS(Prod_Prop!$J:$J,Prod_Prop!$B:$B,$Q32,Prod_Prop!$H:$H,Y32,Prod_Prop!$I:$I,AA$1)*IF(Y32="Peso",$R32,1)) | AB32: =IFERROR(__xludf.DUMMYFUNCTION("IF(OR($U32="""",COUNTIF($I:$I,IFERROR(unique(filter(Prod_Prop!$H:$H,Prod_Prop!$G:$G=$U32,Prod_Prop!$E:$E=AB$1)),""Check""))=0),"""",IFERROR(unique(filter(Prod_Prop!$H:$H,Prod_Prop!$G:$G=$U32,Prod_Prop!$E:$E=AB$1)),""""))"),"") | AC32: =IF(AB32="","",SUMIFS(Prod_Prop!$J:$J,Prod_Prop!$B:$B,$Q32,Prod_Prop!$H:$H,AB32,Prod_Prop!$I:$I,AC$1)*IF(AB32="Peso",$R32,1)) | AD32: =IF(AB32="","",SUMIFS(Prod_Prop!$J:$J,Prod_Prop!$B:$B,$Q32,Prod_Prop!$H:$H,AB32,Prod_Prop!$I:$I,AD$1)*IF(AB32="Peso",$R32,1))
A33: {=IF(COUNTIF(A$1:A32,Cotizador!F$2)=maxifs(Familias!E:E,Familias!D:D,Cotizador!F$2),IF(COUNTIF(A$1:A32,XLOOKUP(Cotizador!F$2,Implementos!B:B,Implementos!C:C,"",0,1))=SUMIFS(Implementos!D:D,Implementos!B:B,Cotizador!F$2,Implementos!C:C,XLOOKUP(Cotizador!F$2,Implementos!B:B,Implementos!C:C,"",0,1)),"",XLOOKUP(Cotizador!F$2,Implementos!B:B,Implementos!C:C,"",0,1)),Cotizador!F$2)} | B33: =IF(A33="","",COUNTIF(A$1:A33,A33)) | C33: {=IF(B33="","",IF(A33=XLOOKUP(A$2,Implementos!B:B,Implementos!C:C,"",0,1),B33+maxifs(B$1:B32,A$1:A32,A$2),B33))} | D33: =IF(B33="","", COUNTIFS(Productos!F:F,A33,Productos!H:H,B33)+IF(F33="SI",0,1)) | E33: =IFERROR(__xludf.DUMMYFUNCTION("IF($B33="""","""",INDEX(filter(Familias!F:F,Familias!$D:$D=$A33,Familias!$E:$E=$B33),1))"),"") | F33: =IFERROR(__xludf.DUMMYFUNCTION("IF($B33="""","""",INDEX(filter(Familias!G:G,Familias!$D:$D=$A33,Familias!$E:$E=$B33),1))"),"") | G33: {=IF(C33=1,XLOOKUP(C33,Cotizador!D:D,Cotizador!E:E,"",0,1),"")} | J33: =IF(I33="","",SUMIF(Cotizador!I$1:V$1,I33,Cotizador!I$2:V$2)) | L33: {=IF(COUNTIF(L$1:L32,A$2)=SUMIF(A:A,A$2,D:D),IF(COUNTIF(L$1:L32,XLOOKUP(A$2,Implementos!B:B,Implementos!C:C,"",0,1))=SUMIF(A:A,XLOOKUP(A$2,Implementos!B:B,Implementos!C:C,"",0,1),D:D),"",XLOOKUP(A$2,Implementos!B:B,Implementos!C:C,"",0,1)),A$2)} -> Acoplados Rurales | M33: =IF(L33="","",max(M$1:M32)+1) -> 32 | N33: =IF(L33="","",IF(N32="Orden",1,IF(COUNTIFS(N$1:N32,N32,L$1:L32,L33)=SUMIFS(D:D,B:B,N32,A:A,L33),IF(N32=maxifs(B:B,A:A,L33),"",maxifs(N$1:N32,L$1:L32,L33)+1),N32))) -> 2 | O33: =IF(N33="","",SUMIFS(C:C,B:B,N33,A:A,L33)) -> 2 | P33: =IF(N33="","",COUNTIFS(N$1:N33,N33,L$1:L33,L33)) -> 4 | Q33: =IF(U33="","",SUMIF(Productos!E:E,U33,Productos!A:A)) -> 60 | R33: {=IF(L33="","", max(1,SUMIF(I:I,XLOOKUP(U33,Productos!E:E,Productos!G:G,"",0,1),J:J)))} -> 1 | S33: =IF(Q33="","",IF(SUMIFS(Compat_Vetado!D:D,Compat_Vetado!B:B,SUM(G:G),Compat_Vetado!C:C,Q33)=1,"SI",IF(OR(SUMIF(Cotizador!E:E,Q33,Cotizador!G:G)>0,SUMIFS(Compat_Vetado!D:D,Compat_Vetado!B:B,SUM(G:G),Compat_Vetado!C:C,Q33)=-1),"NO",""))) | T33: =IF(Q33="","",IF(S33="SI","x",IF(S33="NO","",IF(AND(OR(V33="",AND(W33<=SUMIF(I:I,V33,J:J),SUMIF(I:I,V33,J:J)<=X33)),OR(Y33="",AND(Z33<=SUMIF(I:I,Y33,J:J),SUMIF(I:I,Y33,J:J)<=AA33)),OR(AB33="",AND(AC33<=SUMIF(I:I,AB33,J:J),SUMIF(I:I,AB33,J:J)<=AD33))),"x","")))) -> x | U33: =IFERROR(__xludf.DUMMYFUNCTION("IF(P33="""","""",IFERROR(INDEX(filter(Productos!E:E,Productos!F:F=L33,Productos!H:H=N33),P33),IF(M33=SUM(D:D),""Finalizar"",""-"")))"),"Baulera Standard - 750 - C/Laterales") -> Baulera Standard - 750 - C/Laterales | V33: =IFERROR(__xludf.DUMMYFUNCTION("IF(OR($U33="""",COUNTIF($I:$I,IFERROR(unique(filter(Prod_Prop!$H:$H,Prod_Prop!$G:$G=$U33,Prod_Prop!$E:$E=V$1)),""Check""))=0),"""",IFERROR(unique(filter(Prod_Prop!$H:$H,Prod_Prop!$G:$G=$U33,Prod_Prop!$E:$E=V$1)),""""))"),"") | W33: =IF(V33="","",SUMIFS(Prod_Prop!$J:$J,Prod_Prop!$B:$B,$Q33,Prod_Prop!$H:$H,V33,Prod_Prop!$I:$I,W$1)*IF(V33="Peso",$R33,1)) | X33: =IF(V33="","",SUMIFS(Prod_Prop!$J:$J,Prod_Prop!$B:$B,$Q33,Prod_Prop!$H:$H,V33,Prod_Prop!$I:$I,X$1)*IF(V33="Peso",$R33,1)) | Y33: =IFERROR(__xludf.DUMMYFUNCTION("IF(OR($U33="""",COUNTIF($I:$I,IFERROR(unique(filter(Prod_Prop!$H:$H,Prod_Prop!$G:$G=$U33,Prod_Prop!$E:$E=Y$1)),""Check""))=0),"""",IFERROR(unique(filter(Prod_Prop!$H:$H,Prod_Prop!$G:$G=$U33,Prod_Prop!$E:$E=Y$1)),""""))"),"") | Z33: =IF(Y33="","",SUMIFS(Prod_Prop!$J:$J,Prod_Prop!$B:$B,$Q33,Prod_Prop!$H:$H,Y33,Prod_Prop!$I:$I,Z$1)*IF(Y33="Peso",$R33,1)) | AA33: =IF(Y33="","",SUMIFS(Prod_Prop!$J:$J,Prod_Prop!$B:$B,$Q33,Prod_Prop!$H:$H,Y33,Prod_Prop!$I:$I,AA$1)*IF(Y33="Peso",$R33,1)) | AB33: =IFERROR(__xludf.DUMMYFUNCTION("IF(OR($U33="""",COUNTIF($I:$I,IFERROR(unique(filter(Prod_Prop!$H:$H,Prod_Prop!$G:$G=$U33,Prod_Prop!$E:$E=AB$1)),""Check""))=0),"""",IFERROR(unique(filter(Prod_Prop!$H:$H,Prod_Prop!$G:$G=$U33,Prod_Prop!$E:$E=AB$1)),""""))"),"") | AC33: =IF(AB33="","",SUMIFS(Prod_Prop!$J:$J,Prod_Prop!$B:$B,$Q33,Prod_Prop!$H:$H,AB33,Prod_Prop!$I:$I,AC$1)*IF(AB33="Peso",$R33,1)) | AD33: =IF(AB33="","",SUMIFS(Prod_Prop!$J:$J,Prod_Prop!$B:$B,$Q33,Prod_Prop!$H:$H,AB33,Prod_Prop!$I:$I,AD$1)*IF(AB33="Peso",$R33,1))
A34: {=IF(COUNTIF(A$1:A33,Cotizador!F$2)=maxifs(Familias!E:E,Familias!D:D,Cotizador!F$2),IF(COUNTIF(A$1:A33,XLOOKUP(Cotizador!F$2,Implementos!B:B,Implementos!C:C,"",0,1))=SUMIFS(Implementos!D:D,Implementos!B:B,Cotizador!F$2,Implementos!C:C,XLOOKUP(Cotizador!F$2,Implementos!B:B,Implementos!C:C,"",0,1)),"",XLOOKUP(Cotizador!F$2,Implementos!B:B,Implementos!C:C,"",0,1)),Cotizador!F$2)} | B34: =IF(A34="","",COUNTIF(A$1:A34,A34)) | C34: {=IF(B34="","",IF(A34=XLOOKUP(A$2,Implementos!B:B,Implementos!C:C,"",0,1),B34+maxifs(B$1:B33,A$1:A33,A$2),B34))} | D34: =IF(B34="","", COUNTIFS(Productos!F:F,A34,Productos!H:H,B34)+IF(F34="SI",0,1)) | E34: =IFERROR(__xludf.DUMMYFUNCTION("IF($B34="""","""",INDEX(filter(Familias!F:F,Familias!$D:$D=$A34,Familias!$E:$E=$B34),1))"),"") | F34: =IFERROR(__xludf.DUMMYFUNCTION("IF($B34="""","""",INDEX(filter(Familias!G:G,Familias!$D:$D=$A34,Familias!$E:$E=$B34),1))"),"") | G34: {=IF(C34=1,XLOOKUP(C34,Cotizador!D:D,Cotizador!E:E,"",0,1),"")} | J34: =IF(I34="","",SUMIF(Cotizador!I$1:V$1,I34,Cotizador!I$2:V$2)) | L34: {=IF(COUNTIF(L$1:L33,A$2)=SUMIF(A:A,A$2,D:D),IF(COUNTIF(L$1:L33,XLOOKUP(A$2,Implementos!B:B,Implementos!C:C,"",0,1))=SUMIF(A:A,XLOOKUP(A$2,Implementos!B:B,Implementos!C:C,"",0,1),D:D),"",XLOOKUP(A$2,Implementos!B:B,Implementos!C:C,"",0,1)),A$2)} -> Acoplados Rurales | M34: =IF(L34="","",max(M$1:M33)+1) -> 33 | N34: =IF(L34="","",IF(N33="Orden",1,IF(COUNTIFS(N$1:N33,N33,L$1:L33,L34)=SUMIFS(D:D,B:B,N33,A:A,L34),IF(N33=maxifs(B:B,A:A,L34),"",maxifs(N$1:N33,L$1:L33,L34)+1),N33))) -> 2 | O34: =IF(N34="","",SUMIFS(C:C,B:B,N34,A:A,L34)) -> 2 | P34: =IF(N34="","",COUNTIFS(N$1:N34,N34,L$1:L34,L34)) -> 5 | Q34: =IF(U34="","",SUMIF(Productos!E:E,U34,Productos!A:A)) -> 61 | R34: {=IF(L34="","", max(1,SUMIF(I:I,XLOOKUP(U34,Productos!E:E,Productos!G:G,"",0,1),J:J)))} -> 1 | S34: =IF(Q34="","",IF(SUMIFS(Compat_Vetado!D:D,Compat_Vetado!B:B,SUM(G:G),Compat_Vetado!C:C,Q34)=1,"SI",IF(OR(SUMIF(Cotizador!E:E,Q34,Cotizador!G:G)>0,SUMIFS(Compat_Vetado!D:D,Compat_Vetado!B:B,SUM(G:G),Compat_Vetado!C:C,Q34)=-1),"NO",""))) | T34: =IF(Q34="","",IF(S34="SI","x",IF(S34="NO","",IF(AND(OR(V34="",AND(W34<=SUMIF(I:I,V34,J:J),SUMIF(I:I,V34,J:J)<=X34)),OR(Y34="",AND(Z34<=SUMIF(I:I,Y34,J:J),SUMIF(I:I,Y34,J:J)<=AA34)),OR(AB34="",AND(AC34<=SUMIF(I:I,AB34,J:J),SUMIF(I:I,AB34,J:J)<=AD34))),"x","")))) -> x | U34: =IFERROR(__xludf.DUMMYFUNCTION("IF(P34="""","""",IFERROR(INDEX(filter(Productos!E:E,Productos!F:F=L34,Productos!H:H=N34),P34),IF(M34=SUM(D:D),""Finalizar"",""-"")))"),"Baulera Standard - 1300 - C/Laterales") -> Baulera Standard - 1300 - C/Laterales | V34: =IFERROR(__xludf.DUMMYFUNCTION("IF(OR($U34="""",COUNTIF($I:$I,IFERROR(unique(filter(Prod_Prop!$H:$H,Prod_Prop!$G:$G=$U34,Prod_Prop!$E:$E=V$1)),""Check""))=0),"""",IFERROR(unique(filter(Prod_Prop!$H:$H,Prod_Prop!$G:$G=$U34,Prod_Prop!$E:$E=V$1)),""""))"),"") | W34: =IF(V34="","",SUMIFS(Prod_Prop!$J:$J,Prod_Prop!$B:$B,$Q34,Prod_Prop!$H:$H,V34,Prod_Prop!$I:$I,W$1)*IF(V34="Peso",$R34,1)) | X34: =IF(V34="","",SUMIFS(Prod_Prop!$J:$J,Prod_Prop!$B:$B,$Q34,Prod_Prop!$H:$H,V34,Prod_Prop!$I:$I,X$1)*IF(V34="Peso",$R34,1)) | Y34: =IFERROR(__xludf.DUMMYFUNCTION("IF(OR($U34="""",COUNTIF($I:$I,IFERROR(unique(filter(Prod_Prop!$H:$H,Prod_Prop!$G:$G=$U34,Prod_Prop!$E:$E=Y$1)),""Check""))=0),"""",IFERROR(unique(filter(Prod_Prop!$H:$H,Prod_Prop!$G:$G=$U34,Prod_Prop!$E:$E=Y$1)),""""))"),"") | Z34: =IF(Y34="","",SUMIFS(Prod_Prop!$J:$J,Prod_Prop!$B:$B,$Q34,Prod_Prop!$H:$H,Y34,Prod_Prop!$I:$I,Z$1)*IF(Y34="Peso",$R34,1)) | AA34: =IF(Y34="","",SUMIFS(Prod_Prop!$J:$J,Prod_Prop!$B:$B,$Q34,Prod_Prop!$H:$H,Y34,Prod_Prop!$I:$I,AA$1)*IF(Y34="Peso",$R34,1)) | AB34: =IFERROR(__xludf.DUMMYFUNCTION("IF(OR($U34="""",COUNTIF($I:$I,IFERROR(unique(filter(Prod_Prop!$H:$H,Prod_Prop!$G:$G=$U34,Prod_Prop!$E:$E=AB$1)),""Check""))=0),"""",IFERROR(unique(filter(Prod_Prop!$H:$H,Prod_Prop!$G:$G=$U34,Prod_Prop!$E:$E=AB$1)),""""))"),"") | AC34: =IF(AB34="","",SUMIFS(Prod_Prop!$J:$J,Prod_Prop!$B:$B,$Q34,Prod_Prop!$H:$H,AB34,Prod_Prop!$I:$I,AC$1)*IF(AB34="Peso",$R34,1)) | AD34: =IF(AB34="","",SUMIFS(Prod_Prop!$J:$J,Prod_Prop!$B:$B,$Q34,Prod_Prop!$H:$H,AB34,Prod_Prop!$I:$I,AD$1)*IF(AB34="Peso",$R34,1))
A35: {=IF(COUNTIF(A$1:A34,Cotizador!F$2)=maxifs(Familias!E:E,Familias!D:D,Cotizador!F$2),IF(COUNTIF(A$1:A34,XLOOKUP(Cotizador!F$2,Implementos!B:B,Implementos!C:C,"",0,1))=SUMIFS(Implementos!D:D,Implementos!B:B,Cotizador!F$2,Implementos!C:C,XLOOKUP(Cotizador!F$2,Implementos!B:B,Implementos!C:C,"",0,1)),"",XLOOKUP(Cotizador!F$2,Implementos!B:B,Implementos!C:C,"",0,1)),Cotizador!F$2)} | B35: =IF(A35="","",COUNTIF(A$1:A35,A35)) | C35: {=IF(B35="","",IF(A35=XLOOKUP(A$2,Implementos!B:B,Implementos!C:C,"",0,1),B35+maxifs(B$1:B34,A$1:A34,A$2),B35))} | D35: =IF(B35="","", COUNTIFS(Productos!F:F,A35,Productos!H:H,B35)+IF(F35="SI",0,1)) | E35: =IFERROR(__xludf.DUMMYFUNCTION("IF($B35="""","""",INDEX(filter(Familias!F:F,Familias!$D:$D=$A35,Familias!$E:$E=$B35),1))"),"") | F35: =IFERROR(__xludf.DUMMYFUNCTION("IF($B35="""","""",INDEX(filter(Familias!G:G,Familias!$D:$D=$A35,Familias!$E:$E=$B35),1))"),"") | G35: {=IF(C35=1,XLOOKUP(C35,Cotizador!D:D,Cotizador!E:E,"",0,1),"")} | J35: =IF(I35="","",SUMIF(Cotizador!I$1:V$1,I35,Cotizador!I$2:V$2)) | L35: {=IF(COUNTIF(L$1:L34,A$2)=SUMIF(A:A,A$2,D:D),IF(COUNTIF(L$1:L34,XLOOKUP(A$2,Implementos!B:B,Implementos!C:C,"",0,1))=SUMIF(A:A,XLOOKUP(A$2,Implementos!B:B,Implementos!C:C,"",0,1),D:D),"",XLOOKUP(A$2,Implementos!B:B,Implementos!C:C,"",0,1)),A$2)} -> Acoplados Rurales | M35: =IF(L35="","",max(M$1:M34)+1) -> 34 | N35: =IF(L35="","",IF(N34="Orden",1,IF(COUNTIFS(N$1:N34,N34,L$1:L34,L35)=SUMIFS(D:D,B:B,N34,A:A,L35),IF(N34=maxifs(B:B,A:A,L35),"",maxifs(N$1:N34,L$1:L34,L35)+1),N34))) -> 2 | O35: =IF(N35="","",SUMIFS(C:C,B:B,N35,A:A,L35)) -> 2 | P35: =IF(N35="","",COUNTIFS(N$1:N35,N35,L$1:L35,L35)) -> 6 | Q35: =IF(U35="","",SUMIF(Productos!E:E,U35,Productos!A:A)) -> 62 | R35: {=IF(L35="","", max(1,SUMIF(I:I,XLOOKUP(U35,Productos!E:E,Productos!G:G,"",0,1),J:J)))} -> 1 | S35: =IF(Q35="","",IF(SUMIFS(Compat_Vetado!D:D,Compat_Vetado!B:B,SUM(G:G),Compat_Vetado!C:C,Q35)=1,"SI",IF(OR(SUMIF(Cotizador!E:E,Q35,Cotizador!G:G)>0,SUMIFS(Compat_Vetado!D:D,Compat_Vetado!B:B,SUM(G:G),Compat_Vetado!C:C,Q35)=-1),"NO",""))) | T35: =IF(Q35="","",IF(S35="SI","x",IF(S35="NO","",IF(AND(OR(V35="",AND(W35<=SUMIF(I:I,V35,J:J),SUMIF(I:I,V35,J:J)<=X35)),OR(Y35="",AND(Z35<=SUMIF(I:I,Y35,J:J),SUMIF(I:I,Y35,J:J)<=AA35)),OR(AB35="",AND(AC35<=SUMIF(I:I,AB35,J:J),SUMIF(I:I,AB35,J:J)<=AD35))),"x","")))) -> x | U35: =IFERROR(__xludf.DUMMYFUNCTION("IF(P35="""","""",IFERROR(INDEX(filter(Productos!E:E,Productos!F:F=L35,Productos!H:H=N35),P35),IF(M35=SUM(D:D),""Finalizar"",""-"")))"),"Baulera Alta - 750") -> Baulera Alta - 750 | V35: =IFERROR(__xludf.DUMMYFUNCTION("IF(OR($U35="""",COUNTIF($I:$I,IFERROR(unique(filter(Prod_Prop!$H:$H,Prod_Prop!$G:$G=$U35,Prod_Prop!$E:$E=V$1)),""Check""))=0),"""",IFERROR(unique(filter(Prod_Prop!$H:$H,Prod_Prop!$G:$G=$U35,Prod_Prop!$E:$E=V$1)),""""))"),"") | W35: =IF(V35="","",SUMIFS(Prod_Prop!$J:$J,Prod_Prop!$B:$B,$Q35,Prod_Prop!$H:$H,V35,Prod_Prop!$I:$I,W$1)*IF(V35="Peso",$R35,1)) | X35: =IF(V35="","",SUMIFS(Prod_Prop!$J:$J,Prod_Prop!$B:$B,$Q35,Prod_Prop!$H:$H,V35,Prod_Prop!$I:$I,X$1)*IF(V35="Peso",$R35,1)) | Y35: =IFERROR(__xludf.DUMMYFUNCTION("IF(OR($U35="""",COUNTIF($I:$I,IFERROR(unique(filter(Prod_Prop!$H:$H,Prod_Prop!$G:$G=$U35,Prod_Prop!$E:$E=Y$1)),""Check""))=0),"""",IFERROR(unique(filter(Prod_Prop!$H:$H,Prod_Prop!$G:$G=$U35,Prod_Prop!$E:$E=Y$1)),""""))"),"") | Z35: =IF(Y35="","",SUMIFS(Prod_Prop!$J:$J,Prod_Prop!$B:$B,$Q35,Prod_Prop!$H:$H,Y35,Prod_Prop!$I:$I,Z$1)*IF(Y35="Peso",$R35,1)) | AA35: =IF(Y35="","",SUMIFS(Prod_Prop!$J:$J,Prod_Prop!$B:$B,$Q35,Prod_Prop!$H:$H,Y35,Prod_Prop!$I:$I,AA$1)*IF(Y35="Peso",$R35,1)) | AB35: =IFERROR(__xludf.DUMMYFUNCTION("IF(OR($U35="""",COUNTIF($I:$I,IFERROR(unique(filter(Prod_Prop!$H:$H,Prod_Prop!$G:$G=$U35,Prod_Prop!$E:$E=AB$1)),""Check""))=0),"""",IFERROR(unique(filter(Prod_Prop!$H:$H,Prod_Prop!$G:$G=$U35,Prod_Prop!$E:$E=AB$1)),""""))"),"") | AC35: =IF(AB35="","",SUMIFS(Prod_Prop!$J:$J,Prod_Prop!$B:$B,$Q35,Prod_Prop!$H:$H,AB35,Prod_Prop!$I:$I,AC$1)*IF(AB35="Peso",$R35,1)) | AD35: =IF(AB35="","",SUMIFS(Prod_Prop!$J:$J,Prod_Prop!$B:$B,$Q35,Prod_Prop!$H:$H,AB35,Prod_Prop!$I:$I,AD$1)*IF(AB35="Peso",$R35,1))
A36: {=IF(COUNTIF(A$1:A35,Cotizador!F$2)=maxifs(Familias!E:E,Familias!D:D,Cotizador!F$2),IF(COUNTIF(A$1:A35,XLOOKUP(Cotizador!F$2,Implementos!B:B,Implementos!C:C,"",0,1))=SUMIFS(Implementos!D:D,Implementos!B:B,Cotizador!F$2,Implementos!C:C,XLOOKUP(Cotizador!F$2,Implementos!B:B,Implementos!C:C,"",0,1)),"",XLOOKUP(Cotizador!F$2,Implementos!B:B,Implementos!C:C,"",0,1)),Cotizador!F$2)} | B36: =IF(A36="","",COUNTIF(A$1:A36,A36)) | C36: {=IF(B36="","",IF(A36=XLOOKUP(A$2,Implementos!B:B,Implementos!C:C,"",0,1),B36+maxifs(B$1:B35,A$1:A35,A$2),B36))} | D36: =IF(B36="","", COUNTIFS(Productos!F:F,A36,Productos!H:H,B36)+IF(F36="SI",0,1)) | E36: =IFERROR(__xludf.DUMMYFUNCTION("IF($B36="""","""",INDEX(filter(Familias!F:F,Familias!$D:$D=$A36,Familias!$E:$E=$B36),1))"),"") | F36: =IFERROR(__xludf.DUMMYFUNCTION("IF($B36="""","""",INDEX(filter(Familias!G:G,Familias!$D:$D=$A36,Familias!$E:$E=$B36),1))"),"") | G36: {=IF(C36=1,XLOOKUP(C36,Cotizador!D:D,Cotizador!E:E,"",0,1),"")} | J36: =IF(I36="","",SUMIF(Cotizador!I$1:V$1,I36,Cotizador!I$2:V$2)) | L36: {=IF(COUNTIF(L$1:L35,A$2)=SUMIF(A:A,A$2,D:D),IF(COUNTIF(L$1:L35,XLOOKUP(A$2,Implementos!B:B,Implementos!C:C,"",0,1))=SUMIF(A:A,XLOOKUP(A$2,Implementos!B:B,Implementos!C:C,"",0,1),D:D),"",XLOOKUP(A$2,Implementos!B:B,Implementos!C:C,"",0,1)),A$2)} -> Acoplados Rurales | M36: =IF(L36="","",max(M$1:M35)+1) -> 35 | N36: =IF(L36="","",IF(N35="Orden",1,IF(COUNTIFS(N$1:N35,N35,L$1:L35,L36)=SUMIFS(D:D,B:B,N35,A:A,L36),IF(N35=maxifs(B:B,A:A,L36),"",maxifs(N$1:N35,L$1:L35,L36)+1),N35))) -> 2 | O36: =IF(N36="","",SUMIFS(C:C,B:B,N36,A:A,L36)) -> 2 | P36: =IF(N36="","",COUNTIFS(N$1:N36,N36,L$1:L36,L36)) -> 7 | Q36: =IF(U36="","",SUMIF(Productos!E:E,U36,Productos!A:A)) -> 63 | R36: {=IF(L36="","", max(1,SUMIF(I:I,XLOOKUP(U36,Productos!E:E,Productos!G:G,"",0,1),J:J)))} -> 1 | S36: =IF(Q36="","",IF(SUMIFS(Compat_Vetado!D:D,Compat_Vetado!B:B,SUM(G:G),Compat_Vetado!C:C,Q36)=1,"SI",IF(OR(SUMIF(Cotizador!E:E,Q36,Cotizador!G:G)>0,SUMIFS(Compat_Vetado!D:D,Compat_Vetado!B:B,SUM(G:G),Compat_Vetado!C:C,Q36)=-1),"NO",""))) | T36: =IF(Q36="","",IF(S36="SI","x",IF(S36="NO","",IF(AND(OR(V36="",AND(W36<=SUMIF(I:I,V36,J:J),SUMIF(I:I,V36,J:J)<=X36)),OR(Y36="",AND(Z36<=SUMIF(I:I,Y36,J:J),SUMIF(I:I,Y36,J:J)<=AA36)),OR(AB36="",AND(AC36<=SUMIF(I:I,AB36,J:J),SUMIF(I:I,AB36,J:J)<=AD36))),"x","")))) -> x | U36: =IFERROR(__xludf.DUMMYFUNCTION("IF(P36="""","""",IFERROR(INDEX(filter(Productos!E:E,Productos!F:F=L36,Productos!H:H=N36),P36),IF(M36=SUM(D:D),""Finalizar"",""-"")))"),"Baulera Alta - 1500 - C/Laterales") -> Baulera Alta - 1500 - C/Laterales | V36: =IFERROR(__xludf.DUMMYFUNCTION("IF(OR($U36="""",COUNTIF($I:$I,IFERROR(unique(filter(Prod_Prop!$H:$H,Prod_Prop!$G:$G=$U36,Prod_Prop!$E:$E=V$1)),""Check""))=0),"""",IFERROR(unique(filter(Prod_Prop!$H:$H,Prod_Prop!$G:$G=$U36,Prod_Prop!$E:$E=V$1)),""""))"),"") | W36: =IF(V36="","",SUMIFS(Prod_Prop!$J:$J,Prod_Prop!$B:$B,$Q36,Prod_Prop!$H:$H,V36,Prod_Prop!$I:$I,W$1)*IF(V36="Peso",$R36,1)) | X36: =IF(V36="","",SUMIFS(Prod_Prop!$J:$J,Prod_Prop!$B:$B,$Q36,Prod_Prop!$H:$H,V36,Prod_Prop!$I:$I,X$1)*IF(V36="Peso",$R36,1)) | Y36: =IFERROR(__xludf.DUMMYFUNCTION("IF(OR($U36="""",COUNTIF($I:$I,IFERROR(unique(filter(Prod_Prop!$H:$H,Prod_Prop!$G:$G=$U36,Prod_Prop!$E:$E=Y$1)),""Check""))=0),"""",IFERROR(unique(filter(Prod_Prop!$H:$H,Prod_Prop!$G:$G=$U36,Prod_Prop!$E:$E=Y$1)),""""))"),"") | Z36: =IF(Y36="","",SUMIFS(Prod_Prop!$J:$J,Prod_Prop!$B:$B,$Q36,Prod_Prop!$H:$H,Y36,Prod_Prop!$I:$I,Z$1)*IF(Y36="Peso",$R36,1)) | AA36: =IF(Y36="","",SUMIFS(Prod_Prop!$J:$J,Prod_Prop!$B:$B,$Q36,Prod_Prop!$H:$H,Y36,Prod_Prop!$I:$I,AA$1)*IF(Y36="Peso",$R36,1)) | AB36: =IFERROR(__xludf.DUMMYFUNCTION("IF(OR($U36="""",COUNTIF($I:$I,IFERROR(unique(filter(Prod_Prop!$H:$H,Prod_Prop!$G:$G=$U36,Prod_Prop!$E:$E=AB$1)),""Check""))=0),"""",IFERROR(unique(filter(Prod_Prop!$H:$H,Prod_Prop!$G:$G=$U36,Prod_Prop!$E:$E=AB$1)),""""))"),"") | AC36: =IF(AB36="","",SUMIFS(Prod_Prop!$J:$J,Prod_Prop!$B:$B,$Q36,Prod_Prop!$H:$H,AB36,Prod_Prop!$I:$I,AC$1)*IF(AB36="Peso",$R36,1)) | AD36: =IF(AB36="","",SUMIFS(Prod_Prop!$J:$J,Prod_Prop!$B:$B,$Q36,Prod_Prop!$H:$H,AB36,Prod_Prop!$I:$I,AD$1)*IF(AB36="Peso",$R36,1))
A37: {=IF(COUNTIF(A$1:A36,Cotizador!F$2)=maxifs(Familias!E:E,Familias!D:D,Cotizador!F$2),IF(COUNTIF(A$1:A36,XLOOKUP(Cotizador!F$2,Implementos!B:B,Implementos!C:C,"",0,1))=SUMIFS(Implementos!D:D,Implementos!B:B,Cotizador!F$2,Implementos!C:C,XLOOKUP(Cotizador!F$2,Implementos!B:B,Implementos!C:C,"",0,1)),"",XLOOKUP(Cotizador!F$2,Implementos!B:B,Implementos!C:C,"",0,1)),Cotizador!F$2)} | B37: =IF(A37="","",COUNTIF(A$1:A37,A37)) | C37: {=IF(B37="","",IF(A37=XLOOKUP(A$2,Implementos!B:B,Implementos!C:C,"",0,1),B37+maxifs(B$1:B36,A$1:A36,A$2),B37))} | D37: =IF(B37="","", COUNTIFS(Productos!F:F,A37,Productos!H:H,B37)+IF(F37="SI",0,1)) | E37: =IFERROR(__xludf.DUMMYFUNCTION("IF($B37="""","""",INDEX(filter(Familias!F:F,Familias!$D:$D=$A37,Familias!$E:$E=$B37),1))"),"") | F37: =IFERROR(__xludf.DUMMYFUNCTION("IF($B37="""","""",INDEX(filter(Familias!G:G,Familias!$D:$D=$A37,Familias!$E:$E=$B37),1))"),"") | G37: {=IF(C37=1,XLOOKUP(C37,Cotizador!D:D,Cotizador!E:E,"",0,1),"")} | J37: =IF(I37="","",SUMIF(Cotizador!I$1:V$1,I37,Cotizador!I$2:V$2)) | L37: {=IF(COUNTIF(L$1:L36,A$2)=SUMIF(A:A,A$2,D:D),IF(COUNTIF(L$1:L36,XLOOKUP(A$2,Implementos!B:B,Implementos!C:C,"",0,1))=SUMIF(A:A,XLOOKUP(A$2,Implementos!B:B,Implementos!C:C,"",0,1),D:D),"",XLOOKUP(A$2,Implementos!B:B,Implementos!C:C,"",0,1)),A$2)} -> Acoplados Rurales | M37: =IF(L37="","",max(M$1:M36)+1) -> 36 | N37: =IF(L37="","",IF(N36="Orden",1,IF(COUNTIFS(N$1:N36,N36,L$1:L36,L37)=SUMIFS(D:D,B:B,N36,A:A,L37),IF(N36=maxifs(B:B,A:A,L37),"",maxifs(N$1:N36,L$1:L36,L37)+1),N36))) -> 2 | O37: =IF(N37="","",SUMIFS(C:C,B:B,N37,A:A,L37)) -> 2 | P37: =IF(N37="","",COUNTIFS(N$1:N37,N37,L$1:L37,L37)) -> 8 | Q37: =IF(U37="","",SUMIF(Productos!E:E,U37,Productos!A:A)) -> 64 | R37: {=IF(L37="","", max(1,SUMIF(I:I,XLOOKUP(U37,Productos!E:E,Productos!G:G,"",0,1),J:J)))} -> 1 | S37: =IF(Q37="","",IF(SUMIFS(Compat_Vetado!D:D,Compat_Vetado!B:B,SUM(G:G),Compat_Vetado!C:C,Q37)=1,"SI",IF(OR(SUMIF(Cotizador!E:E,Q37,Cotizador!G:G)>0,SUMIFS(Compat_Vetado!D:D,Compat_Vetado!B:B,SUM(G:G),Compat_Vetado!C:C,Q37)=-1),"NO",""))) | T37: =IF(Q37="","",IF(S37="SI","x",IF(S37="NO","",IF(AND(OR(V37="",AND(W37<=SUMIF(I:I,V37,J:J),SUMIF(I:I,V37,J:J)<=X37)),OR(Y37="",AND(Z37<=SUMIF(I:I,Y37,J:J),SUMIF(I:I,Y37,J:J)<=AA37)),OR(AB37="",AND(AC37<=SUMIF(I:I,AB37,J:J),SUMIF(I:I,AB37,J:J)<=AD37))),"x","")))) -> x | U37: =IFERROR(__xludf.DUMMYFUNCTION("IF(P37="""","""",IFERROR(INDEX(filter(Productos!E:E,Productos!F:F=L37,Productos!H:H=N37),P37),IF(M37=SUM(D:D),""Finalizar"",""-"")))"),"Baulera Extendida 1700 - C/Laterales") -> Baulera Extendida 1700 - C/Laterales | V37: =IFERROR(__xludf.DUMMYFUNCTION("IF(OR($U37="""",COUNTIF($I:$I,IFERROR(unique(filter(Prod_Prop!$H:$H,Prod_Prop!$G:$G=$U37,Prod_Prop!$E:$E=V$1)),""Check""))=0),"""",IFERROR(unique(filter(Prod_Prop!$H:$H,Prod_Prop!$G:$G=$U37,Prod_Prop!$E:$E=V$1)),""""))"),"") | W37: =IF(V37="","",SUMIFS(Prod_Prop!$J:$J,Prod_Prop!$B:$B,$Q37,Prod_Prop!$H:$H,V37,Prod_Prop!$I:$I,W$1)*IF(V37="Peso",$R37,1)) | X37: =IF(V37="","",SUMIFS(Prod_Prop!$J:$J,Prod_Prop!$B:$B,$Q37,Prod_Prop!$H:$H,V37,Prod_Prop!$I:$I,X$1)*IF(V37="Peso",$R37,1)) | Y37: =IFERROR(__xludf.DUMMYFUNCTION("IF(OR($U37="""",COUNTIF($I:$I,IFERROR(unique(filter(Prod_Prop!$H:$H,Prod_Prop!$G:$G=$U37,Prod_Prop!$E:$E=Y$1)),""Check""))=0),"""",IFERROR(unique(filter(Prod_Prop!$H:$H,Prod_Prop!$G:$G=$U37,Prod_Prop!$E:$E=Y$1)),""""))"),"") | Z37: =IF(Y37="","",SUMIFS(Prod_Prop!$J:$J,Prod_Prop!$B:$B,$Q37,Prod_Prop!$H:$H,Y37,Prod_Prop!$I:$I,Z$1)*IF(Y37="Peso",$R37,1)) | AA37: =IF(Y37="","",SUMIFS(Prod_Prop!$J:$J,Prod_Prop!$B:$B,$Q37,Prod_Prop!$H:$H,Y37,Prod_Prop!$I:$I,AA$1)*IF(Y37="Peso",$R37,1)) | AB37: =IFERROR(__xludf.DUMMYFUNCTION("IF(OR($U37="""",COUNTIF($I:$I,IFERROR(unique(filter(Prod_Prop!$H:$H,Prod_Prop!$G:$G=$U37,Prod_Prop!$E:$E=AB$1)),""Check""))=0),"""",IFERROR(unique(filter(Prod_Prop!$H:$H,Prod_Prop!$G:$G=$U37,Prod_Prop!$E:$E=AB$1)),""""))"),"") | AC37: =IF(AB37="","",SUMIFS(Prod_Prop!$J:$J,Prod_Prop!$B:$B,$Q37,Prod_Prop!$H:$H,AB37,Prod_Prop!$I:$I,AC$1)*IF(AB37="Peso",$R37,1)) | AD37: =IF(AB37="","",SUMIFS(Prod_Prop!$J:$J,Prod_Prop!$B:$B,$Q37,Prod_Prop!$H:$H,AB37,Prod_Prop!$I:$I,AD$1)*IF(AB37="Peso",$R37,1))
A38: {=IF(COUNTIF(A$1:A37,Cotizador!F$2)=maxifs(Familias!E:E,Familias!D:D,Cotizador!F$2),IF(COUNTIF(A$1:A37,XLOOKUP(Cotizador!F$2,Implementos!B:B,Implementos!C:C,"",0,1))=SUMIFS(Implementos!D:D,Implementos!B:B,Cotizador!F$2,Implementos!C:C,XLOOKUP(Cotizador!F$2,Implementos!B:B,Implementos!C:C,"",0,1)),"",XLOOKUP(Cotizador!F$2,Implementos!B:B,Implementos!C:C,"",0,1)),Cotizador!F$2)} | B38: =IF(A38="","",COUNTIF(A$1:A38,A38)) | C38: {=IF(B38="","",IF(A38=XLOOKUP(A$2,Implementos!B:B,Implementos!C:C,"",0,1),B38+maxifs(B$1:B37,A$1:A37,A$2),B38))} | D38: =IF(B38="","", COUNTIFS(Productos!F:F,A38,Productos!H:H,B38)+IF(F38="SI",0,1)) | E38: =IFERROR(__xludf.DUMMYFUNCTION("IF($B38="""","""",INDEX(filter(Familias!F:F,Familias!$D:$D=$A38,Familias!$E:$E=$B38),1))"),"") | F38: =IFERROR(__xludf.DUMMYFUNCTION("IF($B38="""","""",INDEX(filter(Familias!G:G,Familias!$D:$D=$A38,Familias!$E:$E=$B38),1))"),"") | G38: {=IF(C38=1,XLOOKUP(C38,Cotizador!D:D,Cotizador!E:E,"",0,1),"")} | J38: =IF(I38="","",SUMIF(Cotizador!I$1:V$1,I38,Cotizador!I$2:V$2)) | L38: {=IF(COUNTIF(L$1:L37,A$2)=SUMIF(A:A,A$2,D:D),IF(COUNTIF(L$1:L37,XLOOKUP(A$2,Implementos!B:B,Implementos!C:C,"",0,1))=SUMIF(A:A,XLOOKUP(A$2,Implementos!B:B,Implementos!C:C,"",0,1),D:D),"",XLOOKUP(A$2,Implementos!B:B,Implementos!C:C,"",0,1)),A$2)} -> Acoplados Rurales | M38: =IF(L38="","",max(M$1:M37)+1) -> 37 | N38: =IF(L38="","",IF(N37="Orden",1,IF(COUNTIFS(N$1:N37,N37,L$1:L37,L38)=SUMIFS(D:D,B:B,N37,A:A,L38),IF(N37=maxifs(B:B,A:A,L38),"",maxifs(N$1:N37,L$1:L37,L38)+1),N37))) -> 2 | O38: =IF(N38="","",SUMIFS(C:C,B:B,N38,A:A,L38)) -> 2 | P38: =IF(N38="","",COUNTIFS(N$1:N38,N38,L$1:L38,L38)) -> 9 | Q38: =IF(U38="","",SUMIF(Productos!E:E,U38,Productos!A:A)) -> 65 | R38: {=IF(L38="","", max(1,SUMIF(I:I,XLOOKUP(U38,Productos!E:E,Productos!G:G,"",0,1),J:J)))} -> 1 | S38: =IF(Q38="","",IF(SUMIFS(Compat_Vetado!D:D,Compat_Vetado!B:B,SUM(G:G),Compat_Vetado!C:C,Q38)=1,"SI",IF(OR(SUMIF(Cotizador!E:E,Q38,Cotizador!G:G)>0,SUMIFS(Compat_Vetado!D:D,Compat_Vetado!B:B,SUM(G:G),Compat_Vetado!C:C,Q38)=-1),"NO",""))) | T38: =IF(Q38="","",IF(S38="SI","x",IF(S38="NO","",IF(AND(OR(V38="",AND(W38<=SUMIF(I:I,V38,J:J),SUMIF(I:I,V38,J:J)<=X38)),OR(Y38="",AND(Z38<=SUMIF(I:I,Y38,J:J),SUMIF(I:I,Y38,J:J)<=AA38)),OR(AB38="",AND(AC38<=SUMIF(I:I,AB38,J:J),SUMIF(I:I,AB38,J:J)<=AD38))),"x","")))) -> x | U38: =IFERROR(__xludf.DUMMYFUNCTION("IF(P38="""","""",IFERROR(INDEX(filter(Productos!E:E,Productos!F:F=L38,Productos!H:H=N38),P38),IF(M38=SUM(D:D),""Finalizar"",""-"")))"),"Taller Móvil - 1500 x 1500 x 1700") -> Taller Móvil - 1500 x 1500 x 1700 | V38: =IFERROR(__xludf.DUMMYFUNCTION("IF(OR($U38="""",COUNTIF($I:$I,IFERROR(unique(filter(Prod_Prop!$H:$H,Prod_Prop!$G:$G=$U38,Prod_Prop!$E:$E=V$1)),""Check""))=0),"""",IFERROR(unique(filter(Prod_Prop!$H:$H,Prod_Prop!$G:$G=$U38,Prod_Prop!$E:$E=V$1)),""""))"),"") | W38: =IF(V38="","",SUMIFS(Prod_Prop!$J:$J,Prod_Prop!$B:$B,$Q38,Prod_Prop!$H:$H,V38,Prod_Prop!$I:$I,W$1)*IF(V38="Peso",$R38,1)) | X38: =IF(V38="","",SUMIFS(Prod_Prop!$J:$J,Prod_Prop!$B:$B,$Q38,Prod_Prop!$H:$H,V38,Prod_Prop!$I:$I,X$1)*IF(V38="Peso",$R38,1)) | Y38: =IFERROR(__xludf.DUMMYFUNCTION("IF(OR($U38="""",COUNTIF($I:$I,IFERROR(unique(filter(Prod_Prop!$H:$H,Prod_Prop!$G:$G=$U38,Prod_Prop!$E:$E=Y$1)),""Check""))=0),"""",IFERROR(unique(filter(Prod_Prop!$H:$H,Prod_Prop!$G:$G=$U38,Prod_Prop!$E:$E=Y$1)),""""))"),"") | Z38: =IF(Y38="","",SUMIFS(Prod_Prop!$J:$J,Prod_Prop!$B:$B,$Q38,Prod_Prop!$H:$H,Y38,Prod_Prop!$I:$I,Z$1)*IF(Y38="Peso",$R38,1)) | AA38: =IF(Y38="","",SUMIFS(Prod_Prop!$J:$J,Prod_Prop!$B:$B,$Q38,Prod_Prop!$H:$H,Y38,Prod_Prop!$I:$I,AA$1)*IF(Y38="Peso",$R38,1)) | AB38: =IFERROR(__xludf.DUMMYFUNCTION("IF(OR($U38="""",COUNTIF($I:$I,IFERROR(unique(filter(Prod_Prop!$H:$H,Prod_Prop!$G:$G=$U38,Prod_Prop!$E:$E=AB$1)),""Check""))=0),"""",IFERROR(unique(filter(Prod_Prop!$H:$H,Prod_Prop!$G:$G=$U38,Prod_Prop!$E:$E=AB$1)),""""))"),"") | AC38: =IF(AB38="","",SUMIFS(Prod_Prop!$J:$J,Prod_Prop!$B:$B,$Q38,Prod_Prop!$H:$H,AB38,Prod_Prop!$I:$I,AC$1)*IF(AB38="Peso",$R38,1)) | AD38: =IF(AB38="","",SUMIFS(Prod_Prop!$J:$J,Prod_Prop!$B:$B,$Q38,Prod_Prop!$H:$H,AB38,Prod_Prop!$I:$I,AD$1)*IF(AB38="Peso",$R38,1))
A39: {=IF(COUNTIF(A$1:A38,Cotizador!F$2)=maxifs(Familias!E:E,Familias!D:D,Cotizador!F$2),IF(COUNTIF(A$1:A38,XLOOKUP(Cotizador!F$2,Implementos!B:B,Implementos!C:C,"",0,1))=SUMIFS(Implementos!D:D,Implementos!B:B,Cotizador!F$2,Implementos!C:C,XLOOKUP(Cotizador!F$2,Implementos!B:B,Implementos!C:C,"",0,1)),"",XLOOKUP(Cotizador!F$2,Implementos!B:B,Implementos!C:C,"",0,1)),Cotizador!F$2)} | B39: =IF(A39="","",COUNTIF(A$1:A39,A39)) | C39: {=IF(B39="","",IF(A39=XLOOKUP(A$2,Implementos!B:B,Implementos!C:C,"",0,1),B39+maxifs(B$1:B38,A$1:A38,A$2),B39))} | D39: =IF(B39="","", COUNTIFS(Productos!F:F,A39,Productos!H:H,B39)+IF(F39="SI",0,1)) | E39: =IFERROR(__xludf.DUMMYFUNCTION("IF($B39="""","""",INDEX(filter(Familias!F:F,Familias!$D:$D=$A39,Familias!$E:$E=$B39),1))"),"") | F39: =IFERROR(__xludf.DUMMYFUNCTION("IF($B39="""","""",INDEX(filter(Familias!G:G,Familias!$D:$D=$A39,Familias!$E:$E=$B39),1))"),"") | G39: {=IF(C39=1,XLOOKUP(C39,Cotizador!D:D,Cotizador!E:E,"",0,1),"")} | J39: =IF(I39="","",SUMIF(Cotizador!I$1:V$1,I39,Cotizador!I$2:V$2)) | L39: {=IF(COUNTIF(L$1:L38,A$2)=SUMIF(A:A,A$2,D:D),IF(COUNTIF(L$1:L38,XLOOKUP(A$2,Implementos!B:B,Implementos!C:C,"",0,1))=SUMIF(A:A,XLOOKUP(A$2,Implementos!B:B,Implementos!C:C,"",0,1),D:D),"",XLOOKUP(A$2,Implementos!B:B,Implementos!C:C,"",0,1)),A$2)} -> Acoplados Rurales | M39: =IF(L39="","",max(M$1:M38)+1) -> 38 | N39: =IF(L39="","",IF(N38="Orden",1,IF(COUNTIFS(N$1:N38,N38,L$1:L38,L39)=SUMIFS(D:D,B:B,N38,A:A,L39),IF(N38=maxifs(B:B,A:A,L39),"",maxifs(N$1:N38,L$1:L38,L39)+1),N38))) -> 2 | O39: =IF(N39="","",SUMIFS(C:C,B:B,N39,A:A,L39)) -> 2 | P39: =IF(N39="","",COUNTIFS(N$1:N39,N39,L$1:L39,L39)) -> 10 | Q39: =IF(U39="","",SUMIF(Productos!E:E,U39,Productos!A:A)) -> 152 | R39: {=IF(L39="","", max(1,SUMIF(I:I,XLOOKUP(U39,Productos!E:E,Productos!G:G,"",0,1),J:J)))} -> 1 | S39: =IF(Q39="","",IF(SUMIFS(Compat_Vetado!D:D,Compat_Vetado!B:B,SUM(G:G),Compat_Vetado!C:C,Q39)=1,"SI",IF(OR(SUMIF(Cotizador!E:E,Q39,Cotizador!G:G)>0,SUMIFS(Compat_Vetado!D:D,Compat_Vetado!B:B,SUM(G:G),Compat_Vetado!C:C,Q39)=-1),"NO",""))) | T39: =IF(Q39="","",IF(S39="SI","x",IF(S39="NO","",IF(AND(OR(V39="",AND(W39<=SUMIF(I:I,V39,J:J),SUMIF(I:I,V39,J:J)<=X39)),OR(Y39="",AND(Z39<=SUMIF(I:I,Y39,J:J),SUMIF(I:I,Y39,J:J)<=AA39)),OR(AB39="",AND(AC39<=SUMIF(I:I,AB39,J:J),SUMIF(I:I,AB39,J:J)<=AD39))),"x","")))) -> x | U39: =IFERROR(__xludf.DUMMYFUNCTION("IF(P39="""","""",IFERROR(INDEX(filter(Productos!E:E,Productos!F:F=L39,Productos!H:H=N39),P39),IF(M39=SUM(D:D),""Finalizar"",""-"")))"),"Cajón de Herramientas Mediano adelante") -> Cajón de Herramientas Mediano adelante | V39: =IFERROR(__xludf.DUMMYFUNCTION("IF(OR($U39="""",COUNTIF($I:$I,IFERROR(unique(filter(Prod_Prop!$H:$H,Prod_Prop!$G:$G=$U39,Prod_Prop!$E:$E=V$1)),""Check""))=0),"""",IFERROR(unique(filter(Prod_Prop!$H:$H,Prod_Prop!$G:$G=$U39,Prod_Prop!$E:$E=V$1)),""""))"),"") | W39: =IF(V39="","",SUMIFS(Prod_Prop!$J:$J,Prod_Prop!$B:$B,$Q39,Prod_Prop!$H:$H,V39,Prod_Prop!$I:$I,W$1)*IF(V39="Peso",$R39,1)) | X39: =IF(V39="","",SUMIFS(Prod_Prop!$J:$J,Prod_Prop!$B:$B,$Q39,Prod_Prop!$H:$H,V39,Prod_Prop!$I:$I,X$1)*IF(V39="Peso",$R39,1)) | Y39: =IFERROR(__xludf.DUMMYFUNCTION("IF(OR($U39="""",COUNTIF($I:$I,IFERROR(unique(filter(Prod_Prop!$H:$H,Prod_Prop!$G:$G=$U39,Prod_Prop!$E:$E=Y$1)),""Check""))=0),"""",IFERROR(unique(filter(Prod_Prop!$H:$H,Prod_Prop!$G:$G=$U39,Prod_Prop!$E:$E=Y$1)),""""))"),"") | Z39: =IF(Y39="","",SUMIFS(Prod_Prop!$J:$J,Prod_Prop!$B:$B,$Q39,Prod_Prop!$H:$H,Y39,Prod_Prop!$I:$I,Z$1)*IF(Y39="Peso",$R39,1)) | AA39: =IF(Y39="","",SUMIFS(Prod_Prop!$J:$J,Prod_Prop!$B:$B,$Q39,Prod_Prop!$H:$H,Y39,Prod_Prop!$I:$I,AA$1)*IF(Y39="Peso",$R39,1)) | AB39: =IFERROR(__xludf.DUMMYFUNCTION("IF(OR($U39="""",COUNTIF($I:$I,IFERROR(unique(filter(Prod_Prop!$H:$H,Prod_Prop!$G:$G=$U39,Prod_Prop!$E:$E=AB$1)),""Check""))=0),"""",IFERROR(unique(filter(Prod_Prop!$H:$H,Prod_Prop!$G:$G=$U39,Prod_Prop!$E:$E=AB$1)),""""))"),"") | AC39: =IF(AB39="","",SUMIFS(Prod_Prop!$J:$J,Prod_Prop!$B:$B,$Q39,Prod_Prop!$H:$H,AB39,Prod_Prop!$I:$I,AC$1)*IF(AB39="Peso",$R39,1)) | AD39: =IF(AB39="","",SUMIFS(Prod_Prop!$J:$J,Prod_Prop!$B:$B,$Q39,Prod_Prop!$H:$H,AB39,Prod_Prop!$I:$I,AD$1)*IF(AB39="Peso",$R39,1))
A40: {=IF(COUNTIF(A$1:A39,Cotizador!F$2)=maxifs(Familias!E:E,Familias!D:D,Cotizador!F$2),IF(COUNTIF(A$1:A39,XLOOKUP(Cotizador!F$2,Implementos!B:B,Implementos!C:C,"",0,1))=SUMIFS(Implementos!D:D,Implementos!B:B,Cotizador!F$2,Implementos!C:C,XLOOKUP(Cotizador!F$2,Implementos!B:B,Implementos!C:C,"",0,1)),"",XLOOKUP(Cotizador!F$2,Implementos!B:B,Implementos!C:C,"",0,1)),Cotizador!F$2)} | B40: =IF(A40="","",COUNTIF(A$1:A40,A40)) | C40: {=IF(B40="","",IF(A40=XLOOKUP(A$2,Implementos!B:B,Implementos!C:C,"",0,1),B40+maxifs(B$1:B39,A$1:A39,A$2),B40))} | D40: =IF(B40="","", COUNTIFS(Productos!F:F,A40,Productos!H:H,B40)+IF(F40="SI",0,1)) | E40: =IFERROR(__xludf.DUMMYFUNCTION("IF($B40="""","""",INDEX(filter(Familias!F:F,Familias!$D:$D=$A40,Familias!$E:$E=$B40),1))"),"") | F40: =IFERROR(__xludf.DUMMYFUNCTION("IF($B40="""","""",INDEX(filter(Familias!G:G,Familias!$D:$D=$A40,Familias!$E:$E=$B40),1))"),"") | G40: {=IF(C40=1,XLOOKUP(C40,Cotizador!D:D,Cotizador!E:E,"",0,1),"")} | J40: =IF(I40="","",SUMIF(Cotizador!I$1:V$1,I40,Cotizador!I$2:V$2)) | L40: {=IF(COUNTIF(L$1:L39,A$2)=SUMIF(A:A,A$2,D:D),IF(COUNTIF(L$1:L39,XLOOKUP(A$2,Implementos!B:B,Implementos!C:C,"",0,1))=SUMIF(A:A,XLOOKUP(A$2,Implementos!B:B,Implementos!C:C,"",0,1),D:D),"",XLOOKUP(A$2,Implementos!B:B,Implementos!C:C,"",0,1)),A$2)} -> Acoplados Rurales | M40: =IF(L40="","",max(M$1:M39)+1) -> 39 | N40: =IF(L40="","",IF(N39="Orden",1,IF(COUNTIFS(N$1:N39,N39,L$1:L39,L40)=SUMIFS(D:D,B:B,N39,A:A,L40),IF(N39=maxifs(B:B,A:A,L40),"",maxifs(N$1:N39,L$1:L39,L40)+1),N39))) -> 2 | O40: =IF(N40="","",SUMIFS(C:C,B:B,N40,A:A,L40)) -> 2 | P40: =IF(N40="","",COUNTIFS(N$1:N40,N40,L$1:L40,L40)) -> 11 | Q40: =IF(U40="","",SUMIF(Productos!E:E,U40,Productos!A:A)) -> 0 | R40: {=IF(L40="","", max(1,SUMIF(I:I,XLOOKUP(U40,Productos!E:E,Productos!G:G,"",0,1),J:J)))} -> 1 | S40: =IF(Q40="","",IF(SUMIFS(Compat_Vetado!D:D,Compat_Vetado!B:B,SUM(G:G),Compat_Vetado!C:C,Q40)=1,"SI",IF(OR(SUMIF(Cotizador!E:E,Q40,Cotizador!G:G)>0,SUMIFS(Compat_Vetado!D:D,Compat_Vetado!B:B,SUM(G:G),Compat_Vetado!C:C,Q40)=-1),"NO",""))) | T40: =IF(Q40="","",IF(S40="SI","x",IF(S40="NO","",IF(AND(OR(V40="",AND(W40<=SUMIF(I:I,V40,J:J),SUMIF(I:I,V40,J:J)<=X40)),OR(Y40="",AND(Z40<=SUMIF(I:I,Y40,J:J),SUMIF(I:I,Y40,J:J)<=AA40)),OR(AB40="",AND(AC40<=SUMIF(I:I,AB40,J:J),SUMIF(I:I,AB40,J:J)<=AD40))),"x","")))) -> x | U40: =IFERROR(__xludf.DUMMYFUNCTION("IF(P40="""","""",IFERROR(INDEX(filter(Productos!E:E,Productos!F:F=L40,Productos!H:H=N40),P40),IF(M40=SUM(D:D),""Finalizar"",""-"")))"),"-") -> - | V40: =IFERROR(__xludf.DUMMYFUNCTION("IF(OR($U40="""",COUNTIF($I:$I,IFERROR(unique(filter(Prod_Prop!$H:$H,Prod_Prop!$G:$G=$U40,Prod_Prop!$E:$E=V$1)),""Check""))=0),"""",IFERROR(unique(filter(Prod_Prop!$H:$H,Prod_Prop!$G:$G=$U40,Prod_Prop!$E:$E=V$1)),""""))"),"") | W40: =IF(V40="","",SUMIFS(Prod_Prop!$J:$J,Prod_Prop!$B:$B,$Q40,Prod_Prop!$H:$H,V40,Prod_Prop!$I:$I,W$1)*IF(V40="Peso",$R40,1)) | X40: =IF(V40="","",SUMIFS(Prod_Prop!$J:$J,Prod_Prop!$B:$B,$Q40,Prod_Prop!$H:$H,V40,Prod_Prop!$I:$I,X$1)*IF(V40="Peso",$R40,1)) | Y40: =IFERROR(__xludf.DUMMYFUNCTION("IF(OR($U40="""",COUNTIF($I:$I,IFERROR(unique(filter(Prod_Prop!$H:$H,Prod_Prop!$G:$G=$U40,Prod_Prop!$E:$E=Y$1)),""Check""))=0),"""",IFERROR(unique(filter(Prod_Prop!$H:$H,Prod_Prop!$G:$G=$U40,Prod_Prop!$E:$E=Y$1)),""""))"),"") | Z40: =IF(Y40="","",SUMIFS(Prod_Prop!$J:$J,Prod_Prop!$B:$B,$Q40,Prod_Prop!$H:$H,Y40,Prod_Prop!$I:$I,Z$1)*IF(Y40="Peso",$R40,1)) | AA40: =IF(Y40="","",SUMIFS(Prod_Prop!$J:$J,Prod_Prop!$B:$B,$Q40,Prod_Prop!$H:$H,Y40,Prod_Prop!$I:$I,AA$1)*IF(Y40="Peso",$R40,1)) | AB40: =IFERROR(__xludf.DUMMYFUNCTION("IF(OR($U40="""",COUNTIF($I:$I,IFERROR(unique(filter(Prod_Prop!$H:$H,Prod_Prop!$G:$G=$U40,Prod_Prop!$E:$E=AB$1)),""Check""))=0),"""",IFERROR(unique(filter(Prod_Prop!$H:$H,Prod_Prop!$G:$G=$U40,Prod_Prop!$E:$E=AB$1)),""""))"),"") | AC40: =IF(AB40="","",SUMIFS(Prod_Prop!$J:$J,Prod_Prop!$B:$B,$Q40,Prod_Prop!$H:$H,AB40,Prod_Prop!$I:$I,AC$1)*IF(AB40="Peso",$R40,1)) | AD40: =IF(AB40="","",SUMIFS(Prod_Prop!$J:$J,Prod_Prop!$B:$B,$Q40,Prod_Prop!$H:$H,AB40,Prod_Prop!$I:$I,AD$1)*IF(AB40="Peso",$R40,1))
A41: {=IF(COUNTIF(A$1:A40,Cotizador!F$2)=maxifs(Familias!E:E,Familias!D:D,Cotizador!F$2),IF(COUNTIF(A$1:A40,XLOOKUP(Cotizador!F$2,Implementos!B:B,Implementos!C:C,"",0,1))=SUMIFS(Implementos!D:D,Implementos!B:B,Cotizador!F$2,Implementos!C:C,XLOOKUP(Cotizador!F$2,Implementos!B:B,Implementos!C:C,"",0,1)),"",XLOOKUP(Cotizador!F$2,Implementos!B:B,Implementos!C:C,"",0,1)),Cotizador!F$2)} | B41: =IF(A41="","",COUNTIF(A$1:A41,A41)) | C41: {=IF(B41="","",IF(A41=XLOOKUP(A$2,Implementos!B:B,Implementos!C:C,"",0,1),B41+maxifs(B$1:B40,A$1:A40,A$2),B41))} | D41: =IF(B41="","", COUNTIFS(Productos!F:F,A41,Productos!H:H,B41)+IF(F41="SI",0,1)) | E41: =IFERROR(__xludf.DUMMYFUNCTION("IF($B41="""","""",INDEX(filter(Familias!F:F,Familias!$D:$D=$A41,Familias!$E:$E=$B41),1))"),"") | F41: =IFERROR(__xludf.DUMMYFUNCTION("IF($B41="""","""",INDEX(filter(Familias!G:G,Familias!$D:$D=$A41,Familias!$E:$E=$B41),1))"),"") | G41: {=IF(C41=1,XLOOKUP(C41,Cotizador!D:D,Cotizador!E:E,"",0,1),"")} | J41: =IF(I41="","",SUMIF(Cotizador!I$1:V$1,I41,Cotizador!I$2:V$2)) | L41: {=IF(COUNTIF(L$1:L40,A$2)=SUMIF(A:A,A$2,D:D),IF(COUNTIF(L$1:L40,XLOOKUP(A$2,Implementos!B:B,Implementos!C:C,"",0,1))=SUMIF(A:A,XLOOKUP(A$2,Implementos!B:B,Implementos!C:C,"",0,1),D:D),"",XLOOKUP(A$2,Implementos!B:B,Implementos!C:C,"",0,1)),A$2)} -> Acoplados Rurales | M41: =IF(L41="","",max(M$1:M40)+1) -> 40 | N41: =IF(L41="","",IF(N40="Orden",1,IF(COUNTIFS(N$1:N40,N40,L$1:L40,L41)=SUMIFS(D:D,B:B,N40,A:A,L41),IF(N40=maxifs(B:B,A:A,L41),"",maxifs(N$1:N40,L$1:L40,L41)+1),N40))) -> 3 | O41: =IF(N41="","",SUMIFS(C:C,B:B,N41,A:A,L41)) -> 3 | P41: =IF(N41="","",COUNTIFS(N$1:N41,N41,L$1:L41,L41)) -> 1 | Q41: =IF(U41="","",SUMIF(Productos!E:E,U41,Productos!A:A)) -> 72 | R41: {=IF(L41="","", max(1,SUMIF(I:I,XLOOKUP(U41,Productos!E:E,Productos!G:G,"",0,1),J:J)))} -> 1 | S41: =IF(Q41="","",IF(SUMIFS(Compat_Vetado!D:D,Compat_Vetado!B:B,SUM(G:G),Compat_Vetado!C:C,Q41)=1,"SI",IF(OR(SUMIF(Cotizador!E:E,Q41,Cotizador!G:G)>0,SUMIFS(Compat_Vetado!D:D,Compat_Vetado!B:B,SUM(G:G),Compat_Vetado!C:C,Q41)=-1),"NO",""))) | T41: =IF(Q41="","",IF(S41="SI","x",IF(S41="NO","",IF(AND(OR(V41="",AND(W41<=SUMIF(I:I,V41,J:J),SUMIF(I:I,V41,J:J)<=X41)),OR(Y41="",AND(Z41<=SUMIF(I:I,Y41,J:J),SUMIF(I:I,Y41,J:J)<=AA41)),OR(AB41="",AND(AC41<=SUMIF(I:I,AB41,J:J),SUMIF(I:I,AB41,J:J)<=AD41))),"x","")))) | U41: =IFERROR(__xludf.DUMMYFUNCTION("IF(P41="""","""",IFERROR(INDEX(filter(Productos!E:E,Productos!F:F=L41,Productos!H:H=N41),P41),IF(M41=SUM(D:D),""Finalizar"",""-"")))"),"Chasis Acoplado 2 Ejes L3000") -> Chasis Acoplado 2 Ejes L3000 | V41: =IFERROR(__xludf.DUMMYFUNCTION("IF(OR($U41="""",COUNTIF($I:$I,IFERROR(unique(filter(Prod_Prop!$H:$H,Prod_Prop!$G:$G=$U41,Prod_Prop!$E:$E=V$1)),""Check""))=0),"""",IFERROR(unique(filter(Prod_Prop!$H:$H,Prod_Prop!$G:$G=$U41,Prod_Prop!$E:$E=V$1)),""""))"),"Longitud") -> Longitud | W41: =IF(V41="","",SUMIFS(Prod_Prop!$J:$J,Prod_Prop!$B:$B,$Q41,Prod_Prop!$H:$H,V41,Prod_Prop!$I:$I,W$1)*IF(V41="Peso",$R41,1)) -> 2.8 | X41: =IF(V41="","",SUMIFS(Prod_Prop!$J:$J,Prod_Prop!$B:$B,$Q41,Prod_Prop!$H:$H,V41,Prod_Prop!$I:$I,X$1)*IF(V41="Peso",$R41,1)) -> 3 | Y41: =IFERROR(__xludf.DUMMYFUNCTION("IF(OR($U41="""",COUNTIF($I:$I,IFERROR(unique(filter(Prod_Prop!$H:$H,Prod_Prop!$G:$G=$U41,Prod_Prop!$E:$E=Y$1)),""Check""))=0),"""",IFERROR(unique(filter(Prod_Prop!$H:$H,Prod_Prop!$G:$G=$U41,Prod_Prop!$E:$E=Y$1)),""""))"),"") | Z41: =IF(Y41="","",SUMIFS(Prod_Prop!$J:$J,Prod_Prop!$B:$B,$Q41,Prod_Prop!$H:$H,Y41,Prod_Prop!$I:$I,Z$1)*IF(Y41="Peso",$R41,1)) | AA41: =IF(Y41="","",SUMIFS(Prod_Prop!$J:$J,Prod_Prop!$B:$B,$Q41,Prod_Prop!$H:$H,Y41,Prod_Prop!$I:$I,AA$1)*IF(Y41="Peso",$R41,1)) | AB41: =IFERROR(__xludf.DUMMYFUNCTION("IF(OR($U41="""",COUNTIF($I:$I,IFERROR(unique(filter(Prod_Prop!$H:$H,Prod_Prop!$G:$G=$U41,Prod_Prop!$E:$E=AB$1)),""Check""))=0),"""",IFERROR(unique(filter(Prod_Prop!$H:$H,Prod_Prop!$G:$G=$U41,Prod_Prop!$E:$E=AB$1)),""""))"),"") | AC41: =IF(AB41="","",SUMIFS(Prod_Prop!$J:$J,Prod_Prop!$B:$B,$Q41,Prod_Prop!$H:$H,AB41,Prod_Prop!$I:$I,AC$1)*IF(AB41="Peso",$R41,1)) | AD41: =IF(AB41="","",SUMIFS(Prod_Prop!$J:$J,Prod_Prop!$B:$B,$Q41,Prod_Prop!$H:$H,AB41,Prod_Prop!$I:$I,AD$1)*IF(AB41="Peso",$R41,1))
A42: {=IF(COUNTIF(A$1:A41,Cotizador!F$2)=maxifs(Familias!E:E,Familias!D:D,Cotizador!F$2),IF(COUNTIF(A$1:A41,XLOOKUP(Cotizador!F$2,Implementos!B:B,Implementos!C:C,"",0,1))=SUMIFS(Implementos!D:D,Implementos!B:B,Cotizador!F$2,Implementos!C:C,XLOOKUP(Cotizador!F$2,Implementos!B:B,Implementos!C:C,"",0,1)),"",XLOOKUP(Cotizador!F$2,Implementos!B:B,Implementos!C:C,"",0,1)),Cotizador!F$2)} | B42: =IF(A42="","",COUNTIF(A$1:A42,A42)) | C42: {=IF(B42="","",IF(A42=XLOOKUP(A$2,Implementos!B:B,Implementos!C:C,"",0,1),B42+maxifs(B$1:B41,A$1:A41,A$2),B42))} | D42: =IF(B42="","", COUNTIFS(Productos!F:F,A42,Productos!H:H,B42)+IF(F42="SI",0,1)) | E42: =IFERROR(__xludf.DUMMYFUNCTION("IF($B42="""","""",INDEX(filter(Familias!F:F,Familias!$D:$D=$A42,Familias!$E:$E=$B42),1))"),"") | F42: =IFERROR(__xludf.DUMMYFUNCTION("IF($B42="""","""",INDEX(filter(Familias!G:G,Familias!$D:$D=$A42,Familias!$E:$E=$B42),1))"),"") | G42: {=IF(C42=1,XLOOKUP(C42,Cotizador!D:D,Cotizador!E:E,"",0,1),"")} | J42: =IF(I42="","",SUMIF(Cotizador!I$1:V$1,I42,Cotizador!I$2:V$2)) | L42: {=IF(COUNTIF(L$1:L41,A$2)=SUMIF(A:A,A$2,D:D),IF(COUNTIF(L$1:L41,XLOOKUP(A$2,Implementos!B:B,Implementos!C:C,"",0,1))=SUMIF(A:A,XLOOKUP(A$2,Implementos!B:B,Implementos!C:C,"",0,1),D:D),"",XLOOKUP(A$2,Implementos!B:B,Implementos!C:C,"",0,1)),A$2)} -> Acoplados Rurales | M42: =IF(L42="","",max(M$1:M41)+1) -> 41 | N42: =IF(L42="","",IF(N41="Orden",1,IF(COUNTIFS(N$1:N41,N41,L$1:L41,L42)=SUMIFS(D:D,B:B,N41,A:A,L42),IF(N41=maxifs(B:B,A:A,L42),"",maxifs(N$1:N41,L$1:L41,L42)+1),N41))) -> 3 | O42: =IF(N42="","",SUMIFS(C:C,B:B,N42,A:A,L42)) -> 3 | P42: =IF(N42="","",COUNTIFS(N$1:N42,N42,L$1:L42,L42)) -> 2 | Q42: =IF(U42="","",SUMIF(Productos!E:E,U42,Productos!A:A)) -> 73 | R42: {=IF(L42="","", max(1,SUMIF(I:I,XLOOKUP(U42,Productos!E:E,Productos!G:G,"",0,1),J:J)))} -> 1 | S42: =IF(Q42="","",IF(SUMIFS(Compat_Vetado!D:D,Compat_Vetado!B:B,SUM(G:G),Compat_Vetado!C:C,Q42)=1,"SI",IF(OR(SUMIF(Cotizador!E:E,Q42,Cotizador!G:G)>0,SUMIFS(Compat_Vetado!D:D,Compat_Vetado!B:B,SUM(G:G),Compat_Vetado!C:C,Q42)=-1),"NO",""))) | T42: =IF(Q42="","",IF(S42="SI","x",IF(S42="NO","",IF(AND(OR(V42="",AND(W42<=SUMIF(I:I,V42,J:J),SUMIF(I:I,V42,J:J)<=X42)),OR(Y42="",AND(Z42<=SUMIF(I:I,Y42,J:J),SUMIF(I:I,Y42,J:J)<=AA42)),OR(AB42="",AND(AC42<=SUMIF(I:I,AB42,J:J),SUMIF(I:I,AB42,J:J)<=AD42))),"x","")))) | U42: =IFERROR(__xludf.DUMMYFUNCTION("IF(P42="""","""",IFERROR(INDEX(filter(Productos!E:E,Productos!F:F=L42,Productos!H:H=N42),P42),IF(M42=SUM(D:D),""Finalizar"",""-"")))"),"Chasis Acoplado 2 Ejes L3750") -> Chasis Acoplado 2 Ejes L3750 | V42: =IFERROR(__xludf.DUMMYFUNCTION("IF(OR($U42="""",COUNTIF($I:$I,IFERROR(unique(filter(Prod_Prop!$H:$H,Prod_Prop!$G:$G=$U42,Prod_Prop!$E:$E=V$1)),""Check""))=0),"""",IFERROR(unique(filter(Prod_Prop!$H:$H,Prod_Prop!$G:$G=$U42,Prod_Prop!$E:$E=V$1)),""""))"),"Longitud") -> Longitud | W42: =IF(V42="","",SUMIFS(Prod_Prop!$J:$J,Prod_Prop!$B:$B,$Q42,Prod_Prop!$H:$H,V42,Prod_Prop!$I:$I,W$1)*IF(V42="Peso",$R42,1)) -> 3.55 | X42: =IF(V42="","",SUMIFS(Prod_Prop!$J:$J,Prod_Prop!$B:$B,$Q42,Prod_Prop!$H:$H,V42,Prod_Prop!$I:$I,X$1)*IF(V42="Peso",$R42,1)) -> 3.75 | Y42: =IFERROR(__xludf.DUMMYFUNCTION("IF(OR($U42="""",COUNTIF($I:$I,IFERROR(unique(filter(Prod_Prop!$H:$H,Prod_Prop!$G:$G=$U42,Prod_Prop!$E:$E=Y$1)),""Check""))=0),"""",IFERROR(unique(filter(Prod_Prop!$H:$H,Prod_Prop!$G:$G=$U42,Prod_Prop!$E:$E=Y$1)),""""))"),"") | Z42: =IF(Y42="","",SUMIFS(Prod_Prop!$J:$J,Prod_Prop!$B:$B,$Q42,Prod_Prop!$H:$H,Y42,Prod_Prop!$I:$I,Z$1)*IF(Y42="Peso",$R42,1)) | AA42: =IF(Y42="","",SUMIFS(Prod_Prop!$J:$J,Prod_Prop!$B:$B,$Q42,Prod_Prop!$H:$H,Y42,Prod_Prop!$I:$I,AA$1)*IF(Y42="Peso",$R42,1)) | AB42: =IFERROR(__xludf.DUMMYFUNCTION("IF(OR($U42="""",COUNTIF($I:$I,IFERROR(unique(filter(Prod_Prop!$H:$H,Prod_Prop!$G:$G=$U42,Prod_Prop!$E:$E=AB$1)),""Check""))=0),"""",IFERROR(unique(filter(Prod_Prop!$H:$H,Prod_Prop!$G:$G=$U42,Prod_Prop!$E:$E=AB$1)),""""))"),"") | AC42: =IF(AB42="","",SUMIFS(Prod_Prop!$J:$J,Prod_Prop!$B:$B,$Q42,Prod_Prop!$H:$H,AB42,Prod_Prop!$I:$I,AC$1)*IF(AB42="Peso",$R42,1)) | AD42: =IF(AB42="","",SUMIFS(Prod_Prop!$J:$J,Prod_Prop!$B:$B,$Q42,Prod_Prop!$H:$H,AB42,Prod_Prop!$I:$I,AD$1)*IF(AB42="Peso",$R42,1))
A43: {=IF(COUNTIF(A$1:A42,Cotizador!F$2)=maxifs(Familias!E:E,Familias!D:D,Cotizador!F$2),IF(COUNTIF(A$1:A42,XLOOKUP(Cotizador!F$2,Implementos!B:B,Implementos!C:C,"",0,1))=SUMIFS(Implementos!D:D,Implementos!B:B,Cotizador!F$2,Implementos!C:C,XLOOKUP(Cotizador!F$2,Implementos!B:B,Implementos!C:C,"",0,1)),"",XLOOKUP(Cotizador!F$2,Implementos!B:B,Implementos!C:C,"",0,1)),Cotizador!F$2)} | B43: =IF(A43="","",COUNTIF(A$1:A43,A43)) | C43: {=IF(B43="","",IF(A43=XLOOKUP(A$2,Implementos!B:B,Implementos!C:C,"",0,1),B43+maxifs(B$1:B42,A$1:A42,A$2),B43))} | D43: =IF(B43="","", COUNTIFS(Productos!F:F,A43,Productos!H:H,B43)+IF(F43="SI",0,1)) | E43: =IFERROR(__xludf.DUMMYFUNCTION("IF($B43="""","""",INDEX(filter(Familias!F:F,Familias!$D:$D=$A43,Familias!$E:$E=$B43),1))"),"") | F43: =IFERROR(__xludf.DUMMYFUNCTION("IF($B43="""","""",INDEX(filter(Familias!G:G,Familias!$D:$D=$A43,Familias!$E:$E=$B43),1))"),"") | G43: {=IF(C43=1,XLOOKUP(C43,Cotizador!D:D,Cotizador!E:E,"",0,1),"")} | J43: =IF(I43="","",SUMIF(Cotizador!I$1:V$1,I43,Cotizador!I$2:V$2)) | L43: {=IF(COUNTIF(L$1:L42,A$2)=SUMIF(A:A,A$2,D:D),IF(COUNTIF(L$1:L42,XLOOKUP(A$2,Implementos!B:B,Implementos!C:C,"",0,1))=SUMIF(A:A,XLOOKUP(A$2,Implementos!B:B,Implementos!C:C,"",0,1),D:D),"",XLOOKUP(A$2,Implementos!B:B,Implementos!C:C,"",0,1)),A$2)} -> Acoplados Rurales | M43: =IF(L43="","",max(M$1:M42)+1) -> 42 | N43: =IF(L43="","",IF(N42="Orden",1,IF(COUNTIFS(N$1:N42,N42,L$1:L42,L43)=SUMIFS(D:D,B:B,N42,A:A,L43),IF(N42=maxifs(B:B,A:A,L43),"",maxifs(N$1:N42,L$1:L42,L43)+1),N42))) -> 3 | O43: =IF(N43="","",SUMIFS(C:C,B:B,N43,A:A,L43)) -> 3 | P43: =IF(N43="","",COUNTIFS(N$1:N43,N43,L$1:L43,L43)) -> 3 | Q43: =IF(U43="","",SUMIF(Productos!E:E,U43,Productos!A:A)) -> 74 | R43: {=IF(L43="","", max(1,SUMIF(I:I,XLOOKUP(U43,Productos!E:E,Productos!G:G,"",0,1),J:J)))} -> 1 | S43: =IF(Q43="","",IF(SUMIFS(Compat_Vetado!D:D,Compat_Vetado!B:B,SUM(G:G),Compat_Vetado!C:C,Q43)=1,"SI",IF(OR(SUMIF(Cotizador!E:E,Q43,Cotizador!G:G)>0,SUMIFS(Compat_Vetado!D:D,Compat_Vetado!B:B,SUM(G:G),Compat_Vetado!C:C,Q43)=-1),"NO",""))) | T43: =IF(Q43="","",IF(S43="SI","x",IF(S43="NO","",IF(AND(OR(V43="",AND(W43<=SUMIF(I:I,V43,J:J),SUMIF(I:I,V43,J:J)<=X43)),OR(Y43="",AND(Z43<=SUMIF(I:I,Y43,J:J),SUMIF(I:I,Y43,J:J)<=AA43)),OR(AB43="",AND(AC43<=SUMIF(I:I,AB43,J:J),SUMIF(I:I,AB43,J:J)<=AD43))),"x","")))) | U43: =IFERROR(__xludf.DUMMYFUNCTION("IF(P43="""","""",IFERROR(INDEX(filter(Productos!E:E,Productos!F:F=L43,Productos!H:H=N43),P43),IF(M43=SUM(D:D),""Finalizar"",""-"")))"),"Chasis Acoplado 2 Ejes L4000") -> Chasis Acoplado 2 Ejes L4000 | V43: =IFERROR(__xludf.DUMMYFUNCTION("IF(OR($U43="""",COUNTIF($I:$I,IFERROR(unique(filter(Prod_Prop!$H:$H,Prod_Prop!$G:$G=$U43,Prod_Prop!$E:$E=V$1)),""Check""))=0),"""",IFERROR(unique(filter(Prod_Prop!$H:$H,Prod_Prop!$G:$G=$U43,Prod_Prop!$E:$E=V$1)),""""))"),"Longitud") -> Longitud | W43: =IF(V43="","",SUMIFS(Prod_Prop!$J:$J,Prod_Prop!$B:$B,$Q43,Prod_Prop!$H:$H,V43,Prod_Prop!$I:$I,W$1)*IF(V43="Peso",$R43,1)) -> 3.8 | X43: =IF(V43="","",SUMIFS(Prod_Prop!$J:$J,Prod_Prop!$B:$B,$Q43,Prod_Prop!$H:$H,V43,Prod_Prop!$I:$I,X$1)*IF(V43="Peso",$R43,1)) -> 4 | Y43: =IFERROR(__xludf.DUMMYFUNCTION("IF(OR($U43="""",COUNTIF($I:$I,IFERROR(unique(filter(Prod_Prop!$H:$H,Prod_Prop!$G:$G=$U43,Prod_Prop!$E:$E=Y$1)),""Check""))=0),"""",IFERROR(unique(filter(Prod_Prop!$H:$H,Prod_Prop!$G:$G=$U43,Prod_Prop!$E:$E=Y$1)),""""))"),"") | Z43: =IF(Y43="","",SUMIFS(Prod_Prop!$J:$J,Prod_Prop!$B:$B,$Q43,Prod_Prop!$H:$H,Y43,Prod_Prop!$I:$I,Z$1)*IF(Y43="Peso",$R43,1)) | AA43: =IF(Y43="","",SUMIFS(Prod_Prop!$J:$J,Prod_Prop!$B:$B,$Q43,Prod_Prop!$H:$H,Y43,Prod_Prop!$I:$I,AA$1)*IF(Y43="Peso",$R43,1)) | AB43: =IFERROR(__xludf.DUMMYFUNCTION("IF(OR($U43="""",COUNTIF($I:$I,IFERROR(unique(filter(Prod_Prop!$H:$H,Prod_Prop!$G:$G=$U43,Prod_Prop!$E:$E=AB$1)),""Check""))=0),"""",IFERROR(unique(filter(Prod_Prop!$H:$H,Prod_Prop!$G:$G=$U43,Prod_Prop!$E:$E=AB$1)),""""))"),"") | AC43: =IF(AB43="","",SUMIFS(Prod_Prop!$J:$J,Prod_Prop!$B:$B,$Q43,Prod_Prop!$H:$H,AB43,Prod_Prop!$I:$I,AC$1)*IF(AB43="Peso",$R43,1)) | AD43: =IF(AB43="","",SUMIFS(Prod_Prop!$J:$J,Prod_Prop!$B:$B,$Q43,Prod_Prop!$H:$H,AB43,Prod_Prop!$I:$I,AD$1)*IF(AB43="Peso",$R43,1))
A44: {=IF(COUNTIF(A$1:A43,Cotizador!F$2)=maxifs(Familias!E:E,Familias!D:D,Cotizador!F$2),IF(COUNTIF(A$1:A43,XLOOKUP(Cotizador!F$2,Implementos!B:B,Implementos!C:C,"",0,1))=SUMIFS(Implementos!D:D,Implementos!B:B,Cotizador!F$2,Implementos!C:C,XLOOKUP(Cotizador!F$2,Implementos!B:B,Implementos!C:C,"",0,1)),"",XLOOKUP(Cotizador!F$2,Implementos!B:B,Implementos!C:C,"",0,1)),Cotizador!F$2)} | B44: =IF(A44="","",COUNTIF(A$1:A44,A44)) | C44: {=IF(B44="","",IF(A44=XLOOKUP(A$2,Implementos!B:B,Implementos!C:C,"",0,1),B44+maxifs(B$1:B43,A$1:A43,A$2),B44))} | D44: =IF(B44="","", COUNTIFS(Productos!F:F,A44,Productos!H:H,B44)+IF(F44="SI",0,1)) | E44: =IFERROR(__xludf.DUMMYFUNCTION("IF($B44="""","""",INDEX(filter(Familias!F:F,Familias!$D:$D=$A44,Familias!$E:$E=$B44),1))"),"") | F44: =IFERROR(__xludf.DUMMYFUNCTION("IF($B44="""","""",INDEX(filter(Familias!G:G,Familias!$D:$D=$A44,Familias!$E:$E=$B44),1))"),"") | G44: {=IF(C44=1,XLOOKUP(C44,Cotizador!D:D,Cotizador!E:E,"",0,1),"")} | J44: =IF(I44="","",SUMIF(Cotizador!I$1:V$1,I44,Cotizador!I$2:V$2)) | L44: {=IF(COUNTIF(L$1:L43,A$2)=SUMIF(A:A,A$2,D:D),IF(COUNTIF(L$1:L43,XLOOKUP(A$2,Implementos!B:B,Implementos!C:C,"",0,1))=SUMIF(A:A,XLOOKUP(A$2,Implementos!B:B,Implementos!C:C,"",0,1),D:D),"",XLOOKUP(A$2,Implementos!B:B,Implementos!C:C,"",0,1)),A$2)} -> Acoplados Rurales | M44: =IF(L44="","",max(M$1:M43)+1) -> 43 | N44: =IF(L44="","",IF(N43="Orden",1,IF(COUNTIFS(N$1:N43,N43,L$1:L43,L44)=SUMIFS(D:D,B:B,N43,A:A,L44),IF(N43=maxifs(B:B,A:A,L44),"",maxifs(N$1:N43,L$1:L43,L44)+1),N43))) -> 3 | O44: =IF(N44="","",SUMIFS(C:C,B:B,N44,A:A,L44)) -> 3 | P44: =IF(N44="","",COUNTIFS(N$1:N44,N44,L$1:L44,L44)) -> 4 | Q44: =IF(U44="","",SUMIF(Productos!E:E,U44,Productos!A:A)) -> 75 | R44: {=IF(L44="","", max(1,SUMIF(I:I,XLOOKUP(U44,Productos!E:E,Productos!G:G,"",0,1),J:J)))} -> 1 | S44: =IF(Q44="","",IF(SUMIFS(Compat_Vetado!D:D,Compat_Vetado!B:B,SUM(G:G),Compat_Vetado!C:C,Q44)=1,"SI",IF(OR(SUMIF(Cotizador!E:E,Q44,Cotizador!G:G)>0,SUMIFS(Compat_Vetado!D:D,Compat_Vetado!B:B,SUM(G:G),Compat_Vetado!C:C,Q44)=-1),"NO",""))) | T44: =IF(Q44="","",IF(S44="SI","x",IF(S44="NO","",IF(AND(OR(V44="",AND(W44<=SUMIF(I:I,V44,J:J),SUMIF(I:I,V44,J:J)<=X44)),OR(Y44="",AND(Z44<=SUMIF(I:I,Y44,J:J),SUMIF(I:I,Y44,J:J)<=AA44)),OR(AB44="",AND(AC44<=SUMIF(I:I,AB44,J:J),SUMIF(I:I,AB44,J:J)<=AD44))),"x","")))) | U44: =IFERROR(__xludf.DUMMYFUNCTION("IF(P44="""","""",IFERROR(INDEX(filter(Productos!E:E,Productos!F:F=L44,Productos!H:H=N44),P44),IF(M44=SUM(D:D),""Finalizar"",""-"")))"),"Chasis Acoplado 2 Ejes L4000 Reforzado") -> Chasis Acoplado 2 Ejes L4000 Reforzado | V44: =IFERROR(__xludf.DUMMYFUNCTION("IF(OR($U44="""",COUNTIF($I:$I,IFERROR(unique(filter(Prod_Prop!$H:$H,Prod_Prop!$G:$G=$U44,Prod_Prop!$E:$E=V$1)),""Check""))=0),"""",IFERROR(unique(filter(Prod_Prop!$H:$H,Prod_Prop!$G:$G=$U44,Prod_Prop!$E:$E=V$1)),""""))"),"Longitud") -> Longitud | W44: =IF(V44="","",SUMIFS(Prod_Prop!$J:$J,Prod_Prop!$B:$B,$Q44,Prod_Prop!$H:$H,V44,Prod_Prop!$I:$I,W$1)*IF(V44="Peso",$R44,1)) -> 3.8 | X44: =IF(V44="","",SUMIFS(Prod_Prop!$J:$J,Prod_Prop!$B:$B,$Q44,Prod_Prop!$H:$H,V44,Prod_Prop!$I:$I,X$1)*IF(V44="Peso",$R44,1)) -> 4 | Y44: =IFERROR(__xludf.DUMMYFUNCTION("IF(OR($U44="""",COUNTIF($I:$I,IFERROR(unique(filter(Prod_Prop!$H:$H,Prod_Prop!$G:$G=$U44,Prod_Prop!$E:$E=Y$1)),""Check""))=0),"""",IFERROR(unique(filter(Prod_Prop!$H:$H,Prod_Prop!$G:$G=$U44,Prod_Prop!$E:$E=Y$1)),""""))"),"") | Z44: =IF(Y44="","",SUMIFS(Prod_Prop!$J:$J,Prod_Prop!$B:$B,$Q44,Prod_Prop!$H:$H,Y44,Prod_Prop!$I:$I,Z$1)*IF(Y44="Peso",$R44,1)) | AA44: =IF(Y44="","",SUMIFS(Prod_Prop!$J:$J,Prod_Prop!$B:$B,$Q44,Prod_Prop!$H:$H,Y44,Prod_Prop!$I:$I,AA$1)*IF(Y44="Peso",$R44,1)) | AB44: =IFERROR(__xludf.DUMMYFUNCTION("IF(OR($U44="""",COUNTIF($I:$I,IFERROR(unique(filter(Prod_Prop!$H:$H,Prod_Prop!$G:$G=$U44,Prod_Prop!$E:$E=AB$1)),""Check""))=0),"""",IFERROR(unique(filter(Prod_Prop!$H:$H,Prod_Prop!$G:$G=$U44,Prod_Prop!$E:$E=AB$1)),""""))"),"") | AC44: =IF(AB44="","",SUMIFS(Prod_Prop!$J:$J,Prod_Prop!$B:$B,$Q44,Prod_Prop!$H:$H,AB44,Prod_Prop!$I:$I,AC$1)*IF(AB44="Peso",$R44,1)) | AD44: =IF(AB44="","",SUMIFS(Prod_Prop!$J:$J,Prod_Prop!$B:$B,$Q44,Prod_Prop!$H:$H,AB44,Prod_Prop!$I:$I,AD$1)*IF(AB44="Peso",$R44,1))
A45: {=IF(COUNTIF(A$1:A44,Cotizador!F$2)=maxifs(Familias!E:E,Familias!D:D,Cotizador!F$2),IF(COUNTIF(A$1:A44,XLOOKUP(Cotizador!F$2,Implementos!B:B,Implementos!C:C,"",0,1))=SUMIFS(Implementos!D:D,Implementos!B:B,Cotizador!F$2,Implementos!C:C,XLOOKUP(Cotizador!F$2,Implementos!B:B,Implementos!C:C,"",0,1)),"",XLOOKUP(Cotizador!F$2,Implementos!B:B,Implementos!C:C,"",0,1)),Cotizador!F$2)} | B45: =IF(A45="","",COUNTIF(A$1:A45,A45)) | C45: {=IF(B45="","",IF(A45=XLOOKUP(A$2,Implementos!B:B,Implementos!C:C,"",0,1),B45+maxifs(B$1:B44,A$1:A44,A$2),B45))} | D45: =IF(B45="","", COUNTIFS(Productos!F:F,A45,Productos!H:H,B45)+IF(F45="SI",0,1)) | E45: =IFERROR(__xludf.DUMMYFUNCTION("IF($B45="""","""",INDEX(filter(Familias!F:F,Familias!$D:$D=$A45,Familias!$E:$E=$B45),1))"),"") | F45: =IFERROR(__xludf.DUMMYFUNCTION("IF($B45="""","""",INDEX(filter(Familias!G:G,Familias!$D:$D=$A45,Familias!$E:$E=$B45),1))"),"") | G45: {=IF(C45=1,XLOOKUP(C45,Cotizador!D:D,Cotizador!E:E,"",0,1),"")} | J45: =IF(I45="","",SUMIF(Cotizador!I$1:V$1,I45,Cotizador!I$2:V$2)) | L45: {=IF(COUNTIF(L$1:L44,A$2)=SUMIF(A:A,A$2,D:D),IF(COUNTIF(L$1:L44,XLOOKUP(A$2,Implementos!B:B,Implementos!C:C,"",0,1))=SUMIF(A:A,XLOOKUP(A$2,Implementos!B:B,Implementos!C:C,"",0,1),D:D),"",XLOOKUP(A$2,Implementos!B:B,Implementos!C:C,"",0,1)),A$2)} -> Acoplados Rurales | M45: =IF(L45="","",max(M$1:M44)+1) -> 44 | N45: =IF(L45="","",IF(N44="Orden",1,IF(COUNTIFS(N$1:N44,N44,L$1:L44,L45)=SUMIFS(D:D,B:B,N44,A:A,L45),IF(N44=maxifs(B:B,A:A,L45),"",maxifs(N$1:N44,L$1:L44,L45)+1),N44))) -> 3 | O45: =IF(N45="","",SUMIFS(C:C,B:B,N45,A:A,L45)) -> 3 | P45: =IF(N45="","",COUNTIFS(N$1:N45,N45,L$1:L45,L45)) -> 5 | Q45: =IF(U45="","",SUMIF(Productos!E:E,U45,Productos!A:A)) -> 76 | R45: {=IF(L45="","", max(1,SUMIF(I:I,XLOOKUP(U45,Productos!E:E,Productos!G:G,"",0,1),J:J)))} -> 1 | S45: =IF(Q45="","",IF(SUMIFS(Compat_Vetado!D:D,Compat_Vetado!B:B,SUM(G:G),Compat_Vetado!C:C,Q45)=1,"SI",IF(OR(SUMIF(Cotizador!E:E,Q45,Cotizador!G:G)>0,SUMIFS(Compat_Vetado!D:D,Compat_Vetado!B:B,SUM(G:G),Compat_Vetado!C:C,Q45)=-1),"NO",""))) | T45: =IF(Q45="","",IF(S45="SI","x",IF(S45="NO","",IF(AND(OR(V45="",AND(W45<=SUMIF(I:I,V45,J:J),SUMIF(I:I,V45,J:J)<=X45)),OR(Y45="",AND(Z45<=SUMIF(I:I,Y45,J:J),SUMIF(I:I,Y45,J:J)<=AA45)),OR(AB45="",AND(AC45<=SUMIF(I:I,AB45,J:J),SUMIF(I:I,AB45,J:J)<=AD45))),"x","")))) | U45: =IFERROR(__xludf.DUMMYFUNCTION("IF(P45="""","""",IFERROR(INDEX(filter(Productos!E:E,Productos!F:F=L45,Productos!H:H=N45),P45),IF(M45=SUM(D:D),""Finalizar"",""-"")))"),"Chasis Acoplado 2 Ejes L4750") -> Chasis Acoplado 2 Ejes L4750 | V45: =IFERROR(__xludf.DUMMYFUNCTION("IF(OR($U45="""",COUNTIF($I:$I,IFERROR(unique(filter(Prod_Prop!$H:$H,Prod_Prop!$G:$G=$U45,Prod_Prop!$E:$E=V$1)),""Check""))=0),"""",IFERROR(unique(filter(Prod_Prop!$H:$H,Prod_Prop!$G:$G=$U45,Prod_Prop!$E:$E=V$1)),""""))"),"Longitud") -> Longitud | W45: =IF(V45="","",SUMIFS(Prod_Prop!$J:$J,Prod_Prop!$B:$B,$Q45,Prod_Prop!$H:$H,V45,Prod_Prop!$I:$I,W$1)*IF(V45="Peso",$R45,1)) -> 4.55 | X45: =IF(V45="","",SUMIFS(Prod_Prop!$J:$J,Prod_Prop!$B:$B,$Q45,Prod_Prop!$H:$H,V45,Prod_Prop!$I:$I,X$1)*IF(V45="Peso",$R45,1)) -> 4.75 | Y45: =IFERROR(__xludf.DUMMYFUNCTION("IF(OR($U45="""",COUNTIF($I:$I,IFERROR(unique(filter(Prod_Prop!$H:$H,Prod_Prop!$G:$G=$U45,Prod_Prop!$E:$E=Y$1)),""Check""))=0),"""",IFERROR(unique(filter(Prod_Prop!$H:$H,Prod_Prop!$G:$G=$U45,Prod_Prop!$E:$E=Y$1)),""""))"),"") | Z45: =IF(Y45="","",SUMIFS(Prod_Prop!$J:$J,Prod_Prop!$B:$B,$Q45,Prod_Prop!$H:$H,Y45,Prod_Prop!$I:$I,Z$1)*IF(Y45="Peso",$R45,1)) | AA45: =IF(Y45="","",SUMIFS(Prod_Prop!$J:$J,Prod_Prop!$B:$B,$Q45,Prod_Prop!$H:$H,Y45,Prod_Prop!$I:$I,AA$1)*IF(Y45="Peso",$R45,1)) | AB45: =IFERROR(__xludf.DUMMYFUNCTION("IF(OR($U45="""",COUNTIF($I:$I,IFERROR(unique(filter(Prod_Prop!$H:$H,Prod_Prop!$G:$G=$U45,Prod_Prop!$E:$E=AB$1)),""Check""))=0),"""",IFERROR(unique(filter(Prod_Prop!$H:$H,Prod_Prop!$G:$G=$U45,Prod_Prop!$E:$E=AB$1)),""""))"),"") | AC45: =IF(AB45="","",SUMIFS(Prod_Prop!$J:$J,Prod_Prop!$B:$B,$Q45,Prod_Prop!$H:$H,AB45,Prod_Prop!$I:$I,AC$1)*IF(AB45="Peso",$R45,1)) | AD45: =IF(AB45="","",SUMIFS(Prod_Prop!$J:$J,Prod_Prop!$B:$B,$Q45,Prod_Prop!$H:$H,AB45,Prod_Prop!$I:$I,AD$1)*IF(AB45="Peso",$R45,1))
A46: {=IF(COUNTIF(A$1:A45,Cotizador!F$2)=maxifs(Familias!E:E,Familias!D:D,Cotizador!F$2),IF(COUNTIF(A$1:A45,XLOOKUP(Cotizador!F$2,Implementos!B:B,Implementos!C:C,"",0,1))=SUMIFS(Implementos!D:D,Implementos!B:B,Cotizador!F$2,Implementos!C:C,XLOOKUP(Cotizador!F$2,Implementos!B:B,Implementos!C:C,"",0,1)),"",XLOOKUP(Cotizador!F$2,Implementos!B:B,Implementos!C:C,"",0,1)),Cotizador!F$2)} | B46: =IF(A46="","",COUNTIF(A$1:A46,A46)) | C46: {=IF(B46="","",IF(A46=XLOOKUP(A$2,Implementos!B:B,Implementos!C:C,"",0,1),B46+maxifs(B$1:B45,A$1:A45,A$2),B46))} | D46: =IF(B46="","", COUNTIFS(Productos!F:F,A46,Productos!H:H,B46)+IF(F46="SI",0,1)) | E46: =IFERROR(__xludf.DUMMYFUNCTION("IF($B46="""","""",INDEX(filter(Familias!F:F,Familias!$D:$D=$A46,Familias!$E:$E=$B46),1))"),"") | F46: =IFERROR(__xludf.DUMMYFUNCTION("IF($B46="""","""",INDEX(filter(Familias!G:G,Familias!$D:$D=$A46,Familias!$E:$E=$B46),1))"),"") | G46: {=IF(C46=1,XLOOKUP(C46,Cotizador!D:D,Cotizador!E:E,"",0,1),"")} | J46: =IF(I46="","",SUMIF(Cotizador!I$1:V$1,I46,Cotizador!I$2:V$2)) | L46: {=IF(COUNTIF(L$1:L45,A$2)=SUMIF(A:A,A$2,D:D),IF(COUNTIF(L$1:L45,XLOOKUP(A$2,Implementos!B:B,Implementos!C:C,"",0,1))=SUMIF(A:A,XLOOKUP(A$2,Implementos!B:B,Implementos!C:C,"",0,1),D:D),"",XLOOKUP(A$2,Implementos!B:B,Implementos!C:C,"",0,1)),A$2)} -> Acoplados Rurales | M46: =IF(L46="","",max(M$1:M45)+1) -> 45 | N46: =IF(L46="","",IF(N45="Orden",1,IF(COUNTIFS(N$1:N45,N45,L$1:L45,L46)=SUMIFS(D:D,B:B,N45,A:A,L46),IF(N45=maxifs(B:B,A:A,L46),"",maxifs(N$1:N45,L$1:L45,L46)+1),N45))) -> 3 | O46: =IF(N46="","",SUMIFS(C:C,B:B,N46,A:A,L46)) -> 3 | P46: =IF(N46="","",COUNTIFS(N$1:N46,N46,L$1:L46,L46)) -> 6 | Q46: =IF(U46="","",SUMIF(Productos!E:E,U46,Productos!A:A)) -> 77 | R46: {=IF(L46="","", max(1,SUMIF(I:I,XLOOKUP(U46,Productos!E:E,Productos!G:G,"",0,1),J:J)))} -> 1 | S46: =IF(Q46="","",IF(SUMIFS(Compat_Vetado!D:D,Compat_Vetado!B:B,SUM(G:G),Compat_Vetado!C:C,Q46)=1,"SI",IF(OR(SUMIF(Cotizador!E:E,Q46,Cotizador!G:G)>0,SUMIFS(Compat_Vetado!D:D,Compat_Vetado!B:B,SUM(G:G),Compat_Vetado!C:C,Q46)=-1),"NO",""))) | T46: =IF(Q46="","",IF(S46="SI","x",IF(S46="NO","",IF(AND(OR(V46="",AND(W46<=SUMIF(I:I,V46,J:J),SUMIF(I:I,V46,J:J)<=X46)),OR(Y46="",AND(Z46<=SUMIF(I:I,Y46,J:J),SUMIF(I:I,Y46,J:J)<=AA46)),OR(AB46="",AND(AC46<=SUMIF(I:I,AB46,J:J),SUMIF(I:I,AB46,J:J)<=AD46))),"x","")))) | U46: =IFERROR(__xludf.DUMMYFUNCTION("IF(P46="""","""",IFERROR(INDEX(filter(Productos!E:E,Productos!F:F=L46,Productos!H:H=N46),P46),IF(M46=SUM(D:D),""Finalizar"",""-"")))"),"Chasis Acoplado 2 Ejes L4750 Reforzado") -> Chasis Acoplado 2 Ejes L4750 Reforzado | V46: =IFERROR(__xludf.DUMMYFUNCTION("IF(OR($U46="""",COUNTIF($I:$I,IFERROR(unique(filter(Prod_Prop!$H:$H,Prod_Prop!$G:$G=$U46,Prod_Prop!$E:$E=V$1)),""Check""))=0),"""",IFERROR(unique(filter(Prod_Prop!$H:$H,Prod_Prop!$G:$G=$U46,Prod_Prop!$E:$E=V$1)),""""))"),"Longitud") -> Longitud | W46: =IF(V46="","",SUMIFS(Prod_Prop!$J:$J,Prod_Prop!$B:$B,$Q46,Prod_Prop!$H:$H,V46,Prod_Prop!$I:$I,W$1)*IF(V46="Peso",$R46,1)) -> 4.55 | X46: =IF(V46="","",SUMIFS(Prod_Prop!$J:$J,Prod_Prop!$B:$B,$Q46,Prod_Prop!$H:$H,V46,Prod_Prop!$I:$I,X$1)*IF(V46="Peso",$R46,1)) -> 4.75 | Y46: =IFERROR(__xludf.DUMMYFUNCTION("IF(OR($U46="""",COUNTIF($I:$I,IFERROR(unique(filter(Prod_Prop!$H:$H,Prod_Prop!$G:$G=$U46,Prod_Prop!$E:$E=Y$1)),""Check""))=0),"""",IFERROR(unique(filter(Prod_Prop!$H:$H,Prod_Prop!$G:$G=$U46,Prod_Prop!$E:$E=Y$1)),""""))"),"") | Z46: =IF(Y46="","",SUMIFS(Prod_Prop!$J:$J,Prod_Prop!$B:$B,$Q46,Prod_Prop!$H:$H,Y46,Prod_Prop!$I:$I,Z$1)*IF(Y46="Peso",$R46,1)) | AA46: =IF(Y46="","",SUMIFS(Prod_Prop!$J:$J,Prod_Prop!$B:$B,$Q46,Prod_Prop!$H:$H,Y46,Prod_Prop!$I:$I,AA$1)*IF(Y46="Peso",$R46,1)) | AB46: =IFERROR(__xludf.DUMMYFUNCTION("IF(OR($U46="""",COUNTIF($I:$I,IFERROR(unique(filter(Prod_Prop!$H:$H,Prod_Prop!$G:$G=$U46,Prod_Prop!$E:$E=AB$1)),""Check""))=0),"""",IFERROR(unique(filter(Prod_Prop!$H:$H,Prod_Prop!$G:$G=$U46,Prod_Prop!$E:$E=AB$1)),""""))"),"") | AC46: =IF(AB46="","",SUMIFS(Prod_Prop!$J:$J,Prod_Prop!$B:$B,$Q46,Prod_Prop!$H:$H,AB46,Prod_Prop!$I:$I,AC$1)*IF(AB46="Peso",$R46,1)) | AD46: =IF(AB46="","",SUMIFS(Prod_Prop!$J:$J,Prod_Prop!$B:$B,$Q46,Prod_Prop!$H:$H,AB46,Prod_Prop!$I:$I,AD$1)*IF(AB46="Peso",$R46,1))
A47: {=IF(COUNTIF(A$1:A46,Cotizador!F$2)=maxifs(Familias!E:E,Familias!D:D,Cotizador!F$2),IF(COUNTIF(A$1:A46,XLOOKUP(Cotizador!F$2,Implementos!B:B,Implementos!C:C,"",0,1))=SUMIFS(Implementos!D:D,Implementos!B:B,Cotizador!F$2,Implementos!C:C,XLOOKUP(Cotizador!F$2,Implementos!B:B,Implementos!C:C,"",0,1)),"",XLOOKUP(Cotizador!F$2,Implementos!B:B,Implementos!C:C,"",0,1)),Cotizador!F$2)} | B47: =IF(A47="","",COUNTIF(A$1:A47,A47)) | C47: {=IF(B47="","",IF(A47=XLOOKUP(A$2,Implementos!B:B,Implementos!C:C,"",0,1),B47+maxifs(B$1:B46,A$1:A46,A$2),B47))} | D47: =IF(B47="","", COUNTIFS(Productos!F:F,A47,Productos!H:H,B47)+IF(F47="SI",0,1)) | E47: =IFERROR(__xludf.DUMMYFUNCTION("IF($B47="""","""",INDEX(filter(Familias!F:F,Familias!$D:$D=$A47,Familias!$E:$E=$B47),1))"),"") | F47: =IFERROR(__xludf.DUMMYFUNCTION("IF($B47="""","""",INDEX(filter(Familias!G:G,Familias!$D:$D=$A47,Familias!$E:$E=$B47),1))"),"") | G47: {=IF(C47=1,XLOOKUP(C47,Cotizador!D:D,Cotizador!E:E,"",0,1),"")} | J47: =IF(I47="","",SUMIF(Cotizador!I$1:V$1,I47,Cotizador!I$2:V$2)) | L47: {=IF(COUNTIF(L$1:L46,A$2)=SUMIF(A:A,A$2,D:D),IF(COUNTIF(L$1:L46,XLOOKUP(A$2,Implementos!B:B,Implementos!C:C,"",0,1))=SUMIF(A:A,XLOOKUP(A$2,Implementos!B:B,Implementos!C:C,"",0,1),D:D),"",XLOOKUP(A$2,Implementos!B:B,Implementos!C:C,"",0,1)),A$2)} -> Acoplados Rurales | M47: =IF(L47="","",max(M$1:M46)+1) -> 46 | N47: =IF(L47="","",IF(N46="Orden",1,IF(COUNTIFS(N$1:N46,N46,L$1:L46,L47)=SUMIFS(D:D,B:B,N46,A:A,L47),IF(N46=maxifs(B:B,A:A,L47),"",maxifs(N$1:N46,L$1:L46,L47)+1),N46))) -> 3 | O47: =IF(N47="","",SUMIFS(C:C,B:B,N47,A:A,L47)) -> 3 | P47: =IF(N47="","",COUNTIFS(N$1:N47,N47,L$1:L47,L47)) -> 7 | Q47: =IF(U47="","",SUMIF(Productos!E:E,U47,Productos!A:A)) -> 78 | R47: {=IF(L47="","", max(1,SUMIF(I:I,XLOOKUP(U47,Productos!E:E,Productos!G:G,"",0,1),J:J)))} -> 1 | S47: =IF(Q47="","",IF(SUMIFS(Compat_Vetado!D:D,Compat_Vetado!B:B,SUM(G:G),Compat_Vetado!C:C,Q47)=1,"SI",IF(OR(SUMIF(Cotizador!E:E,Q47,Cotizador!G:G)>0,SUMIFS(Compat_Vetado!D:D,Compat_Vetado!B:B,SUM(G:G),Compat_Vetado!C:C,Q47)=-1),"NO",""))) | T47: =IF(Q47="","",IF(S47="SI","x",IF(S47="NO","",IF(AND(OR(V47="",AND(W47<=SUMIF(I:I,V47,J:J),SUMIF(I:I,V47,J:J)<=X47)),OR(Y47="",AND(Z47<=SUMIF(I:I,Y47,J:J),SUMIF(I:I,Y47,J:J)<=AA47)),OR(AB47="",AND(AC47<=SUMIF(I:I,AB47,J:J),SUMIF(I:I,AB47,J:J)<=AD47))),"x","")))) | U47: =IFERROR(__xludf.DUMMYFUNCTION("IF(P47="""","""",IFERROR(INDEX(filter(Productos!E:E,Productos!F:F=L47,Productos!H:H=N47),P47),IF(M47=SUM(D:D),""Finalizar"",""-"")))"),"Chasis Acoplado 2 Ejes L4750 Reforzado R. Camion") -> Chasis Acoplado 2 Ejes L4750 Reforzado R. Camion | V47: =IFERROR(__xludf.DUMMYFUNCTION("IF(OR($U47="""",COUNTIF($I:$I,IFERROR(unique(filter(Prod_Prop!$H:$H,Prod_Prop!$G:$G=$U47,Prod_Prop!$E:$E=V$1)),""Check""))=0),"""",IFERROR(unique(filter(Prod_Prop!$H:$H,Prod_Prop!$G:$G=$U47,Prod_Prop!$E:$E=V$1)),""""))"),"Longitud") -> Longitud | W47: =IF(V47="","",SUMIFS(Prod_Prop!$J:$J,Prod_Prop!$B:$B,$Q47,Prod_Prop!$H:$H,V47,Prod_Prop!$I:$I,W$1)*IF(V47="Peso",$R47,1)) -> 4.55 | X47: =IF(V47="","",SUMIFS(Prod_Prop!$J:$J,Prod_Prop!$B:$B,$Q47,Prod_Prop!$H:$H,V47,Prod_Prop!$I:$I,X$1)*IF(V47="Peso",$R47,1)) -> 4.75 | Y47: =IFERROR(__xludf.DUMMYFUNCTION("IF(OR($U47="""",COUNTIF($I:$I,IFERROR(unique(filter(Prod_Prop!$H:$H,Prod_Prop!$G:$G=$U47,Prod_Prop!$E:$E=Y$1)),""Check""))=0),"""",IFERROR(unique(filter(Prod_Prop!$H:$H,Prod_Prop!$G:$G=$U47,Prod_Prop!$E:$E=Y$1)),""""))"),"") | Z47: =IF(Y47="","",SUMIFS(Prod_Prop!$J:$J,Prod_Prop!$B:$B,$Q47,Prod_Prop!$H:$H,Y47,Prod_Prop!$I:$I,Z$1)*IF(Y47="Peso",$R47,1)) | AA47: =IF(Y47="","",SUMIFS(Prod_Prop!$J:$J,Prod_Prop!$B:$B,$Q47,Prod_Prop!$H:$H,Y47,Prod_Prop!$I:$I,AA$1)*IF(Y47="Peso",$R47,1)) | AB47: =IFERROR(__xludf.DUMMYFUNCTION("IF(OR($U47="""",COUNTIF($I:$I,IFERROR(unique(filter(Prod_Prop!$H:$H,Prod_Prop!$G:$G=$U47,Prod_Prop!$E:$E=AB$1)),""Check""))=0),"""",IFERROR(unique(filter(Prod_Prop!$H:$H,Prod_Prop!$G:$G=$U47,Prod_Prop!$E:$E=AB$1)),""""))"),"") | AC47: =IF(AB47="","",SUMIFS(Prod_Prop!$J:$J,Prod_Prop!$B:$B,$Q47,Prod_Prop!$H:$H,AB47,Prod_Prop!$I:$I,AC$1)*IF(AB47="Peso",$R47,1)) | AD47: =IF(AB47="","",SUMIFS(Prod_Prop!$J:$J,Prod_Prop!$B:$B,$Q47,Prod_Prop!$H:$H,AB47,Prod_Prop!$I:$I,AD$1)*IF(AB47="Peso",$R47,1))
A48: {=IF(COUNTIF(A$1:A47,Cotizador!F$2)=maxifs(Familias!E:E,Familias!D:D,Cotizador!F$2),IF(COUNTIF(A$1:A47,XLOOKUP(Cotizador!F$2,Implementos!B:B,Implementos!C:C,"",0,1))=SUMIFS(Implementos!D:D,Implementos!B:B,Cotizador!F$2,Implementos!C:C,XLOOKUP(Cotizador!F$2,Implementos!B:B,Implementos!C:C,"",0,1)),"",XLOOKUP(Cotizador!F$2,Implementos!B:B,Implementos!C:C,"",0,1)),Cotizador!F$2)} | B48: =IF(A48="","",COUNTIF(A$1:A48,A48)) | C48: {=IF(B48="","",IF(A48=XLOOKUP(A$2,Implementos!B:B,Implementos!C:C,"",0,1),B48+maxifs(B$1:B47,A$1:A47,A$2),B48))} | D48: =IF(B48="","", COUNTIFS(Productos!F:F,A48,Productos!H:H,B48)+IF(F48="SI",0,1)) | E48: =IFERROR(__xludf.DUMMYFUNCTION("IF($B48="""","""",INDEX(filter(Familias!F:F,Familias!$D:$D=$A48,Familias!$E:$E=$B48),1))"),"") | F48: =IFERROR(__xludf.DUMMYFUNCTION("IF($B48="""","""",INDEX(filter(Familias!G:G,Familias!$D:$D=$A48,Familias!$E:$E=$B48),1))"),"") | G48: {=IF(C48=1,XLOOKUP(C48,Cotizador!D:D,Cotizador!E:E,"",0,1),"")} | J48: =IF(I48="","",SUMIF(Cotizador!I$1:V$1,I48,Cotizador!I$2:V$2)) | L48: {=IF(COUNTIF(L$1:L47,A$2)=SUMIF(A:A,A$2,D:D),IF(COUNTIF(L$1:L47,XLOOKUP(A$2,Implementos!B:B,Implementos!C:C,"",0,1))=SUMIF(A:A,XLOOKUP(A$2,Implementos!B:B,Implementos!C:C,"",0,1),D:D),"",XLOOKUP(A$2,Implementos!B:B,Implementos!C:C,"",0,1)),A$2)} -> Acoplados Rurales | M48: =IF(L48="","",max(M$1:M47)+1) -> 47 | N48: =IF(L48="","",IF(N47="Orden",1,IF(COUNTIFS(N$1:N47,N47,L$1:L47,L48)=SUMIFS(D:D,B:B,N47,A:A,L48),IF(N47=maxifs(B:B,A:A,L48),"",maxifs(N$1:N47,L$1:L47,L48)+1),N47))) -> 3 | O48: =IF(N48="","",SUMIFS(C:C,B:B,N48,A:A,L48)) -> 3 | P48: =IF(N48="","",COUNTIFS(N$1:N48,N48,L$1:L48,L48)) -> 8 | Q48: =IF(U48="","",SUMIF(Productos!E:E,U48,Productos!A:A)) -> 79 | R48: {=IF(L48="","", max(1,SUMIF(I:I,XLOOKUP(U48,Productos!E:E,Productos!G:G,"",0,1),J:J)))} -> 1 | S48: =IF(Q48="","",IF(SUMIFS(Compat_Vetado!D:D,Compat_Vetado!B:B,SUM(G:G),Compat_Vetado!C:C,Q48)=1,"SI",IF(OR(SUMIF(Cotizador!E:E,Q48,Cotizador!G:G)>0,SUMIFS(Compat_Vetado!D:D,Compat_Vetado!B:B,SUM(G:G),Compat_Vetado!C:C,Q48)=-1),"NO",""))) | T48: =IF(Q48="","",IF(S48="SI","x",IF(S48="NO","",IF(AND(OR(V48="",AND(W48<=SUMIF(I:I,V48,J:J),SUMIF(I:I,V48,J:J)<=X48)),OR(Y48="",AND(Z48<=SUMIF(I:I,Y48,J:J),SUMIF(I:I,Y48,J:J)<=AA48)),OR(AB48="",AND(AC48<=SUMIF(I:I,AB48,J:J),SUMIF(I:I,AB48,J:J)<=AD48))),"x","")))) -> x | U48: =IFERROR(__xludf.DUMMYFUNCTION("IF(P48="""","""",IFERROR(INDEX(filter(Productos!E:E,Productos!F:F=L48,Productos!H:H=N48),P48),IF(M48=SUM(D:D),""Finalizar"",""-"")))"),"Chasis Acoplado 2 Ejes L5000") -> Chasis Acoplado 2 Ejes L5000 | V48: =IFERROR(__xludf.DUMMYFUNCTION("IF(OR($U48="""",COUNTIF($I:$I,IFERROR(unique(filter(Prod_Prop!$H:$H,Prod_Prop!$G:$G=$U48,Prod_Prop!$E:$E=V$1)),""Check""))=0),"""",IFERROR(unique(filter(Prod_Prop!$H:$H,Prod_Prop!$G:$G=$U48,Prod_Prop!$E:$E=V$1)),""""))"),"Longitud") -> Longitud | W48: =IF(V48="","",SUMIFS(Prod_Prop!$J:$J,Prod_Prop!$B:$B,$Q48,Prod_Prop!$H:$H,V48,Prod_Prop!$I:$I,W$1)*IF(V48="Peso",$R48,1)) -> 4.8 | X48: =IF(V48="","",SUMIFS(Prod_Prop!$J:$J,Prod_Prop!$B:$B,$Q48,Prod_Prop!$H:$H,V48,Prod_Prop!$I:$I,X$1)*IF(V48="Peso",$R48,1)) -> 5 | Y48: =IFERROR(__xludf.DUMMYFUNCTION("IF(OR($U48="""",COUNTIF($I:$I,IFERROR(unique(filter(Prod_Prop!$H:$H,Prod_Prop!$G:$G=$U48,Prod_Prop!$E:$E=Y$1)),""Check""))=0),"""",IFERROR(unique(filter(Prod_Prop!$H:$H,Prod_Prop!$G:$G=$U48,Prod_Prop!$E:$E=Y$1)),""""))"),"") | Z48: =IF(Y48="","",SUMIFS(Prod_Prop!$J:$J,Prod_Prop!$B:$B,$Q48,Prod_Prop!$H:$H,Y48,Prod_Prop!$I:$I,Z$1)*IF(Y48="Peso",$R48,1)) | AA48: =IF(Y48="","",SUMIFS(Prod_Prop!$J:$J,Prod_Prop!$B:$B,$Q48,Prod_Prop!$H:$H,Y48,Prod_Prop!$I:$I,AA$1)*IF(Y48="Peso",$R48,1)) | AB48: =IFERROR(__xludf.DUMMYFUNCTION("IF(OR($U48="""",COUNTIF($I:$I,IFERROR(unique(filter(Prod_Prop!$H:$H,Prod_Prop!$G:$G=$U48,Prod_Prop!$E:$E=AB$1)),""Check""))=0),"""",IFERROR(unique(filter(Prod_Prop!$H:$H,Prod_Prop!$G:$G=$U48,Prod_Prop!$E:$E=AB$1)),""""))"),"") | AC48: =IF(AB48="","",SUMIFS(Prod_Prop!$J:$J,Prod_Prop!$B:$B,$Q48,Prod_Prop!$H:$H,AB48,Prod_Prop!$I:$I,AC$1)*IF(AB48="Peso",$R48,1)) | AD48: =IF(AB48="","",SUMIFS(Prod_Prop!$J:$J,Prod_Prop!$B:$B,$Q48,Prod_Prop!$H:$H,AB48,Prod_Prop!$I:$I,AD$1)*IF(AB48="Peso",$R48,1))
